Workbook
Name Additional_Instance: 'Static Reference Tables'!$H$11:$H$13
Name administrator_vsphere_local_password: 'Value Reference Tables'!$L$14
Name air_GPU_network_operator_namespace: 'Value Reference Tables'!$U$43
Name air_GPU_operator_namespace: 'Value Reference Tables'!$U$42
Name air_GPU_VM_class: 'Value Reference Tables'!$U$41
Name air_license: 'Value Reference Tables'!$U$40
Name asn_instance: 'Value Reference Tables - MR'!$AH$18
Name asn_mgmt_az1: 'Value Reference Tables - MR'!$AH$19
Name asn_mgmt_az2: 'Value Reference Tables - MR'!$AH$20
Name asn_start: 'Value Reference Tables - MR'!$AH$17
Name asn_wld_az1: 'Value Reference Tables - MR'!$AH$21
Name asn_wld_az2: 'Value Reference Tables - MR'!$AH$22
Name avilb_root_password: 'Value Reference Tables'!$L$32
Name aws_regions: 'Static Reference Tables'!$B$386:$B$413
Name ca_administrator_password: 'Value Reference Tables'!$L$31
Name ca_administrator_username: 'Value Reference Tables'!$L$8
Name ca_algorithm: 'Value Reference Tables'!$O$39
Name ca_country: 'Value Reference Tables'!$O$38
Name ca_email_address: 'Value Reference Tables'!$O$41
Name ca_key_size: 'Value Reference Tables'!$O$40
Name ca_locality: 'Value Reference Tables'!$O$42
Name ca_organization: 'Value Reference Tables'!$O$43
Name ca_organization_unit: 'Value Reference Tables'!$O$44
Name ca_state: 'Value Reference Tables'!$O$45
Name ca_template_name: 'Value Reference Tables'!$O$37
Name calculated_mgmt_host_count: #REF!
Name cbr_aria_logs_key: 'Value Reference Tables'!$U$149
Name cbr_aria_logs_url: 'Value Reference Tables'!$U$148
Name cbr_firewall_rule_vcenter: 'Value Reference Tables'!$U$134
Name cbr_recovery_host_count: 'Value Reference Tables'!$U$130
Name cbr_recovery_host_type: 'Value Reference Tables'!$U$129
Name cbr_recovery_management_subnet: 'Value Reference Tables'!$U$133
Name cbr_recovery_region: 'Value Reference Tables'!$U$128
Name cbr_recovery_sddc_name: 'Value Reference Tables'!$U$127
Name cbr_recovery_subnet: 'Value Reference Tables'!$U$132
Name cbr_recovery_vpc: 'Value Reference Tables'!$U$131
Name cbr_vcdr_anti_affinity: 'Value Reference Tables'!$U$145
Name cbr_vcdr_cdp1_hostname: 'Value Reference Tables'!$U$137
Name cbr_vcdr_cdp1_ip: 'Value Reference Tables'!$U$138
Name cbr_vcdr_cdp2_hostname: 'Value Reference Tables'!$U$139
Name cbr_vcdr_cdp2_ip: 'Value Reference Tables'!$U$140
Name cbr_vcdr_email_recipient: 'Value Reference Tables'!$U$146
Name cbr_vcdr_email_sender: 'Value Reference Tables'!$U$147
Name cbr_vcdr_label: 'Value Reference Tables'!$U$144
Name cbr_vcdr_orchestrator_fqdn: 'Value Reference Tables'!$U$142
Name cbr_vcdr_ova: 'Value Reference Tables'!$U$141
Name cbr_vcdr_passcode: 'Value Reference Tables'!$U$143
Name cbr_vcdr_site_name: 'Value Reference Tables'!$U$135
Name cbr_vcdr_timezone: 'Value Reference Tables'!$U$136
Name cbr_vcdr_vsphere_role: 'Value Reference Tables'!$U$123
Name cbr_vm_folder: 'Value Reference Tables'!$U$126
Name ccm_aws_admin_password: 'Value Reference Tables'!$U$180
Name ccm_aws_admin_ssouser: 'Value Reference Tables'!$U$179
Name ccm_aws_host_count: 'Value Reference Tables'!$U$164
Name ccm_aws_host_type: 'Value Reference Tables'!$U$163
Name ccm_aws_management_subnet: 'Value Reference Tables'!$U$167
Name ccm_aws_region: 'Value Reference Tables'!$U$162
Name ccm_aws_sddc_name: 'Value Reference Tables'!$U$161
Name ccm_aws_subnet: 'Value Reference Tables'!$U$166
Name ccm_aws_vpc: 'Value Reference Tables'!$U$165

Sheet CPUs
A1: CPU Series | B1: Cores/Threads | C1: CPUID Info | D1: CPUIDs | E1: Supported Releases
A2: AMD EPYC 7001 Series | B2: 32c/64t | C2: 17.01 | D2: 0x00800F10 | E2: ESXi 9.1
A3: AMD EPYC 7002/7Fx2/7Hx2 Series | B3: 64c/128t | C3: 17.31 | D3: 0x00830F10 | E3: ESXi 9.1
A4: AMD EPYC 7003/7003X Series | B4: 64C/128T | C4: 19.01 | D4: 0x00A00F11,0x00A00F12 | E4: ESXi 9.1
A5: AMD EPYC 8004 Series | B5: 64c/128t | C5: 19.A0 | D5: 0x00A10F11,0x00AA0F02 | E5: ESXi 9.1
A6: AMD EPYC 9004 Series | B6: 128c/256t | C6: 19.11 19.A0 | D6: 0x00A10F11,0x00A10F12,0x00AA0F02 | E6: ESXi 9.1
A7: AMD EPYC 9005 Series | B7: 192c/384t | C7: 1A.2 1A.11 | D7: 0x00B00F21,0x00B10F10 | E7: ESXi 9.1
A8: AMD Ryzen Embedded V1000 Series | B8: 4c/8t | C8: 17.11 | D8: 0x00810F10 | E8: ESXi 9.1
A9: Intel Atom C3000 Series | B9: 16c/16t | C9: 6.5F | D9: 0x000506F0 | E9: ESXi 9.1
A10: Intel Core i3/i5/i7-1100GRE Processor Series | C10: 6.8C 6.8D | D10: 0x000806C1,0x000806C2 | E10: ESXi 9.1
A11: Intel Xeon 6500P/6700P (Granite Rapids-SP) Series | B11: 86c/172t | C11: 6.AD.1 | D11: 0x000A06D1 | E11: ESXi 9.1
A12: Intel Xeon 6900P (Granite Rapids-AP) Series | C12: 6 AD 1 | D12: 0x000A06D1 | E12: ESXi 9.1
A13: Intel Xeon CPU Max 9400 (Sapphire-Rapids-HBM) Series | B13: 56c/112t | C13: 6.8F.8 | D13: 0x000806F8 | E13: ESXi 9.1
A14: Intel Xeon D-1700 (Ice-Lake-D) Series | B14: 20c/40t | C14: 6.6C.1 | D14: 0x000606C1 | E14: ESXi 9.1
A15: Intel Xeon D-2700 (Ice-Lake-D) Series | B15: 20c/40t | C15: 6.6C.1 | D15: 0x000606C1 | E15: ESXi 9.1
A16: Intel Xeon E-2100 Series | B16: 6c/112t | C16: 6.9E.A | D16: 0x000906EA,0x000906EB,0x000906EC | E16: ESXi 9.1
A17: Intel Xeon E-2200 (4 or 6-core) Series | B17: 6c/12t | C17: 6.9E.A | D17: 0x000906EA | E17: ESXi 9.1
A18: Intel Xeon E-2200 (8-core) Series | B18: 8c/16t | C18: 6.9E.D | D18: 0x000906ED | E18: ESXi 9.1
A19: Intel Xeon E-2300 Series | B19: 8c/16t | C19: 6.A7.1 | D19: 0x000A0671 | E19: ESXi 9.1
A20: Intel Xeon E-2400/Xeon 6300 Series | B20: 12c/24t | C20: 6.B7.1 | D20: 0x000B0671 | E20: ESXi 9.1
A21: Intel Xeon Gold 6200/5200 (Cascade-Lake-SP/Refresh) Series | B21: 28c/56t | C21: 6.55.7 | D21: 0x00050657 | E21: ESXi 9.1
A22: Intel Xeon Gold 6300/5300 (Cooper-Lake-SP) Series | B22: 28c/56t | C22: 6.55.B | D22: 0x0005065B | E22: ESXi 9.1
A23: Intel Xeon Gold 6300/5300 (Ice-Lake-SP) Series | B23: 32c/64t | C23: 6.6A.6 | D23: 0x000606A6 | E23: ESXi 9.1
A24: Intel Xeon Gold 6400/5400 (Sapphire-Rapids-SP) Series | B24: 60c/120t | C24: 6.8F.8 | D24: 0x000806F8 | E24: ESXi 9.1
... A36: Intel Xeon W-11000 Processor Series | B36: 8c/16t | C36: 6.8C 6.8D | D36: 0x000806C1,0x000806C2,0x000806D1 | E36: ESXi 9.1

Sheet GuestOS
A1: OS Vendors | B1: OS Release | C1: OS Arch | D1: Supported Releases | E1: Support Level
A2: AlmaLinux OS Foundation | B2: AlmaLinux OS 8.x | C2: x86(64-bit) | D2: ESXi 9.1 | E2: Supported
A3: AlmaLinux OS Foundation | B3: AlmaLinux OS 10.x | C3: x86(64-bit) | D3: ESXi 9.1 | E3: Supported
A4: AlmaLinux OS Foundation | B4: AlmaLinux OS 9.x | C4: x86(64-bit) | D4: ESXi 9.1 | E4: Supported
A5: Asianux | B5: Asianux 4.0 | C5: x86(32-bit) | D5: ESXi 9.1 | E5: Deprecated
A6: Asianux | B6: Asianux 7.0 | C6: x86(64-bit) | D6: ESXi 9.1 | E6: Legacy
A7: Asianux | B7: Asianux 4.0 | C7: x86(64-bit) | D7: ESXi 9.1 | E7: Deprecated
A8: Canonical Ltd | B8: Ubuntu 14.04 LTS | C8: x86(64-bit) | D8: ESXi 9.1 | E8: Legacy
A9: Canonical Ltd | B9: Ubuntu 25.04 | C9: x86(64-bit) | D9: ESXi 9.1 | E9: Legacy
A10: Canonical Ltd | B10: Ubuntu 25.10 | C10: x86(64-bit) | D10: ESXi 9.1 | E10: Supported
A11: Canonical Ltd | B11: Ubuntu 16.04 LTS | C11: x86(64-bit) | D11: ESXi 9.1 | E11: Supported
A12: Canonical Ltd | B12: Ubuntu 14.04 LTS | C12: x86(32-bit) | D12: ESXi 9.1 | E12: Legacy
... A130: xFusion Digital Technologies Co. Ltd | B130: FusionOS 22 | C130: x86(64-bit) | D130: ESXi 9.1 | E130: Supported

Sheet IODevices
A1: Brand Name | B1: Model | C1: Device Type | D1: Supported Releases | E1: _
A2: Adaptec | B2: Adaptec SmartRAID 3100 | C2: SAS-RAID | D2: ESXi 9.1 ESXi 9.0
A3: Adaptec | B3: Adaptec SmartRAID 3162-8i | C3: SAS-RAID | D3: ESXi 9.1 ESXi 9.0
A4: Adaptec | B4: Adaptec SmartHBA 2100-8i | C4: SAS-RAID | D4: ESXi 9.1 ESXi 9.0
A5: Adaptec | B5: Adaptec SmartHBA 2100-4i | C5: SAS-RAID | D5: ESXi 9.1 ESXi 9.0
A6: Adaptec | B6: Adaptec HBA 1100-8i | C6: SAS | D6: ESXi 9.1 ESXi 9.0
A7: Adaptec | B7: Adaptec HBA 1100-4i | C7: SAS | D7: ESXi 9.1 ESXi 9.0
A8: Adaptec | B8: Adaptec SmartHBA 2100-8e | C8: SAS-RAID | D8: ESXi 9.1 ESXi 9.0
A9: Adaptec | B9: Adaptec HBA 1100-8e | C9: SAS | D9: ESXi 9.1 ESXi 9.0
A10: Adaptec | B10: Adaptec SmartHBA 2100-4i4e | C10: SAS-RAID | D10: ESXi 9.1 ESXi 9.0
A11: Adaptec | B11: Adaptec HBA 1100 | C11: SAS | D11: ESXi 9.1 ESXi 9.0
A12: Adaptec | B12: Adaptec SmartHBA 2100 | C12: SAS-RAID | D12: ESXi 9.1 ESXi 9.0
A13: Adaptec | B13: Adaptec SmartHBA 2100A-8i | C13: SAS-RAID | D13: ESXi 9.1 ESXi 9.0
... A259: Broadcom | B259: MegaRAID SAS 9480-8i8e /w JBOD Mode | C259: SAS-SATA-NVME Tri-mode | D259: ESXi 9.1 ESXi 9.0
A260: Broadcom | B260: BCM57417 NetXtreme-E RDMA Partition | C260: Network | D260: ESXi 9.1 ESXi 9.0 | E260: Restricted
A261: Broadcom | B261: NetXtreme-E RDMA Virtual Function | C261: Network | D261: ESXi 9.1 ESXi 9.0 | E261: Restricted
A262: Broadcom | B262: BCM57417 NetXtreme-E Ethernet Partition | C262: Network | D262: ESXi 9.1 ESXi 9.0 | E262: Restricted
A263: Broadcom | B263: BCM57311 NetXtreme-C 10Gb RDMA Ethernet Controller | C263: Network | D263: ESXi 9.1 ESXi 9.0 | E263: Restricted
A264: Broadcom | B264: BCM57312 NetXtreme-C 10Gb/25Gb RDMA Ethernet Controller | C264: Network | D264: ESXi 9.1 ESXi 9.0 | E264: Restricted
A265: Broadcom | B265: BCM57414 NetXtreme-E 10Gb/25Gb RDMA Ethernet Controller | C265: Network | D265: ESXi 9.1 ESXi 9.0 | E265: Restricted
A266: Broadcom | B266: BCM57416 NetXtreme-E 10GBASE-T RDMA Ethernet Controller | C266: Network | D266: ESXi 9.1 ESXi 9.0 | E266: Restricted
A267: Broadcom | B267: BCM57417 NetXtreme-E 10GBASE-T RDMA Ethernet Controller | C267: Network | D267: ESXi 9.1 ESXi 9.0 | E267: Restricted
A268: Broadcom | B268: BCM57414 NetXtreme-E Ethernet Virtual Function | C268: Network | D268: ESXi 9.1 ESXi 9.0 | E268: Restricted
A269: Broadcom | B269: BCM57412 Broadcom NetXtreme-E Partition | C269: Network | D269: ESXi 9.1 ESXi 9.0 | E269: Restricted
A270: Broadcom | B270: BCM57314 NetXtreme-C 10Gb/25Gb/40Gb/50Gb RDMA Ethernet Controller | C270: Network | D270: ESXi 9.1 ESXi 9.0 | E270: Restricted
A271: Broadcom | B271: BCM57317 NetXtreme-C 10GBase-T RDMA Ethernet Controller | C271: Network | D271: ESXi 9.1 ESXi 9.0 | E271: Restricted
... A283: Broadcom | B283: BCM57412 NetXtreme-E 10Gb RDMA Ethernet Controller | C283: Network | D283: ESXi 9.1 ESXi 9.0 | E283: Restricted
A284: Broadcom | B284: BCM57412 | C284: Network | D284: ESXi 9.1 ESXi 9.0
A285: Broadcom | B285: BCM57412 | C285: Network | D285: ESXi 9.1 ESXi 9.0
A286: Broadcom | B286: BCM57412 | C286: Network | D286: ESXi 9.1 ESXi 9.0
A287: Broadcom | B287: BCM57412 | C287: Network | D287: ESXi 9.1 ESXi 9.0
A288: Broadcom | B288: BCM57412 | C288: Network | D288: ESXi 9.1 ESXi 9.0
A289: Broadcom | B289: BCM57412 | C289: Network | D289: ESXi 9.1 ESXi 9.0
A290: Broadcom | B290: MegaRAID SAS 9450-8i | C290: SAS-SATA-NVME Tri-mode RAID | D290: ESXi 9.1 ESXi 9.0
A291: Broadcom | B291: BCM57416 | C291: Network | D291: ESXi 9.1 ESXi 9.0
A292: Broadcom | B292: BCM57416 | C292: Network | D292: ESXi 9.1 ESXi 9.0
A293: Broadcom | B293: BCM57416 | C293: Network | D293: ESXi 9.1 ESXi 9.0
A294: Broadcom | B294: BCM57416 | C294: Network | D294: ESXi 9.1 ESXi 9.0
A295: Broadcom | B295: BCM57416 | C295: Network | D295: ESXi 9.1 ESXi 9.0
A296: Broadcom | B296: MegaRAID SAS 9461-16i | C296: SAS-SATA-NVME Tri-mode | D296: ESXi 9.1 ESXi 9.0
A297: Broadcom | B297: BCM57454 NetXtreme-E RDMA Virtual Function | C297: Network | D297: ESXi 9.1 ESXi 9.0 | E297: Restricted
A298: Broadcom | B298: BCM57454 | C298: Network | D298: ESXi 9.1 ESXi 9.0
A299: Broadcom | B299: MegaRaid 9560-16i | C299: SAS-SATA-NVME Tri-mode | D299: ESXi 9.1 ESXi 9.0
A300: Broadcom | B300: MegaRaid 9560-8i | C300: SAS-SATA-NVME Tri-mode | D300: ESXi 9.1 ESXi 9.0
A301: Broadcom | B301: Megaraid 9580-8i8e | C301: SAS-SATA-NVME Tri-mode | D301: ESXi 9.1 ESXi 9.0
A302: Broadcom | B302: BCM57508 | C302: Network | D302: ESXi 9.1 ESXi 9.0
A303: Broadcom | B303: BCM57508 | C303: Network | D303: ESXi 9.1 ESXi 9.0
A304: Broadcom | B304: BCM57504 | C304: Network | D304: ESXi 9.1 ESXi 9.0
A305: Broadcom | B305: BCM57502 | C305: Network | D305: ESXi 9.1 ESXi 9.0
A306: Broadcom | B306: BCM57508 | C306: Network | D306: ESXi 9.1 ESXi 9.0
A307: Broadcom | B307: BCM57504 | C307: Network | D307: ESXi 9.1 ESXi 9.0
A308: Broadcom | B308: BCM57504 | C308: Network | D308: ESXi 9.1 ESXi 9.0
A309: Broadcom | B309: BCM57504 | C309: Network | D309: ESXi 9.1 ESXi 9.0
... A312: Broadcom | B312: BCM57504 | C312: Network | D312: ESXi 9.1 ESXi 9.0
A313: Broadcom | B313: BCM57454 NetXtreme-E Partition | C313: Network | D313: ESXi 9.1 ESXi 9.0 | E313: Restricted
A314: Broadcom | B314: BCM57454 NetXtreme-E RDMA Partition | C314: Network | D314: ESXi 9.1 ESXi 9.0 | E314: Restricted
A315: Broadcom | B315: NetXtreme BCM57766 Gigabit Ethernet | C315: Network | D315: ESXi 9.1 ESXi 9.0
A316: Broadcom | B316: SAS 9500-8e | C316: SAS-SATA-NVME Tri-mode | D316: ESXi 9.1 ESXi 9.0
A317: Broadcom | B317: SAS 9500-16e | C317: SAS/SATA-RAID | D317: ESXi 9.1 ESXi 9.0
A318: Broadcom | B318: SAS 9500-8i | C318: SAS-SATA-NVME Tri-mode | D318: ESXi 9.1 ESXi 9.0
A319: Broadcom | B319: SAS 9500-16i | C319: SAS-SATA-NVME Tri-mode | D319: ESXi 9.1 ESXi 9.0
A320: Broadcom | B320: SAS3416 Fusion-MPT Tri-Mode I/O Controller Chip (IOC) | C320: SAS | D320: ESXi 9.1 ESXi 9.0
A321: Broadcom | B321: SAS3508 Fusion-MPT Tri-Mode RAID On Chip (ROC) | C321: SAS | D321: ESXi 9.1 ESXi 9.0
A322: Broadcom | B322: SAS3716 Fusion-MPT Tri-Mode RAID Controller Chip (ROC) | C322: SAS | D322: ESXi 9.1 ESXi 9.0
A323: Broadcom | B323: SAS3616 Fusion-MPT Tri-Mode I/O Controller Chip (IOC) | C323: SAS | D323: ESXi 9.1 ESXi 9.0
A324: Broadcom | B324: Fusion-MPT 12G SAS/PCIe SAS39xx | C324: SAS | D324: ESXi 9.1 ESXi 9.0
A325: Broadcom | B325: Fusion-MPT 12G SAS/PCIe Secure SAS39xx | C325: SAS | D325: ESXi 9.1 ESXi 9.0
A326: Broadcom | B326: Fusion-MPT 12G SAS/PCIe SAS39xx | C326: SAS | D326: ESXi 9.1 ESXi 9.0
... A374: Broadcom | B374: NetXtreme-E-Series Dual-port 100Gb Ethernet PCIe Virtual Function | C374: Network | D374: ESXi 9.1 ESXi 9.0
A375: Broadcom | B375: NetXtreme-E NGM2100D BCM57508 2x100G KR Mezz Ethernet Virtual Function | C375: Network | D375: ESXi 9.1 ESXi 9.0 | E375: Restricted
A376: Broadcom | B376: NetXtreme E-Series Quad-port 25Gb Ethernet LOM RDMA Virtual Function | C376: Network | D376: ESXi 9.1 ESXi 9.0
A377: Broadcom | B377: NetXtreme E-Series Quad-port 25Gb SFP28 OCP 3.0 RDMA Virtual Function | C377: Network | D377: ESXi 9.1 ESXi 9.0
A378: Broadcom | B378: NetXtreme E-Series Quad-port 25Gb SFP28 PCIe RDMA Virtual Function | C378: Network | D378: ESXi 9.1 ESXi 9.0
A379: Broadcom | B379: NetXtreme E-Series Dual-port 100Gb OCP 3.0 RDMA Virtual Function | C379: Network | D379: ESXi 9.1 ESXi 9.0
A380: Broadcom | B380: NetXtreme-E-Series Dual-port 100Gb Ethernet PCIe RDMA Virtual Function | C380: Network | D380: ESXi 9.1 ESXi 9.0
A381: Broadcom | B381: NetXtreme-E NGM2100D BCM57508 2x100G KR Mezz RDMA Virtual Function | C381: Network | D381: ESXi 9.1 ESXi 9.0 | E381: Restricted
A382: Broadcom | B382: NetXtreme-S Ethernet Virtual Function | C382: Network | D382: ESXi 9.1 ESXi 9.0 | E382: Restricted
A383: Broadcom | B383: MegaRAID 9620-16i | C383: SAS-SATA-NVME Tri-mode RAID | D383: ESXi 9.1 ESXi 9.0
A384: Broadcom | B384: Megaraid 9540-2M2 | C384: SAS-SATA-NVME Tri-mode | D384: ESXi 9.1 ESXi 9.0
A385: Broadcom | B385: Megaraid 9562-8i | C385: SAS-SATA-NVME Tri-mode | D385: ESXi 9.1 ESXi 9.0
A386: Broadcom | B386: Megaraid 9670-24i | C386: SAS-SATA-NVME Tri-mode RAID | D386: ESXi 9.1 ESXi 9.0
A387: Broadcom | B387: NetXtreme-E N2100DE BCM57508 2x100G QSFP56 OCP3.0 Ethernet | C387: Network | D387: ESXi 9.1 ESXi 9.0
A388: Broadcom | B388: NetXtreme-E N425DE BCM57504 4x25G SFP28 OCP3.0 Ethernet | C388: Network | D388: ESXi 9.1 ESXi 9.0
A389: Broadcom | B389: NetXtreme-E N425DE BCM57504 4x25G SFP28 OCP3.0 Ethernet Partition | C389: Network | D389: ESXi 9.1 ESXi 9.0
A390: Broadcom | B390: NetXtreme-E N2100DE BCM57508 2x100G QSFP56 OCP3.0 Ethernet Partition | C390: Network | D390: ESXi 9.1 ESXi 9.0
A391: Broadcom | B391: NetXtreme-E N425DE BCM57504 4x25G SFP28 OCP3.0 RDMA Partition | C391: Network | D391: ESXi 9.1 ESXi 9.0
A392: Broadcom | B392: NetXtreme-E N2100DE BCM57508 2x100G QSFP56 OCP3.0 RDMA Partition | C392: Network | D392: ESXi 9.1 ESXi 9.0
A393: Broadcom | B393: NetXtreme-E N410TDE BCM57416 4x10G BT OCP3.0 Ethernet | C393: Network | D393: ESXi 9.1 ESXi 9.0
A394: Broadcom | B394: Ethernet NIC 10GBASE-T OCP3.0 | C394: Network | D394: ESXi 9.1 ESXi 9.0 | E394: Restricted
A395: Broadcom | B395: NetXtreme-E Dual-port 100Gb Ethernet | C395: Network | D395: ESXi 9.1 ESXi 9.0
A396: Broadcom | B396: Broadcom BCM57608 1x400G QSFP-DD OCP Ethernet NIC | C396: Network | D396: ESXi 9.1 ESXi 9.0
A397: Broadcom | B397: Broadcom BCM57608 2x200G OCP Ethernet NIC | C397: Network | D397: ESXi 9.1 ESXi 9.0
A398: Broadcom | B398: Broadcom BCM57608 1x400G QSFP-DD PCIe Ethernet NIC | C398: Network | D398: ESXi 9.1 ESXi 9.0
A399: Broadcom | B399: Broadcom BCM57608 1x400G PCIe Ethernet NIC | C399: Network | D399: ESXi 9.1 ESXi 9.0
A400: Broadcom | B400: Broadcom BCM57608 2x200G PCIe Ethernet NIC | C400: Network | D400: ESXi 9.1 ESXi 9.0
A401: Broadcom | B401: Broadcom BCM57608 2x100G OCP Ethernet NIC | C401: Network | D401: ESXi 9.1 ESXi 9.0
A402: Broadcom | B402: Broadcom BCM57608 2x200G OCP Ethernet NIC | C402: Network | D402: ESXi 9.1 ESXi 9.0
A403: Broadcom | B403: Broadcom BCM57608 4x25G OCP Ethernet NIC | C403: Network | D403: ESXi 9.1 ESXi 9.0
A404: Broadcom | B404: Broadcom BCM57608 2x100G PCIe Ethernet NIC | C404: Network | D404: ESXi 9.1 ESXi 9.0
A405: Broadcom | B405: Broadcom BCM57608 2x200G PCIe Ethernet NIC | C405: Network | D405: ESXi 9.1 ESXi 9.0
...

Sheet VCF Sizing
A1: Component | B1: Availability | C1: Size | D1: Nodes | E1: vCPU | F1: RAM (GB) | G1: Disk (GB) | H1: Location | I1: Required | J1: Design_IDs | K1: Funnel_CFG_IDs | L1: Doc_Ref | M1: Considerations | N1: Source_URL | O1: Notes
A2: Management Domain AVI Load Balancer | B2: HA | C2: Small | D2: 3 | E2: 18 | F2: 96 | G2: 1536 | H2: AVI Management Domain | I2: No | J2: DES-AVI-VALIDATE; DES-PNP; DES-OPTIONAL-DAYN | K2: VCF-AVI-REQD-CFG-001;VCF-AUTO-REQD-CFG-006 | L2: DES-AVI-VALIDATE | M2: DES-AVI-VALIDATE: Avi controller sizing: use P&P / Avi docs; cluster is typically 3 controllers when enabled. | DES-PNP: Confirm absolute vCPU/RAM/Disk from Planning & Preparation workbook Management Domain Sizing tab. | DES-OPTIONAL-DAYN: Optional/day-N component ‚Äî enable only when design needs it; may add MS worker capacity. | N2: https://techdocs.broadcom.com/us/en/vmware-cis/vcf/vcf-9-0-and-later/9-1/design/vmware-cloud-foundation-concepts/vcf-fleet-sizing-models-9-x.html
A3: Management Domain AVI Load Balancer | B3: HA | C3: Large | D3: 3 | E3: 48 | F3: 144 | G3: 4200 | H3: AVI Management Domain | I3: No | J3: DES-AVI-VALIDATE; DES-PNP; DES-OPTIONAL-DAYN | K3: VCF-AVI-REQD-CFG-001;VCF-AUTO-REQD-CFG-006 | L3: DES-AVI-VALIDATE | M3: DES-AVI-VALIDATE: Avi controller sizing: use P&P / Avi docs; cluster is typically 3 controllers when enabled. | DES-PNP: Confirm absolute vCPU/RAM/Disk from Planning & Preparation workbook Management Domain Sizing tab. | DES-OPTIONAL-DAYN: Optional/day-N component ‚Äî enable only when design needs it; may add MS worker capacity. | N3: https://techdocs.broadcom.com/us/en/vmware-cis/vcf/vcf-9-0-and-later/9-1/design/vmware-cloud-foundation-concepts/vcf-fleet-sizing-models-9-x.html
A4: Management Domain AVI Load Balancer | B4: HA | C4: X-Large | D4: 3 | E4: 48 | F4: 192 | G4: 5250 | H4: AVI Management Domain | I4: No | J4: DES-AVI-VALIDATE; DES-PNP; DES-OPTIONAL-DAYN | K4: VCF-AVI-REQD-CFG-001;VCF-AUTO-REQD-CFG-006 | L4: DES-AVI-VALIDATE | M4: DES-AVI-VALIDATE: Avi controller sizing: use P&P / Avi docs; cluster is typically 3 controllers when enabled. | DES-PNP: Confirm absolute vCPU/RAM/Disk from Planning & Preparation workbook Management Domain Sizing tab. | DES-OPTIONAL-DAYN: Optional/day-N component ‚Äî enable only when design needs it; may add MS worker capacity. | N4: https://techdocs.broadcom.com/us/en/vmware-cis/vcf/vcf-9-0-and-later/9-1/design/vmware-cloud-foundation-concepts/vcf-fleet-sizing-models-9-x.html
A5: Workload Domain AVI Load Balancer | B5: HA | C5: Small | D5: 3 | E5: 18 | F5: 96 | G5: 1536 | H5: AVI Workload Domain | I5: No | J5: DES-AVI-VALIDATE; DES-PNP; DES-OPTIONAL-DAYN | K5: VCF-AVI-REQD-CFG-001 | L5: DES-AVI-VALIDATE | M5: DES-AVI-VALIDATE: Avi controller sizing: use P&P / Avi docs; cluster is typically 3 controllers when enabled. | DES-PNP: Confirm absolute vCPU/RAM/Disk from Planning & Preparation workbook Management Domain Sizing tab. | DES-OPTIONAL-DAYN: Optional/day-N component ‚Äî enable only when design needs it; may add MS worker capacity. | N5: https://techdocs.broadcom.com/us/en/vmware-cis/vcf/vcf-9-0-and-later/9-1/design/vmware-cloud-foundation-concepts/vcf-fleet-sizing-models-9-x.html
A6: Workload Domain AVI Load Balancer | B6: HA | C6: Large | D6: 3 | E6: 48 | F6: 144 | G6: 4200 | H6: AVI Workload Domain | I6: No | J6: DES-AVI-VALIDATE; DES-PNP; DES-OPTIONAL-DAYN | K6: VCF-AVI-REQD-CFG-001 | L6: DES-AVI-VALIDATE | M6: DES-AVI-VALIDATE: Avi controller sizing: use P&P / Avi docs; cluster is typically 3 controllers when enabled. | DES-PNP: Confirm absolute vCPU/RAM/Disk from Planning & Preparation workbook Management Domain Sizing tab. | DES-OPTIONAL-DAYN: Optional/day-N component ‚Äî enable only when design needs it; may add MS worker capacity. | N6: https://techdocs.broadcom.com/us/en/vmware-cis/vcf/vcf-9-0-and-later/9-1/design/vmware-cloud-foundation-concepts/vcf-fleet-sizing-models-9-x.html
A7: Workload Domain AVI Load Balancer | B7: HA | C7: X-Large | D7: 3 | E7: 48 | F7: 192 | G7: 5250 | H7: AVI Workload Domain | I7: No | J7: DES-AVI-VALIDATE; DES-PNP; DES-OPTIONAL-DAYN | K7: VCF-AVI-REQD-CFG-001 | L7: DES-AVI-VALIDATE | M7: DES-AVI-VALIDATE: Avi controller sizing: use P&P / Avi docs; cluster is typically 3 controllers when enabled. | DES-PNP: Confirm absolute vCPU/RAM/Disk from Planning & Preparation workbook Management Domain Sizing tab. | DES-OPTIONAL-DAYN: Optional/day-N component ‚Äî enable only when design needs it; may add MS worker capacity. | N7: https://techdocs.broadcom.com/us/en/vmware-cis/vcf/vcf-9-0-and-later/9-1/design/vmware-cloud-foundation-concepts/vcf-fleet-sizing-models-9-x.html
A8: vDefend and AVI Licensing Hub | B8: HA | C8: Base | D8: 3 | E8: 10 | F8: 30 | G8: 710 | H8: Base with SSP in Management Domain | I8: No | J8: DES-AVI-VALIDATE; DES-PNP; DES-OPTIONAL-DAYN | L8: DES-AVI-VALIDATE | M8: DES-AVI-VALIDATE: Avi controller sizing: use P&P / Avi docs; cluster is typically 3 controllers when enabled. | DES-PNP: Confirm absolute vCPU/RAM/Disk from Planning & Preparation workbook Management Domain Sizing tab. | DES-OPTIONAL-DAYN: Optional/day-N component ‚Äî enable only when design needs it; may add MS worker capacity. | N8: https://techdocs.broadcom.com/us/en/vmware-cis/vcf/vcf-9-0-and-later/9-1/design/vmware-cloud-foundation-concepts/vcf-fleet-sizing-models-9-x.html
A9: Management Domain Security Services Platform | B9: HA | C9: Medium | D9: 9 | E9: 122 | F9: 444 | G9: 4806 | H9: Security Serices Platform Management Domain | I9: No | J9: DES-SSP-VALIDATE; DES-OPTIONAL-DAYN; DES-PNP | L9: DES-SSP-VALIDATE | M9: DES-SSP-VALIDATE: SSP node counts/sizes change by release ‚Äî validate against current Broadcom SSP sizing before SoW. | DES-OPTIONAL-DAYN: Optional/day-N component ‚Äî enable only when design needs it; may add MS worker capacity. | DES-PNP: Confirm absolute vCPU/RAM/Disk from Planning & Preparation workbook Management Domain Sizing tab. | N9: https://techdocs.broadcom.com/us/en/vmware-cis/vcf/vcf-9-0-and-later/9-1/design/vmware-cloud-foundation-concepts/vcf-fleet-sizing-models-9-x.html
A10: Management Domain Security Services Platform | B10: HA | C10: Large | D10: 12 | E10: 170 | F10: 636 | G10: 5830 | H10: Security Serices Platform Management Domain | I10: No | J10: DES-SSP-VALIDATE; DES-OPTIONAL-DAYN; DES-PNP | L10: DES-SSP-VALIDATE | M10: DES-SSP-VALIDATE: SSP node counts/sizes change by release ‚Äî validate against current Broadcom SSP sizing before SoW. | DES-OPTIONAL-DAYN: Optional/day-N component ‚Äî enable only when design needs it; may add MS worker capacity. | DES-PNP: Confirm absolute vCPU/RAM/Disk from Planning & Preparation workbook Management Domain Sizing tab. | N10: https://techdocs.broadcom.com/us/en/vmware-cis/vcf/vcf-9-0-and-later/9-1/design/vmware-cloud-foundation-concepts/vcf-fleet-sizing-models-9-x.html
A11: Management Domain Security Services Platform | B11: HA | C11: X-Large | D11: 14 | E11: 202 | F11: 764 | G11: 7366 | H11: Security Serices Platform Management Domain | I11: No | J11: DES-SSP-VALIDATE; DES-OPTIONAL-DAYN; DES-PNP | L11: DES-SSP-VALIDATE | M11: DES-SSP-VALIDATE: SSP node counts/sizes change by release ‚Äî validate against current Broadcom SSP sizing before SoW. | DES-OPTIONAL-DAYN: Optional/day-N component ‚Äî enable only when design needs it; may add MS worker capacity. | DES-PNP: Confirm absolute vCPU/RAM/Disk from Planning & Preparation workbook Management Domain Sizing tab. | N11: https://techdocs.broadcom.com/us/en/vmware-cis/vcf/vcf-9-0-and-later/9-1/design/vmware-cloud-foundation-concepts/vcf-fleet-sizing-models-9-x.html
A12: Workload Domain Security Services Platform | B12: HA | C12: Medium | D12: 9 | E12: 122 | F12: 444 | G12: 4806 | H12: Security Serices Platform Workload Domain | I12: No | J12: DES-SSP-VALIDATE; DES-OPTIONAL-DAYN; DES-PNP | L12: DES-SSP-VALIDATE | M12: DES-SSP-VALIDATE: SSP node counts/sizes change by release ‚Äî validate against current Broadcom SSP sizing before SoW. | DES-OPTIONAL-DAYN: Optional/day-N component ‚Äî enable only when design needs it; may add MS worker capacity. | DES-PNP: Confirm absolute vCPU/RAM/Disk from Planning & Preparation workbook Management Domain Sizing tab. | N12: https://techdocs.broadcom.com/us/en/vmware-cis/vcf/vcf-9-0-and-later/9-1/design/vmware-cloud-foundation-concepts/vcf-fleet-sizing-models-9-x.html
A13: Workload Domain Security Services Platform | B13: HA | C13: Large | D13: 12 | E13: 170 | F13: 636 | G13: 5830 | H13: Security Serices Platform Workload Domain | I13: No | J13: DES-SSP-VALIDATE; DES-OPTIONAL-DAYN; DES-PNP | L13: DES-SSP-VALIDATE | M13: DES-SSP-VALIDATE: SSP node counts/sizes change by release ‚Äî validate against current Broadcom SSP sizing before SoW. | DES-OPTIONAL-DAYN: Optional/day-N component ‚Äî enable only when design needs it; may add MS worker capacity. | DES-PNP: Confirm absolute vCPU/RAM/Disk from Planning & Preparation workbook Management Domain Sizing tab. | N13: https://techdocs.broadcom.com/us/en/vmware-cis/vcf/vcf-9-0-and-later/9-1/design/vmware-cloud-foundation-concepts/vcf-fleet-sizing-models-9-x.html
A14: Workload Domain Security Services Platform | B14: HA | C14: X-Large | D14: 14 | E14: 202 | F14: 764 | G14: 7366 | H14: Security Serices Platform Workload Domain | I14: No | J14: DES-SSP-VALIDATE; DES-OPTIONAL-DAYN; DES-PNP | L14: DES-SSP-VALIDATE | M14: DES-SSP-VALIDATE: SSP node counts/sizes change by release ‚Äî validate against current Broadcom SSP sizing before SoW. | DES-OPTIONAL-DAYN: Optional/day-N component ‚Äî enable only when design needs it; may add MS worker capacity. | DES-PNP: Confirm absolute vCPU/RAM/Disk from Planning & Preparation workbook Management Domain Sizing tab. | N14: https://techdocs.broadcom.com/us/en/vmware-cis/vcf/vcf-9-0-and-later/9-1/design/vmware-cloud-foundation-concepts/vcf-fleet-sizing-models-9-x.html
A15: Cloud Proxy | B15: HA | C15: Base | D15: 1 | E15: 4 | F15: 16 | G15: 264 | H15: VCF Fleet Components | I15: Yes | J15: VCF-OPS-REQD-COM-003; DES-PNP; DES-PROXY-HA | K15: VCF-EDGE-REQD-PAT-009 | L15: VCF-OPS-REQD-COM-003 | M15: VCF-OPS-REQD-COM-003: Deploy cloud proxy in default mgmt cluster to offload local metric/log collection. | DES-PNP: Confirm absolute vCPU/RAM/Disk from Planning & Preparation workbook Management Domain Sizing tab. | DES-PROXY-HA: Cloud Proxy: 1√ó Standard in HA Fleet models (still single appliance unless scaled). | N15: https://techdocs.broadcom.com/us/en/vmware-cis/vcf/vcf-9-0-and-later/9-1/design/vmware-cloud-foundation-concepts/vcf-operations.html
A16: Cloud Proxy | B16: Simple | C16: Small | D16: 1 | E16: 4 | F16: 16 | G16: 264 | H16: VCF Fleet Components | I16: No | J16: VCF-OPS-REQD-COM-003; DES-PNP; DES-PROXY-SIMPLE | K16: VCF-EDGE-REQD-PAT-009 | L16: VCF-OPS-REQD-COM-003 | M16: VCF-OPS-REQD-COM-003: Deploy cloud proxy in default mgmt cluster to offload local metric/log collection. | DES-PNP: Confirm absolute vCPU/RAM/Disk from Planning & Preparation workbook Management Domain Sizing tab. | DES-PROXY-SIMPLE: Cloud Proxy: 1√ó Small in Simple Fleet model. | N16: https://techdocs.broadcom.com/us/en/vmware-cis/vcf/vcf-9-0-and-later/9-1/design/vmware-cloud-foundation-concepts/vcf-operations.html | O16: migrated from 'Cloud Proxy - Simple'; Size was Simple ‚Üí Small; Availability=Simple; Required cleared (was Yes on Simple)
A17: VCF Automation | B17: HA | C17: Medium | D17: 3 | E17: 72 | F17: 288 | G17: 1002 | H17: VCF Fleet Components | I17: No | J17: VCF-AUTO-REQD-HA-001; DES-PNP | K17: VCF-AUTO-REQD-CFG-001;VCF-AUTO-REQD-CFG-002;VCF-AUTO-REQD-CFG-003;VCF-AUTO-REQD-CFG-006;VCF-AUTO-REQD-CFG-009;VCF-AUTO-REQD-CFG-010 | L17: VCF-AUTO-REQD-HA-001 | M17: VCF-AUTO-REQD-HA-001: HA Automation: three-node cluster (Medium/Large node sizes); optional external LB. | DES-PNP: Confirm absolute vCPU/RAM/Disk from Planning & Preparation workbook Management Domain Sizing tab. | N17: https://techdocs.broadcom.com/us/en/vmware-cis/vcf/vcf-9-0-and-later/9-1/design/design-library/vcf-automation-deployment-models-9-x/vcf-automation-high-availability-deployment-model.html
A18: VCF Automation | B18: HA | C18: Large | D18: 3 | E18: 96 | F18: 384 | G18: 1290 | H18: VCF Fleet Components | I18: No | J18: VCF-AUTO-REQD-HA-001; DES-PNP | K18: VCF-AUTO-REQD-CFG-001;VCF-AUTO-REQD-CFG-002;VCF-AUTO-REQD-CFG-003;VCF-AUTO-REQD-CFG-006;VCF-AUTO-REQD-CFG-009;VCF-AUTO-REQD-CFG-010 | L18: VCF-AUTO-REQD-HA-001 | M18: VCF-AUTO-REQD-HA-001: HA Automation: three-node cluster (Medium/Large node sizes); optional external LB. | DES-PNP: Confirm absolute vCPU/RAM/Disk from Planning & Preparation workbook Management Domain Sizing tab. | N18: https://techdocs.broadcom.com/us/en/vmware-cis/vcf/vcf-9-0-and-later/9-1/design/design-library/vcf-automation-deployment-models-9-x/vcf-automation-high-availability-deployment-model.html
A19: VCF Automation | B19: Simple | C19: Small | D19: 1 | E19: 24 | F19: 96 | G19: 717 | H19: VCF Fleet Components | I19: No | J19: VCF-AUTO-REQD-SIM-001; VCF-AUTO-REQD-SIM-002; DES-PNP | K19: VCF-AUTO-REQD-CFG-001;VCF-AUTO-REQD-CFG-003;VCF-AUTO-REQD-CFG-004;VCF-AUTO-REQD-CFG-010 | L19: VCF-AUTO-REQD-SIM-001 | M19: VCF-AUTO-REQD-SIM-001: Simple Automation: single node (defaults to small appliance); know scale/perf limits before production. | VCF-AUTO-REQD-SIM-002: Protect Automation Simple node with vSphere HA. | DES-PNP: Confirm absolute vCPU/RAM/Disk from Planning & Preparation workbook Management Domain Sizing tab. | N19: https://techdocs.broadcom.com/us/en/vmware-cis/vcf/vcf-9-0-and-later/9-1/design/design-library/vcf-automation-deployment-models-9-x/vcf-automation-simple-deployment-model.html | O19: migrated from 'VCF Automation - Simple'; Size was Simple ‚Üí Small; Availability=Simple
A20: VCF Operations | B20: HA | C20: Medium | D20: 3 | E20: 48 | F20: 144 | G20: 822 | H20: VCF Fleet Components | I20: Yes | J20: VCF-OPS-REQD-COM-001; DES-PNP; DES-FLEET-HA | K20: VCF-OPS-REQD-CFG-001;VCF-OPS-REQD-CFG-002;VCF-OPS-REQD-CFG-003;VCF-OPS-REQD-CFG-004;VCF-OPS-REQD-CFG-005;VCF-OPS-REQD-CFG-006;VCF-OPS-REQD-CFG-007;VCF-OPS-REQD-CFG-008 | L20: VCF-OPS-REQD-COM-001 | M20: VCF-OPS-REQD-COM-001: Fleet management components run on VCF management services in default mgmt cluster. | DES-PNP: Confirm absolute vCPU/RAM/Disk from Planning & Preparation workbook Management Domain Sizing tab. | DES-FLEET-HA: Fleet HA footprint: typically 3-node clustered appliances (Ops/NSX/Automation) + sized MS workers. | N20: https://techdocs.broadcom.com/us/en/vmware-cis/vcf/vcf-9-0-and-later/9-1/design/vmware-cloud-foundation-concepts/vcf-operations.html
A21: VCF Operations | B21: HA | C21: Large | D21: 3 | E21: 72 | F21: 384 | G21: 822 | H21: VCF Fleet Components | I21: No | J21: VCF-OPS-REQD-COM-001; DES-PNP; DES-FLEET-HA | K21: VCF-OPS-REQD-CFG-001;VCF-OPS-REQD-CFG-002;VCF-OPS-REQD-CFG-003;VCF-OPS-REQD-CFG-004;VCF-OPS-REQD-CFG-005;VCF-OPS-REQD-CFG-006;VCF-OPS-REQD-CFG-007;VCF-OPS-REQD-CFG-008 | L21: VCF-OPS-REQD-COM-001 | M21: VCF-OPS-REQD-COM-001: Fleet management components run on VCF management services in default mgmt cluster. | DES-PNP: Confirm absolute vCPU/RAM/Disk from Planning & Preparation workbook Management Domain Sizing tab. | DES-FLEET-HA: Fleet HA footprint: typically 3-node clustered appliances (Ops/NSX/Automation) + sized MS workers. | N21: https://techdocs.broadcom.com/us/en/vmware-cis/vcf/vcf-9-0-and-later/9-1/design/vmware-cloud-foundation-concepts/vcf-operations.html | O21: Required cleared (non-default HA size)
A22: VCF Operations | B22: Simple | C22: Small | D22: 1 | E22: 4 | F22: 16 | G22: 274 | H22: VCF Fleet Components | I22: No | J22: VCF-OPS-REQD-COM-001; DES-PNP; VCF-OPS-REQD-SIM-001; DES-FLEET-SIMPLE | K22: VCF-OPS-REQD-CFG-001;VCF-OPS-REQD-CFG-002;VCF-OPS-REQD-CFG-003;VCF-OPS-REQD-CFG-004 | L22: VCF-OPS-REQD-COM-001 | M22: VCF-OPS-REQD-COM-001: Fleet management components run on VCF management services in default mgmt cluster. | DES-PNP: Confirm absolute vCPU/RAM/Disk from Planning & Preparation workbook Management Domain Sizing tab. | VCF-OPS-REQD-SIM-001: Simple Ops: single analytics node in default mgmt cluster; no app-level HA; size to object scale. | DES-FLEET-SIMPLE: Fleet Simple footprint: prefer single-node appliances where model allows (lab/PoC/minimal). | N22: https://techdocs.broadcom.com/us/en/vmware-cis/vcf/vcf-9-0-and-later/9-1/design/design-blueprints-for/infrastructure-modernization/vcf-fleet-in-a-single-site-with-minimal-footprint-blueprint/management-domain-design-selections/operations-layer/simple-vcf-operations-model.html | O22: migrated from 'VCF Operations - Simple'; Size was Simple ‚Üí Small; Availability=Simple; Required cleared (was Yes on Simple)
A23: Management Domain NSX Edges | B23: HA | C23: Small | D23: 2 | E23: 4 | F23: 8 | G23: 400 | H23: VCF Management Domain | I23: No | J23: DES-PNP; DES-FLEET-HA; DES-OPTIONAL-DAYN | L23: DES-PNP | M23: DES-PNP: Confirm absolute vCPU/RAM/Disk from Planning & Preparation workbook Management Domain Sizing tab. | DES-FLEET-HA: Fleet HA footprint: typically 3-node clustered appliances (Ops/NSX/Automation) + sized MS workers. | DES-OPTIONAL-DAYN: Optional/day-N component ‚Äî enable only when design needs it; may add MS worker capacity. | N23: https://techdocs.broadcom.com/us/en/vmware-cis/vcf/vcf-9-0-and-later/9-1/design/vmware-cloud-foundation-concepts/vcf-fleet-sizing-models-9-x.html
A24: Management Domain NSX Edges | B24: HA | C24: Medium | D24: 2 | E24: 8 | F24: 16 | G24: 400 | H24: VCF Management Domain | I24: No | J24: DES-PNP; DES-FLEET-HA; DES-OPTIONAL-DAYN | L24: DES-PNP | M24: DES-PNP: Confirm absolute vCPU/RAM/Disk from Planning & Preparation workbook Management Domain Sizing tab. | DES-FLEET-HA: Fleet HA footprint: typically 3-node clustered appliances (Ops/NSX/Automation) + sized MS workers. | DES-OPTIONAL-DAYN: Optional/day-N component ‚Äî enable only when design needs it; may add MS worker capacity. | N24: https://techdocs.broadcom.com/us/en/vmware-cis/vcf/vcf-9-0-and-later/9-1/design/vmware-cloud-foundation-concepts/vcf-fleet-sizing-models-9-x.html
A25: Management Domain NSX Edges | B25: HA | C25: Large | D25: 2 | E25: 16 | F25: 64 | G25: 400 | H25: VCF Management Domain | I25: No | J25: DES-PNP; DES-FLEET-HA; DES-OPTIONAL-DAYN | L25: DES-PNP | M25: DES-PNP: Confirm absolute vCPU/RAM/Disk from Planning & Preparation workbook Management Domain Sizing tab. | DES-FLEET-HA: Fleet HA footprint: typically 3-node clustered appliances (Ops/NSX/Automation) + sized MS workers. | DES-OPTIONAL-DAYN: Optional/day-N component ‚Äî enable only when design needs it; may add MS worker capacity. | N25: https://techdocs.broadcom.com/us/en/vmware-cis/vcf/vcf-9-0-and-later/9-1/design/vmware-cloud-foundation-concepts/vcf-fleet-sizing-models-9-x.html
A26: Management Domain NSX Edges | B26: HA | C26: X-Large | D26: 2 | E26: 32 | F26: 128 | G26: 400 | H26: VCF Management Domain | I26: No | J26: DES-PNP; DES-FLEET-HA; DES-OPTIONAL-DAYN | L26: DES-PNP | M26: DES-PNP: Confirm absolute vCPU/RAM/Disk from Planning & Preparation workbook Management Domain Sizing tab. | DES-FLEET-HA: Fleet HA footprint: typically 3-node clustered appliances (Ops/NSX/Automation) + sized MS workers. | DES-OPTIONAL-DAYN: Optional/day-N component ‚Äî enable only when design needs it; may add MS worker capacity. | N26: https://techdocs.broadcom.com/us/en/vmware-cis/vcf/vcf-9-0-and-later/9-1/design/vmware-cloud-foundation-concepts/vcf-fleet-sizing-models-9-x.html
A27: Management Domain NSX Managers (Local / Global) | B27: HA | C27: Medium | D27: 3 | E27: 18 | F27: 72 | G27: 900 | H27: VCF Management Domain | I27: Yes | J27: DES-NSX-HA; DES-FLEET-HA; DES-PNP | K27: VCF-NSX-LM-REQD-CFG-001;VCF-NSX-LM-REQD-CFG-002;VCF-NSX-LM-REQD-CFG-004;VCF-NSX-LM-REQD-CFG-005 | L27: DES-NSX-HA | M27: DES-NSX-HA: HA NSX: 3 managers (Medium or Large per scale); needs host count for anti-affinity + VIP. | DES-FLEET-HA: Fleet HA footprint: typically 3-node clustered appliances (Ops/NSX/Automation) + sized MS workers. | DES-PNP: Confirm absolute vCPU/RAM/Disk from Planning & Preparation workbook Management Domain Sizing tab. | N27: https://techdocs.broadcom.com/us/en/vmware-cis/vcf/vcf-9-0-and-later/9-1/design/vmware-cloud-foundation-concepts/vcf-fleet-sizing-models-9-x.html
A28: Management Domain NSX Managers (Local / Global) | B28: HA | C28: Large | D28: 3 | E28: 36 | F28: 144 | G28: 900 | H28: VCF Management Domain | I28: No | J28: DES-NSX-HA; DES-FLEET-HA; DES-PNP | K28: VCF-NSX-LM-REQD-CFG-001;VCF-NSX-LM-REQD-CFG-002;VCF-NSX-LM-REQD-CFG-004;VCF-NSX-LM-REQD-CFG-005 | L28: DES-NSX-HA | M28: DES-NSX-HA: HA NSX: 3 managers (Medium or Large per scale); needs host count for anti-affinity + VIP. | DES-FLEET-HA: Fleet HA footprint: typically 3-node clustered appliances (Ops/NSX/Automation) + sized MS workers. | DES-PNP: Confirm absolute vCPU/RAM/Disk from Planning & Preparation workbook Management Domain Sizing tab. | N28: https://techdocs.broadcom.com/us/en/vmware-cis/vcf/vcf-9-0-and-later/9-1/design/vmware-cloud-foundation-concepts/vcf-fleet-sizing-models-9-x.html | O28: Required cleared (non-default HA size)
A29: Management Domain NSX Managers (Local / Global) | B29: Simple | C29: Small | D29: 1 | E29: 6 | F29: 24 | G29: 300 | H29: VCF Management Domain | I29: No | J29: DES-NSX-SIMPLE; DES-FLEET-SIMPLE; DES-PNP | K29: VCF-NSX-LM-REQD-CFG-001;VCF-NSX-LM-REQD-CFG-005 | L29: DES-NSX-SIMPLE | M29: DES-NSX-SIMPLE: Simple NSX: 1√ó Medium manager (not a 3-node cluster). | DES-FLEET-SIMPLE: Fleet Simple footprint: prefer single-node appliances where model allows (lab/PoC/minimal). | DES-PNP: Confirm absolute vCPU/RAM/Disk from Planning & Preparation workbook Management Domain Sizing tab. | N29: https://techdocs.broadcom.com/us/en/vmware-cis/vcf/vcf-9-0-and-later/9-1/design/vmware-cloud-foundation-concepts/vcf-fleet-sizing-models-9-x.html | O29: migrated from 'Management Domain NSX Managers (Simple)'; Size was Simple ‚Üí Small; Availability=Simple; aligned to HA NSX component name '(Local / Global)'; Required cleared (was Yes on Simple)
A30: Management Domain Virtual Network Appliances | B30: HA | C30: Small | D30: 2 | E30: 4 | F30: 8 | G30: 400 | H30: VCF Management Domain | I30: No | J30: DES-PNP; DES-FLEET-HA; DES-OPTIONAL-DAYN | L30: DES-PNP | M30: DES-PNP: Confirm absolute vCPU/RAM/Disk from Planning & Preparation workbook Management Domain Sizing tab. | DES-FLEET-HA: Fleet HA footprint: typically 3-node clustered appliances (Ops/NSX/Automation) + sized MS workers. | DES-OPTIONAL-DAYN: Optional/day-N component ‚Äî enable only when design needs it; may add MS worker capacity. | N30: https://techdocs.broadcom.com/us/en/vmware-cis/vcf/vcf-9-0-and-later/9-1/design/vmware-cloud-foundation-concepts/vcf-fleet-sizing-models-9-x.html
A31: Management Domain Virtual Network Appliances | B31: HA | C31: Medium | D31: 2 | E31: 8 | F31: 16 | G31: 400 | H31: VCF Management Domain | I31: No | J31: DES-PNP; DES-FLEET-HA; DES-OPTIONAL-DAYN | L31: DES-PNP | M31: DES-PNP: Confirm absolute vCPU/RAM/Disk from Planning & Preparation workbook Management Domain Sizing tab. | DES-FLEET-HA: Fleet HA footprint: typically 3-node clustered appliances (Ops/NSX/Automation) + sized MS workers. | DES-OPTIONAL-DAYN: Optional/day-N component ‚Äî enable only when design needs it; may add MS worker capacity. | N31: https://techdocs.broadcom.com/us/en/vmware-cis/vcf/vcf-9-0-and-later/9-1/design/vmware-cloud-foundation-concepts/vcf-fleet-sizing-models-9-x.html
A32: Management Domain Virtual Network Appliances | B32: HA | C32: Large | D32: 2 | E32: 16 | F32: 64 | G32: 400 | H32: VCF Management Domain | I32: No | J32: DES-PNP; DES-FLEET-HA; DES-OPTIONAL-DAYN | L32: DES-PNP | M32: DES-PNP: Confirm absolute vCPU/RAM/Disk from Planning & Preparation workbook Management Domain Sizing tab. | DES-FLEET-HA: Fleet HA footprint: typically 3-node clustered appliances (Ops/NSX/Automation) + sized MS workers. | DES-OPTIONAL-DAYN: Optional/day-N component ‚Äî enable only when design needs it; may add MS worker capacity. | N32: https://techdocs.broadcom.com/us/en/vmware-cis/vcf/vcf-9-0-and-later/9-1/design/vmware-cloud-foundation-concepts/vcf-fleet-sizing-models-9-x.html
A33: Management Domain Virtual Network Appliances | B33: HA | C33: X-Large | D33: 2 | E33: 32 | F33: 128 | G33: 400 | H33: VCF Management Domain | I33: No | J33: DES-PNP; DES-FLEET-HA; DES-OPTIONAL-DAYN | L33: DES-PNP | M33: DES-PNP: Confirm absolute vCPU/RAM/Disk from Planning & Preparation workbook Management Domain Sizing tab. | DES-FLEET-HA: Fleet HA footprint: typically 3-node clustered appliances (Ops/NSX/Automation) + sized MS workers. | DES-OPTIONAL-DAYN: Optional/day-N component ‚Äî enable only when design needs it; may add MS worker capacity. | N33: https://techdocs.broadcom.com/us/en/vmware-cis/vcf/vcf-9-0-and-later/9-1/design/vmware-cloud-foundation-concepts/vcf-fleet-sizing-models-9-x.html
A34: Management Domain vCenter | B34: HA | C34: Medium | D34: 1 | E34: 8 | F34: 30 | G34: 1658 | H34: VCF Management Domain | I34: Yes | J34: DES-VC-HA; DES-FLEET-HA; DES-PNP | K34: VCF-VC-REQD-CFG-001;VCF-VC-REQD-CFG-003;VCF-VC-REQD-CFG-005 | L34: DES-VC-HA | M34: DES-VC-HA: vCenter Medium/Large per Fleet sizing; single VC appliance (availability via vSphere HA, not a 3-node VC cluster). | DES-FLEET-HA: Fleet HA footprint: typically 3-node clustered appliances (Ops/NSX/Automation) + sized MS workers. | DES-PNP: Confirm absolute vCPU/RAM/Disk from Planning & Preparation workbook Management Domain Sizing tab. | N34: https://techdocs.broadcom.com/us/en/vmware-cis/vcf/vcf-9-0-and-later/9-1/design/vmware-cloud-foundation-concepts/vcf-fleet-sizing-models-9-x.html
A35: Management Domain vCenter | B35: HA | C35: Large | D35: 1 | E35: 16 | F35: 39 | G35: 3088 | H35: VCF Management Domain | I35: No | J35: DES-VC-HA; DES-FLEET-HA; DES-PNP | K35: VCF-VC-REQD-CFG-001;VCF-VC-REQD-CFG-003;VCF-VC-REQD-CFG-005 | L35: DES-VC-HA | M35: DES-VC-HA: vCenter Medium/Large per Fleet sizing; single VC appliance (availability via vSphere HA, not a 3-node VC cluster). | DES-FLEET-HA: Fleet HA footprint: typically 3-node clustered appliances (Ops/NSX/Automation) + sized MS workers. | DES-PNP: Confirm absolute vCPU/RAM/Disk from Planning & Preparation workbook Management Domain Sizing tab. | N35: https://techdocs.broadcom.com/us/en/vmware-cis/vcf/vcf-9-0-and-later/9-1/design/vmware-cloud-foundation-concepts/vcf-fleet-sizing-models-9-x.html | O35: Required cleared (non-default HA size)
A36: Management Domain vCenter | B36: Simple | C36: Small | D36: 1 | E36: 4 | F36: 8 | G36: 1519 | H36: VCF Management Domain | I36: No | J36: DES-VC-SIMPLE; DES-FLEET-SIMPLE; DES-PNP | K36: VCF-VC-REQD-CFG-001;VCF-VC-REQD-CFG-003;VCF-VC-REQD-CFG-005 | L36: DES-VC-SIMPLE | M36: DES-VC-SIMPLE: Simple vCenter: Small appliance class per Fleet Simple model. | DES-FLEET-SIMPLE: Fleet Simple footprint: prefer single-node appliances where model allows (lab/PoC/minimal). | DES-PNP: Confirm absolute vCPU/RAM/Disk from Planning & Preparation workbook Management Domain Sizing tab. | N36: https://techdocs.broadcom.com/us/en/vmware-cis/vcf/vcf-9-0-and-later/9-1/design/vmware-cloud-foundation-concepts/vcf-fleet-sizing-models-9-x.html | O36: migrated from 'Management Domain vCenter - Simple'; Size was Simple ‚Üí Small; Availability=Simple; Required cleared (was Yes on Simple)
A37: Identity Broker | B37: HA | C37: Base | D37: 3 | E37: 24 | F37: 48 | G37: 150 | H37: VCF Management Services | I37: Yes | J37: DES-MS-HOSTED; VCF-MS-REQD-COM-001; VCF-MS-REQD-HA-001 | K37: VCF-AUTO-REQD-CFG-004 | L37: VCF-MS-REQD-COM-001 | M37: DES-MS-HOSTED: Runs as a workload on the VCF services runtime; inherits Simple vs HA from the runtime model (SIM-001 / HA-001 on control+worker rows). | VCF-MS-REQD-COM-001: Allocate IP range for all planned control + worker nodes (day-N scale-out consumes more). | VCF-MS-REQD-HA-001: HA MS: deploy 3 control-plane nodes + workers for chosen size (Medium/Large); higher resource cost. | N37: https://techdocs.broadcom.com/us/en/vmware-cis/vcf/vcf-9-0-and-later/9-1/design/vmware-cloud-foundation-concepts/vcf-management-services-models.html
A38: Identity Broker | B38: Simple | C38: Small | D38: 1 | E38: 24 | F38: 48 | G38: 150 | H38: VCF Management Services | I38: No | J38: DES-MS-HOSTED; VCF-MS-REQD-COM-001; VCF-MS-REQD-SIM-001 | K38: VCF-AUTO-REQD-CFG-004 | L38: VCF-MS-REQD-COM-001 | M38: DES-MS-HOSTED: Runs as a workload on the VCF services runtime; inherits Simple vs HA from the runtime model (SIM-001 / HA-001 on control+worker rows). | VCF-MS-REQD-COM-001: Allocate IP range for all planned control + worker nodes (day-N scale-out consumes more). | VCF-MS-REQD-SIM-001: Simple MS: deploy 1 control-plane + 3 workers in default mgmt cluster; CP loss ‚áí redeploy/restore. | N38: https://techdocs.broadcom.com/us/en/vmware-cis/vcf/vcf-9-0-and-later/9-1/design/vmware-cloud-foundation-concepts/vcf-management-services-models.html | O38: migrated from 'Identity Broker - Simple'; Size was Simple ‚Üí Small; Availability=Simple; Required cleared (was Yes on Simple)
A39: License Server | B39: HA | C39: Base | D39: 1 | E39: 2 | F39: 4 | G39: 12 | H39: VCF Management Services | I39: Yes | J39: DES-LICENSE; DES-PNP | K39: VCF-LIC-REQD-CFG-001;VCF-LIC-RCMD-CFG-002 | L39: DES-LICENSE | M39: DES-LICENSE: License Server: 1√ó Default in both Simple and HA Fleet models. | DES-PNP: Confirm absolute vCPU/RAM/Disk from Planning & Preparation workbook Management Domain Sizing tab. | N39: https://techdocs.broadcom.com/us/en/vmware-cis/vcf/vcf-9-0-and-later/9-1/design/vmware-cloud-foundation-concepts/vcf-fleet-sizing-models-9-x.html
A40: License Server | B40: Simple | C40: Small | D40: 1 | E40: 2 | F40: 4 | G40: 12 | H40: VCF Management Services | I40: No | J40: DES-LICENSE; DES-PNP | K40: VCF-LIC-REQD-CFG-001;VCF-LIC-RCMD-CFG-002 | L40: DES-LICENSE | M40: DES-LICENSE: License Server: 1√ó Default in both Simple and HA Fleet models. | DES-PNP: Confirm absolute vCPU/RAM/Disk from Planning & Preparation workbook Management Domain Sizing tab. | N40: https://techdocs.broadcom.com/us/en/vmware-cis/vcf/vcf-9-0-and-later/9-1/design/vmware-cloud-foundation-concepts/vcf-fleet-sizing-models-9-x.html | O40: migrated from 'License Server - Simple'; Size was Simple ‚Üí Small; Availability=Simple; Required cleared (was Yes on Simple)
A41: Log Management | B41: HA | C41: Medium | D41: 3 | E41: 72 | F41: 144 | G41: 1725 | H41: VCF Management Services | I41: No | J41: DES-MS-HOSTED; VCF-MS-REQD-COM-001; VCF-MS-REQD-HA-001; DES-OPTIONAL-DAYN | L41: VCF-MS-REQD-COM-001 | M41: DES-MS-HOSTED: Runs as a workload on the VCF services runtime; inherits Simple vs HA from the runtime model (SIM-001 / HA-001 on control+worker rows). | VCF-MS-REQD-COM-001: Allocate IP range for all planned control + worker nodes (day-N scale-out consumes more). | VCF-MS-REQD-HA-001: HA MS: deploy 3 control-plane nodes + workers for chosen size (Medium/Large); higher resource cost. | DES-OPTIONAL-DAYN: Optional/day-N component ‚Äî enable only when design needs it; may add MS worker capacity. | N41: https://techdocs.broadcom.com/us/en/vmware-cis/vcf/vcf-9-0-and-later/9-1/design/vmware-cloud-foundation-concepts/vcf-management-services-models.html
A42: Log Management | B42: HA | C42: Large | D42: 6 | E42: 144 | F42: 288 | G42: 1725 | H42: VCF Management Services | I42: No | J42: DES-MS-HOSTED; VCF-MS-REQD-COM-001; VCF-MS-REQD-HA-001; DES-OPTIONAL-DAYN | L42: VCF-MS-REQD-COM-001 | M42: DES-MS-HOSTED: Runs as a workload on the VCF services runtime; inherits Simple vs HA from the runtime model (SIM-001 / HA-001 on control+worker rows). | VCF-MS-REQD-COM-001: Allocate IP range for all planned control + worker nodes (day-N scale-out consumes more). | VCF-MS-REQD-HA-001: HA MS: deploy 3 control-plane nodes + workers for chosen size (Medium/Large); higher resource cost. | DES-OPTIONAL-DAYN: Optional/day-N component ‚Äî enable only when design needs it; may add MS worker capacity. | N42: https://techdocs.broadcom.com/us/en/vmware-cis/vcf/vcf-9-0-and-later/9-1/design/vmware-cloud-foundation-concepts/vcf-management-services-models.html
A43: Offline Software Depot | B43: HA | C43: Base | D43: 1 | E43: 2 | F43: 8 | G43: 500 | H43: VCF Management Services | I43: No | J43: DES-MS-HOSTED; VCF-MS-REQD-COM-001; VCF-MS-REQD-HA-001; DES-OPTIONAL-DAYN | L43: VCF-MS-REQD-COM-001 | M43: DES-MS-HOSTED: Runs as a workload on the VCF services runtime; inherits Simple vs HA from the runtime model (SIM-001 / HA-001 on control+worker rows). | VCF-MS-REQD-COM-001: Allocate IP range for all planned control + worker nodes (day-N scale-out consumes more). | VCF-MS-REQD-HA-001: HA MS: deploy 3 control-plane nodes + workers for chosen size (Medium/Large); higher resource cost. | DES-OPTIONAL-DAYN: Optional/day-N component ‚Äî enable only when design needs it; may add MS worker capacity. | N43: https://techdocs.broadcom.com/us/en/vmware-cis/vcf/vcf-9-0-and-later/9-1/design/vmware-cloud-foundation-concepts/vcf-management-services-models.html | O43: Size was 'Optional' ‚Üí Base (Required=No)
A44: Protection Blueprint Requirements | B44: HA | C44: Base | D44: 1 | E44: 8 | F44: 24 | G44: 800 | H44: VCF Management Services | I44: Yes | J44: DES-PNP; DES-FLEET-HA | L44: DES-PNP | M44: DES-PNP: Confirm absolute vCPU/RAM/Disk from Planning & Preparation workbook Management Domain Sizing tab. | DES-FLEET-HA: Fleet HA footprint: typically 3-node clustered appliances (Ops/NSX/Automation) + sized MS workers. | N44: https://techdocs.broadcom.com/us/en/vmware-cis/vcf/vcf-9-0-and-later/9-1/design/vmware-cloud-foundation-concepts/vcf-fleet-sizing-models-9-x.html
A45: Protection Blueprint Requirements | B45: Simple | C45: Small | D45: 1 | E45: 8 | F45: 24 | G45: 800 | H45: VCF Management Services | I45: No | J45: DES-PNP; DES-FLEET-SIMPLE | L45: DES-PNP | M45: DES-PNP: Confirm absolute vCPU/RAM/Disk from Planning & Preparation workbook Management Domain Sizing tab. | DES-FLEET-SIMPLE: Fleet Simple footprint: prefer single-node appliances where model allows (lab/PoC/minimal). | N45: https://techdocs.broadcom.com/us/en/vmware-cis/vcf/vcf-9-0-and-later/9-1/design/vmware-cloud-foundation-concepts/vcf-fleet-sizing-models-9-x.html | O45: migrated from 'Protection Blueprint Requirements - Simple'; Size was Simple ‚Üí Small; Availability=Simple; Required cleared (was Yes on Simple)
A46: Real-time Metrics | B46: HA | C46: Medium | D46: 2 | E46: 48 | F46: 96 | G46: 205 | H46: VCF Management Services | I46: No | J46: DES-MS-HOSTED; VCF-MS-REQD-COM-001; VCF-MS-REQD-HA-001; DES-OPTIONAL-DAYN | L46: VCF-MS-REQD-COM-001 | M46: DES-MS-HOSTED: Runs as a workload on the VCF services runtime; inherits Simple vs HA from the runtime model (SIM-001 / HA-001 on control+worker rows). | VCF-MS-REQD-COM-001: Allocate IP range for all planned control + worker nodes (day-N scale-out consumes more). | VCF-MS-REQD-HA-001: HA MS: deploy 3 control-plane nodes + workers for chosen size (Medium/Large); higher resource cost. | DES-OPTIONAL-DAYN: Optional/day-N component ‚Äî enable only when design needs it; may add MS worker capacity. | N46: https://techdocs.broadcom.com/us/en/vmware-cis/vcf/vcf-9-0-and-later/9-1/design/vmware-cloud-foundation-concepts/vcf-management-services-models.html | O46: Size was 'Required' ‚Üí Medium (Required flag remains No)
A47: Real-time Metrics | B47: Simple | C47: Small | D47: 2 | E47: 24 | F47: 48 | G47: 205 | H47: VCF Management Services | I47: No | J47: DES-MS-HOSTED; VCF-MS-REQD-COM-001; VCF-MS-REQD-SIM-001; DES-OPTIONAL-DAYN | L47: VCF-MS-REQD-COM-001 | M47: DES-MS-HOSTED: Runs as a workload on the VCF services runtime; inherits Simple vs HA from the runtime model (SIM-001 / HA-001 on control+worker rows). | VCF-MS-REQD-COM-001: Allocate IP range for all planned control + worker nodes (day-N scale-out consumes more). | VCF-MS-REQD-SIM-001: Simple MS: deploy 1 control-plane + 3 workers in default mgmt cluster; CP loss ‚áí redeploy/restore. | DES-OPTIONAL-DAYN: Optional/day-N component ‚Äî enable only when design needs it; may add MS worker capacity. | N47: https://techdocs.broadcom.com/us/en/vmware-cis/vcf/vcf-9-0-and-later/9-1/design/vmware-cloud-foundation-concepts/vcf-management-services-models.html | O47: migrated from 'Real-time Metrics - Simple'; Size was Simple ‚Üí Small; Availability=Simple
A48: SDDC Manager | B48: HA | C48: Base | D48: 1 | E48: 4 | F48: 16 | G48: 914 | H48: VCF Management Services | I48: Yes | J48: DES-SDDC; DES-PNP | K48: VCF-SDDCMGR-REQD-CFG-001;VCF-SDDCMGR-REQD-CFG-005 | L48: DES-SDDC | M48: DES-SDDC: SDDC Manager: 1√ó Default in both Simple and HA Fleet models. | DES-PNP: Confirm absolute vCPU/RAM/Disk from Planning & Preparation workbook Management Domain Sizing tab. | N48: https://techdocs.broadcom.com/us/en/vmware-cis/vcf/vcf-9-0-and-later/9-1/design/vmware-cloud-foundation-concepts/vcf-fleet-sizing-models-9-x.html
A49: SDDC Manager | B49: Simple | C49: Small | D49: 1 | E49: 4 | F49: 16 | G49: 914 | H49: VCF Management Services | I49: No | J49: DES-SDDC; DES-PNP | K49: VCF-SDDCMGR-REQD-CFG-001;VCF-SDDCMGR-REQD-CFG-005 | L49: DES-SDDC | M49: DES-SDDC: SDDC Manager: 1√ó Default in both Simple and HA Fleet models. | DES-PNP: Confirm absolute vCPU/RAM/Disk from Planning & Preparation workbook Management Domain Sizing tab. | N49: https://techdocs.broadcom.com/us/en/vmware-cis/vcf/vcf-9-0-and-later/9-1/design/vmware-cloud-foundation-concepts/vcf-fleet-sizing-models-9-x.html | O49: migrated from 'SDDC Manager - Simple'; Size was Simple ‚Üí Small; Availability=Simple; Required cleared (was Yes on Simple)
A50: VCF Operations for networks | B50: HA | C50: Medium | D50: 1 | E50: 8 | F50: 32 | G50: 1024 | H50: VCF Management Services | I50: No | J50: DES-PNP; DES-FLEET-HA; DES-OPTIONAL-DAYN | L50: DES-PNP | M50: DES-PNP: Confirm absolute vCPU/RAM/Disk from Planning & Preparation workbook Management Domain Sizing tab. | DES-FLEET-HA: Fleet HA footprint: typically 3-node clustered appliances (Ops/NSX/Automation) + sized MS workers. | DES-OPTIONAL-DAYN: Optional/day-N component ‚Äî enable only when design needs it; may add MS worker capacity. | N50: https://techdocs.broadcom.com/us/en/vmware-cis/vcf/vcf-9-0-and-later/9-1/design/vmware-cloud-foundation-concepts/vcf-fleet-sizing-models-9-x.html
A51: VCF Operations for networks | B51: HA | C51: Large | D51: 3 | E51: 36 | F51: 144 | G51: 3072 | H51: VCF Management Services | I51: No | J51: DES-PNP; DES-FLEET-HA; DES-OPTIONAL-DAYN | L51: DES-PNP | M51: DES-PNP: Confirm absolute vCPU/RAM/Disk from Planning & Preparation workbook Management Domain Sizing tab. | DES-FLEET-HA: Fleet HA footprint: typically 3-node clustered appliances (Ops/NSX/Automation) + sized MS workers. | DES-OPTIONAL-DAYN: Optional/day-N component ‚Äî enable only when design needs it; may add MS worker capacity. | N51: https://techdocs.broadcom.com/us/en/vmware-cis/vcf/vcf-9-0-and-later/9-1/design/vmware-cloud-foundation-concepts/vcf-fleet-sizing-models-9-x.html
A52: VCF Operations for networks | B52: Simple | C52: Small | D52: 1 | E52: 4 | F52: 16 | G52: 1024 | H52: VCF Management Services | I52: No | J52: DES-PNP; DES-FLEET-SIMPLE; DES-OPTIONAL-DAYN | L52: DES-PNP | M52: DES-PNP: Confirm absolute vCPU/RAM/Disk from Planning & Preparation workbook Management Domain Sizing tab. | DES-FLEET-SIMPLE: Fleet Simple footprint: prefer single-node appliances where model allows (lab/PoC/minimal). | DES-OPTIONAL-DAYN: Optional/day-N component ‚Äî enable only when design needs it; may add MS worker capacity. | N52: https://techdocs.broadcom.com/us/en/vmware-cis/vcf/vcf-9-0-and-later/9-1/design/vmware-cloud-foundation-concepts/vcf-fleet-sizing-models-9-x.html | O52: migrated from 'VCF Operations for networks - Simple'; Size was Simple ‚Üí Small; Availability=Simple
A53: VCF Operations for networks collector | B53: HA | C53: Base | D53: 1 | E53: 4 | F53: 12 | G53: 250 | H53: VCF Management Services | I53: No | J53: DES-PNP; DES-FLEET-HA; DES-OPTIONAL-DAYN | L53: DES-PNP | M53: DES-PNP: Confirm absolute vCPU/RAM/Disk from Planning & Preparation workbook Management Domain Sizing tab. | DES-FLEET-HA: Fleet HA footprint: typically 3-node clustered appliances (Ops/NSX/Automation) + sized MS workers. | DES-OPTIONAL-DAYN: Optional/day-N component ‚Äî enable only when design needs it; may add MS worker capacity. | N53: https://techdocs.broadcom.com/us/en/vmware-cis/vcf/vcf-9-0-and-later/9-1/design/vmware-cloud-foundation-concepts/vcf-fleet-sizing-models-9-x.html
A54: VCF Operations for networks collector | B54: Simple | C54: Small | D54: 1 | E54: 2 | F54: 4 | G54: 250 | H54: VCF Management Services | I54: No | J54: DES-PNP; DES-FLEET-SIMPLE; DES-OPTIONAL-DAYN | L54: DES-PNP | M54: DES-PNP: Confirm absolute vCPU/RAM/Disk from Planning & Preparation workbook Management Domain Sizing tab. | DES-FLEET-SIMPLE: Fleet Simple footprint: prefer single-node appliances where model allows (lab/PoC/minimal). | DES-OPTIONAL-DAYN: Optional/day-N component ‚Äî enable only when design needs it; may add MS worker capacity. | N54: https://techdocs.broadcom.com/us/en/vmware-cis/vcf/vcf-9-0-and-later/9-1/design/vmware-cloud-foundation-concepts/vcf-fleet-sizing-models-9-x.html | O54: migrated from 'VCF Operations for networks collector - Simple'; Size was Simple ‚Üí Small; Availability=Simple
A55: VCF services runtime control nodes | B55: HA | C55: Medium | D55: 3 | E55: 12 | F55: 30 | G55: 300 | H55: VCF Management Services | I55: Yes | J55: VCF-MS-REQD-COM-001; VCF-MS-REQD-COM-002; VCF-MS-REQD-COM-003; VCF-MS-REQD-HA-001 | K55: VCF-CLS-REQD-CFG-001;VCF-CLS-REQD-CFG-002 | L55: VCF-MS-REQD-COM-001 | M55: VCF-MS-REQD-COM-001: Allocate IP range for all planned control + worker nodes (day-N scale-out consumes more). | VCF-MS-REQD-COM-002: CAPV anti-affinity: MS nodes on different ESX hosts (DRS rules not required). | VCF-MS-REQD-COM-003: Protect MS nodes with vSphere HA (restart on host failure). | VCF-MS-REQD-HA-001: HA MS: deploy 3 control-plane nodes + workers for chosen size (Medium/Large); higher resource cost. | N55: https://techdocs.broadcom.com/us/en/vmware-cis/vcf/vcf-9-0-and-later/9-1/design/design-library/vcf-management-services-availabilty-detailed-design/vcf-management-services-high-availability-deployment-model.html
A56: VCF services runtime control nodes | B56: HA | C56: Large | D56: 3 | E56: 24 | F56: 42 | G56: 300 | H56: VCF Management Services | I56: No | J56: VCF-MS-REQD-COM-001; VCF-MS-REQD-COM-002; VCF-MS-REQD-COM-003; VCF-MS-REQD-HA-001 | K56: VCF-CLS-REQD-CFG-001;VCF-CLS-REQD-CFG-002 | L56: VCF-MS-REQD-COM-001 | M56: VCF-MS-REQD-COM-001: Allocate IP range for all planned control + worker nodes (day-N scale-out consumes more). | VCF-MS-REQD-COM-002: CAPV anti-affinity: MS nodes on different ESX hosts (DRS rules not required). | VCF-MS-REQD-COM-003: Protect MS nodes with vSphere HA (restart on host failure). | VCF-MS-REQD-HA-001: HA MS: deploy 3 control-plane nodes + workers for chosen size (Medium/Large); higher resource cost. | N56: https://techdocs.broadcom.com/us/en/vmware-cis/vcf/vcf-9-0-and-later/9-1/design/design-library/vcf-management-services-availabilty-detailed-design/vcf-management-services-high-availability-deployment-model.html | O56: Required cleared (non-default HA size)
A57: VCF services runtime control nodes | B57: Simple | C57: Small | D57: 1 | E57: 4 | F57: 10 | G57: 100 | H57: VCF Management Services | I57: No | J57: VCF-MS-REQD-COM-001; VCF-MS-REQD-COM-002; VCF-MS-REQD-COM-003; VCF-MS-REQD-SIM-001 | K57: VCF-CLS-REQD-CFG-001;VCF-CLS-REQD-CFG-002 | L57: VCF-MS-REQD-COM-001 | M57: VCF-MS-REQD-COM-001: Allocate IP range for all planned control + worker nodes (day-N scale-out consumes more). | VCF-MS-REQD-COM-002: CAPV anti-affinity: MS nodes on different ESX hosts (DRS rules not required). | VCF-MS-REQD-COM-003: Protect MS nodes with vSphere HA (restart on host failure). | VCF-MS-REQD-SIM-001: Simple MS: deploy 1 control-plane + 3 workers in default mgmt cluster; CP loss ‚áí redeploy/restore. | N57: https://techdocs.broadcom.com/us/en/vmware-cis/vcf/vcf-9-0-and-later/9-1/design/design-library/vcf-management-services-availabilty-detailed-design/vcf-management-services-simple-deployment-model.html | O57: migrated from 'VCF services runtime control nodes - Simple'; Size was Simple ‚Üí Small; Availability=Simple; Required cleared (was Yes on Simple)
A58: VCF services runtime worker nodes | B58: HA | C58: Medium | D58: 3 | E58: 72 | F58: 144 | G58: 3300 | H58: VCF Management Services | I58: Yes | J58: VCF-MS-REQD-COM-001; VCF-MS-REQD-COM-002; VCF-MS-REQD-COM-003; VCF-MS-REQD-HA-001 | K58: VCF-CLS-REQD-CFG-001;VCF-CLS-REQD-CFG-002 | L58: VCF-MS-REQD-COM-001 | M58: VCF-MS-REQD-COM-001: Allocate IP range for all planned control + worker nodes (day-N scale-out consumes more). | VCF-MS-REQD-COM-002: CAPV anti-affinity: MS nodes on different ESX hosts (DRS rules not required). | VCF-MS-REQD-COM-003: Protect MS nodes with vSphere HA (restart on host failure). | VCF-MS-REQD-HA-001: HA MS: deploy 3 control-plane nodes + workers for chosen size (Medium/Large); higher resource cost. | N58: https://techdocs.broadcom.com/us/en/vmware-cis/vcf/vcf-9-0-and-later/9-1/design/design-library/vcf-management-services-availabilty-detailed-design/vcf-management-services-high-availability-deployment-model.html
A59: VCF services runtime worker nodes | B59: HA | C59: Large | D59: 4 | E59: 96 | F59: 192 | G59: 4102 | H59: VCF Management Services | I59: No | J59: VCF-MS-REQD-COM-001; VCF-MS-REQD-COM-002; VCF-MS-REQD-COM-003; VCF-MS-REQD-HA-001 | K59: VCF-CLS-REQD-CFG-001;VCF-CLS-REQD-CFG-002 | L59: VCF-MS-REQD-COM-001 | M59: VCF-MS-REQD-COM-001: Allocate IP range for all planned control + worker nodes (day-N scale-out consumes more). | VCF-MS-REQD-COM-002: CAPV anti-affinity: MS nodes on different ESX hosts (DRS rules not required). | VCF-MS-REQD-COM-003: Protect MS nodes with vSphere HA (restart on host failure). | VCF-MS-REQD-HA-001: HA MS: deploy 3 control-plane nodes + workers for chosen size (Medium/Large); higher resource cost. | N59: https://techdocs.broadcom.com/us/en/vmware-cis/vcf/vcf-9-0-and-later/9-1/design/design-library/vcf-management-services-availabilty-detailed-design/vcf-management-services-high-availability-deployment-model.html | O59: Required cleared (non-default HA size)
A60: VCF services runtime worker nodes | B60: Simple | C60: Small | D60: 3 | E60: 36 | F60: 72 | G60: 2900 | H60: VCF Management Services | I60: No | J60: VCF-MS-REQD-COM-001; VCF-MS-REQD-COM-002; VCF-MS-REQD-COM-003; VCF-MS-REQD-SIM-001 | K60: VCF-CLS-REQD-CFG-001;VCF-CLS-REQD-CFG-002 | L60: VCF-MS-REQD-COM-001 | M60: VCF-MS-REQD-COM-001: Allocate IP range for all planned control + worker nodes (day-N scale-out consumes more). | VCF-MS-REQD-COM-002: CAPV anti-affinity: MS nodes on different ESX hosts (DRS rules not required). | VCF-MS-REQD-COM-003: Protect MS nodes with vSphere HA (restart on host failure). | VCF-MS-REQD-SIM-001: Simple MS: deploy 1 control-plane + 3 workers in default mgmt cluster; CP loss ‚áí redeploy/restore. | N60: https://techdocs.broadcom.com/us/en/vmware-cis/vcf/vcf-9-0-and-later/9-1/design/design-library/vcf-management-services-availabilty-detailed-design/vcf-management-services-simple-deployment-model.html | O60: migrated from 'VCF services runtime worker nodes - Simple'; Size was Simple ‚Üí Small; Availability=Simple; Required cleared (was Yes on Simple)
A61: Workload Domain NSX Managers (Local / Global) | B61: HA | C61: Small | D61: 3 | E61: 4 | F61: 16 | G61: 300 | H61: VCF Workload Domain | I61: No | J61: DES-NSX-HA; DES-FLEET-HA; DES-PNP | K61: VCF-NSX-LM-REQD-CFG-003;VCF-NSX-LM-REQD-CFG-004;VCF-NSX-LM-REQD-CFG-005 | L61: DES-NSX-HA | M61: DES-NSX-HA: HA NSX: 3 managers (Medium or Large per scale); needs host count for anti-affinity + VIP. | DES-FLEET-HA: Fleet HA footprint: typically 3-node clustered appliances (Ops/NSX/Automation) + sized MS workers. | DES-PNP: Confirm absolute vCPU/RAM/Disk from Planning & Preparation workbook Management Domain Sizing tab. | N61: https://techdocs.broadcom.com/us/en/vmware-cis/vcf/vcf-9-0-and-later/9-1/design/vmware-cloud-foundation-concepts/vcf-fleet-sizing-models-9-x.html
A62: Workload Domain NSX Managers (Local / Global) | B62: HA | C62: Medium | D62: 3 | E62: 6 | F62: 24 | G62: 300 | H62: VCF Workload Domain | I62: No | J62: DES-NSX-HA; DES-FLEET-HA; DES-PNP | K62: VCF-NSX-LM-REQD-CFG-003;VCF-NSX-LM-REQD-CFG-004;VCF-NSX-LM-REQD-CFG-005 | L62: DES-NSX-HA | M62: DES-NSX-HA: HA NSX: 3 managers (Medium or Large per scale); needs host count for anti-affinity + VIP. | DES-FLEET-HA: Fleet HA footprint: typically 3-node clustered appliances (Ops/NSX/Automation) + sized MS workers. | DES-PNP: Confirm absolute vCPU/RAM/Disk from Planning & Preparation workbook Management Domain Sizing tab. | N62: https://techdocs.broadcom.com/us/en/vmware-cis/vcf/vcf-9-0-and-later/9-1/design/vmware-cloud-foundation-concepts/vcf-fleet-sizing-models-9-x.html
A63: Workload Domain NSX Managers (Local / Global) | B63: HA | C63: Large | D63: 3 | E63: 12 | F63: 48 | G63: 300 | H63: VCF Workload Domain | I63: No | J63: DES-NSX-HA; DES-FLEET-HA; DES-PNP | K63: VCF-NSX-LM-REQD-CFG-003;VCF-NSX-LM-REQD-CFG-004;VCF-NSX-LM-REQD-CFG-005 | L63: DES-NSX-HA | M63: DES-NSX-HA: HA NSX: 3 managers (Medium or Large per scale); needs host count for anti-affinity + VIP. | DES-FLEET-HA: Fleet HA footprint: typically 3-node clustered appliances (Ops/NSX/Automation) + sized MS workers. | DES-PNP: Confirm absolute vCPU/RAM/Disk from Planning & Preparation workbook Management Domain Sizing tab. | N63: https://techdocs.broadcom.com/us/en/vmware-cis/vcf/vcf-9-0-and-later/9-1/design/vmware-cloud-foundation-concepts/vcf-fleet-sizing-models-9-x.html
A64: Workload Domain NSX Managers (Local / Global) | B64: HA | C64: X-Large | D64: 3 | E64: 24 | F64: 96 | G64: 400 | H64: VCF Workload Domain | I64: No | J64: DES-NSX-HA; DES-FLEET-HA; DES-PNP | K64: VCF-NSX-LM-REQD-CFG-003;VCF-NSX-LM-REQD-CFG-004;VCF-NSX-LM-REQD-CFG-005 | L64: DES-NSX-HA | M64: DES-NSX-HA: HA NSX: 3 managers (Medium or Large per scale); needs host count for anti-affinity + VIP. | DES-FLEET-HA: Fleet HA footprint: typically 3-node clustered appliances (Ops/NSX/Automation) + sized MS workers. | DES-PNP: Confirm absolute vCPU/RAM/Disk from Planning & Preparation workbook Management Domain Sizing tab. | N64: https://techdocs.broadcom.com/us/en/vmware-cis/vcf/vcf-9-0-and-later/9-1/design/vmware-cloud-foundation-concepts/vcf-fleet-sizing-models-9-x.html
A65: Workload Domain vCenter | B65: HA | C65: Medium | D65: 1 | E65: 8 | F65: 30 | G65: 1658 | H65: VCF Workload Domain | I65: No | J65: DES-VC-HA; DES-FLEET-HA; DES-PNP | K65: VCF-VC-REQD-CFG-002;VCF-VC-REQD-CFG-005 | L65: DES-VC-HA | M65: DES-VC-HA: vCenter Medium/Large per Fleet sizing; single VC appliance (availability via vSphere HA, not a 3-node VC cluster). | DES-FLEET-HA: Fleet HA footprint: typically 3-node clustered appliances (Ops/NSX/Automation) + sized MS workers. | DES-PNP: Confirm absolute vCPU/RAM/Disk from Planning & Preparation workbook Management Domain Sizing tab. | N65: https://techdocs.broadcom.com/us/en/vmware-cis/vcf/vcf-9-0-and-later/9-1/design/vmware-cloud-foundation-concepts/vcf-fleet-sizing-models-9-x.html
A66: Workload Domain vCenter | B66: HA | C66: Large | D66: 1 | E66: 16 | F66: 39 | G66: 3088 | H66: VCF Workload Domain | I66: No | J66: DES-VC-HA; DES-FLEET-HA; DES-PNP | K66: VCF-VC-REQD-CFG-002;VCF-VC-REQD-CFG-005 | L66: DES-VC-HA | M66: DES-VC-HA: vCenter Medium/Large per Fleet sizing; single VC appliance (availability via vSphere HA, not a 3-node VC cluster). | DES-FLEET-HA: Fleet HA footprint: typically 3-node clustered appliances (Ops/NSX/Automation) + sized MS workers. | DES-PNP: Confirm absolute vCPU/RAM/Disk from Planning & Preparation workbook Management Domain Sizing tab. | N66: https://techdocs.broadcom.com/us/en/vmware-cis/vcf/vcf-9-0-and-later/9-1/design/vmware-cloud-foundation-concepts/vcf-fleet-sizing-models-9-x.html

Sheet Design IDs
A1: ID | B1: Bucket | C1: Title | D1: Decision Type | E1: Trigger Criteria | F1: Requirement | G1: Justification | H1: Parent Decision IDs | I1: Baseline Bundle ID | J1: Rule Classification | K1: Mapping Status | L1: Mapping Rationale | M1: Source Version | N1: Source URL | O1: Source Match
A2: VCF-PAI-REQD-CFG-001 | B2: AI | C2: GPU Host Profiling | D2: Required | E2: hldIncAI=true | F2: Ensure all hosts in the AI workload domain have identical NVIDIA GPU hardware and profiles. | G2: Guarantees DRS load balancing and vMotion compatibility for AI/ML workloads. | H2: DEC-AI-001; DEC-AI-002; DEC-NET-004 | I2: BL-SOL-001 | J2: DECISION_LED | K2: MAPPED | L2: Activated by hldIncAI=true; governed by DEC-AI-001, DEC-AI-002, DEC-NET-004. | M2: VCF 9.1 | N2: https://techdocs.broadcom.com/us/en/vmware-cis/vcf/vcf-9-0-and-later/9-1/design/design-library/private-ai-platform-detailed-design.html | O2: prefix:VCF-PAI-
A3: VCF-PAI-REQD-CFG-002 | B3: AI | C3: Backend AI Network | D3: Required | E3: hldIncAI=true | F3: Allocate a dedicated high-throughput, low-latency VLAN (RoCEv2) for GPU-to-GPU communications. | G3: Prevents deep learning network traffic from bottlenecking standard VM traffic. | H3: DEC-AI-001; DEC-AI-002; DEC-NET-004 | I3: BL-SOL-001 | J3: DECISION_LED | K3: MAPPED | L3: Activated by hldIncAI=true; governed by DEC-AI-001, DEC-AI-002, DEC-NET-004. | M3: VCF 9.1 | N3: https://techdocs.broadcom.com/us/en/vmware-cis/vcf/vcf-9-0-and-later/9-1/design/design-library/private-ai-platform-detailed-design.html | O3: prefix:VCF-PAI-
A4: VCF-PAI-REQD-CFG-003 | B4: AI | C4: NVIDIA Licensing System | D4: Required | E4: ALWAYS | F4: Deploy the NVIDIA License System (NLS) appliance in the management domain. | G4: Centralizes vGPU license distribution for tenant workload clusters. | H4: DEC-AI-001; DEC-AI-002 | I4: BL-SOL-001 | J4: INHERIT_PARENT_SCOPE | K4: MAPPED | L4: Required after parent decision DEC-AI-001, DEC-AI-002 activates this domain or solution. | M4: VCF 9.1 | N4: https://techdocs.broadcom.com/us/en/vmware-cis/vcf/vcf-9-0-and-later/9-1/design/design-library/private-ai-platform-detailed-design.html | O4: prefix:VCF-PAI-
A5: VCF-PAI-REQD-CFG-004 | B5: AI | C5: AI Workload Orchestration Model | D5: Required | E5: ALWAYS | F5: Determine whether AI/ML workloads will be scheduled via an MLOps orchestration platform (e.g., Run:ai, NVIDIA AI Enterprise tooling) or managed directly through vCenter/vGPU assignment. | G5: Orchestration model determines whether GPU capacity is exposed as an aggregate pool or requires explicit per-VM MIG/vGPU partition design; getting this wrong means re-architecting GPU allocation later. | H5: DEC-AI-001; DEC-AI-002 | I5: BL-SOL-001 | J5: INHERIT_PARENT_SCOPE | K5: MAPPED | L5: Required after parent decision DEC-AI-001, DEC-AI-002 activates this domain or solution. | M5: VCF 9.1 | N5: https://techdocs.broadcom.com/us/en/vmware-cis/vcf/vcf-9-0-and-later/9-1/design/design-library/private-ai-platform-detailed-design.html | O5: prefix:VCF-PAI-
A6: VCF-AUTO-REQD-CFG-001 | B6: AUTO | C6: VCF Automation Placement | D6: Required | E6: ALWAYS | F6: Deploy VCF Automation in the management domain or a dedicated management cluster. | G6: Secures the automation and orchestration engine within the primary administrative boundary. | H6: DEC-AUTO-001; DEC-AUTO-002 | I6: BL-SOL-001 | J6: INHERIT_PARENT_SCOPE | K6: MAPPED | L6: Required after parent decision DEC-AUTO-001, DEC-AUTO-002 activates this domain or solution. | M6: VCF 9.1 | N6: https://techdocs.broadcom.com/us/en/vmware-cis/vcf/vcf-9-0-and-later/9-1/design/design-library/vcf-automation-deployment-models-9-x.html | O6: prefix:VCF-AUTO-
A7: VCF-AUTO-REQD-CFG-002 | B7: AUTO | C7: VCF Automation HA | D7: Required | E7: availabilityModel=HA | F7: Deploy a cluster of three VCF Automation appliances for high availability. | G7: Guarantees continuous self-service and orchestration during host or node failures. | H7: DEC-AUTO-001; DEC-AUTO-002 | I7: BL-SOL-001 | J7: INHERIT_PARENT_SCOPE | K7: MAPPED | L7: Required after parent decision DEC-AUTO-001, DEC-AUTO-002 activates this domain or solution. | M7: VCF 9.1 | N7: https://techdocs.broadcom.com/us/en/vmware-cis/vcf/vcf-9-0-and-later/9-1/design/design-library/vcf-automation-deployment-models-9-x.html | O7: prefix:VCF-AUTO-
A8: VCF-AUTO-REQD-CFG-004 | B8: AUTO | C8: Identity Broker Integration | D8: Required | E8: ALWAYS | F8: Integrate VCF Automation with Identity Broker. | G8: Standardizes Role-Based Access Control (RBAC) and single sign-on across the VCF portal. | H8: DEC-AUTO-001; DEC-ID-001; DEC-AUTO-002 | I8: BL-SOL-001 | J8: INHERIT_PARENT_SCOPE | K8: MAPPED | L8: Required after parent decision DEC-AUTO-001, DEC-ID-001, DEC-AUTO-002 activates this domain or solution. | M8: VCF 9.1 | N8: https://techdocs.broadcom.com/us/en/vmware-cis/vcf/vcf-9-0-and-later/9-1/design/design-library/vcf-automation-deployment-models-9-x.html | O8: prefix:VCF-AUTO-
A9: VCF-AUTO-REQD-CFG-005 | B9: AUTO | C9: NSX Cloud Accounts | D9: Required | E9: ALWAYS | F9: Configure NSX cloud accounts within VCF Automation to enable on-demand network provisioning. | G9: Allows developers to dynamically spin up load balancers and networks via self-service blueprints. | H9: DEC-AUTO-001; DEC-AUTO-002 | I9: BL-SOL-001 | J9: INHERIT_PARENT_SCOPE | K9: MAPPED | L9: Required after parent decision DEC-AUTO-001, DEC-AUTO-002 activates this domain or solution. | M9: VCF 9.1 | N9: https://techdocs.broadcom.com/us/en/vmware-cis/vcf/vcf-9-0-and-later/9-1/design/design-library/vcf-automation-deployment-models-9-x.html | O9: prefix:VCF-AUTO-
A10: VCF-AUTO-REQD-CFG-006 | B10: AUTO | C10: VCF Auto Load Balancer | D10: Required | E10: ALWAYS | F10: Deploy an Avi or equivalent to front the VCF Automation cluster. | G10: Ensures highly available access to the self-service portal for developers and users. | H10: DEC-AUTO-001; DEC-NET-004; DEC-AUTO-002 | I10: BL-SOL-001 | J10: INHERIT_PARENT_SCOPE | K10: MAPPED | L10: Required after parent decision DEC-AUTO-001, DEC-NET-004, DEC-AUTO-002 activates this domain or solution. | M10: VCF 9.1 | N10: https://techdocs.broadcom.com/us/en/vmware-cis/vcf/vcf-9-0-and-later/9-1/design/design-library/vcf-automation-deployment-models-9-x.html | O10: prefix:VCF-AUTO-
A11: VCF-AUTO-REQD-CFG-007 | B11: AUTO | C11: Automation Extensibility | D11: Required | E11: ALWAYS | F11: Deploy VCF Automation Orchestrator nodes independently if complex scripting exceeds built-in capabilities. | G11: Offloads heavy API interaction and customized workflows from the core Automation appliances. | H11: DEC-AUTO-001; DEC-AUTO-002 | I11: BL-SOL-001 | J11: INHERIT_PARENT_SCOPE | K11: MAPPED | L11: Required after parent decision DEC-AUTO-001, DEC-AUTO-002 activates this domain or solution. | M11: VCF 9.1 | N11: https://techdocs.broadcom.com/us/en/vmware-cis/vcf/vcf-9-0-and-later/9-1/design/design-library/vcf-automation-deployment-models-9-x.html | O11: prefix:VCF-AUTO-
A12: VCF-AUTO-REQD-CFG-008 | B12: AUTO | C12: Cloud Zone Grouping | D12: Required | E12: ALWAYS | F12: Group vCenter compute clusters into VCF Automation Cloud Zones by SLA or purpose. | G12: Allows fine-grained placement policies for developer blueprints targeting specific hardware tiers. | H12: DEC-AUTO-001; DEC-AUTO-002 | I12: BL-SOL-001 | J12: INHERIT_PARENT_SCOPE | K12: MAPPED | L12: Required after parent decision DEC-AUTO-001, DEC-AUTO-002 activates this domain or solution. | M12: VCF 9.1 | N12: https://techdocs.broadcom.com/us/en/vmware-cis/vcf/vcf-9-0-and-later/9-1/design/design-library/vcf-automation-deployment-models-9-x.html | O12: prefix:VCF-AUTO-
... A164: DES-MS-HOSTED | B164: FLEET | C164: MS-Hosted Component Inherits Topology | D164: Required | E164: ALWAYS | F164: Treat Identity Broker, Real-time Metrics, Log Management, and Software Depot as workloads hosted on VCF services runtime; inherit Simple vs HA from MS topology (SIM-001 / HA-001). | G164: Avoids duplicating CP/worker topology rules onto every hosted service row. | H164: DEC-FLEET-001; DEC-AVAIL-002 | I164: BL-MGMT-001 | J164: DECISION_LED | K164: NEW_SIZING_BRIDGE | L164: Imported from Broadcom TechDocs design requirement tables. | M164: VCF 9.1 | N164: https://techdocs.broadcom.com/us/en/vmware-cis/vcf/vcf-9-0-and-later/9-1/design/vmware-cloud-foundation-concepts/vcf-management-services-models.html | O164: preexisting-techdocs

Sheet Design Bridge
A1: Component | B1: Availability | C1: Size | D1: TechDocs_or_DES_IDs | E1: Funnel_CFG_IDs | F1: Bridge_Note | G1: Source_URL
A2: Management Domain AVI Load Balancer | B2: HA | C2: Small | D2: DES-AVI-VALIDATE;DES-PNP;DES-OPTIONAL-DAYN | E2: VCF-AVI-REQD-CFG-001;VCF-AUTO-REQD-CFG-006 | F2: Avi controllers in mgmt domain. | G2: https://techdocs.broadcom.com/us/en/vmware-cis/vcf/vcf-9-0-and-later/9-1/design/vmware-cloud-foundation-concepts/vcf-fleet-sizing-models-9-x.html
A3: Management Domain AVI Load Balancer | B3: HA | C3: Large | D3: DES-AVI-VALIDATE;DES-PNP;DES-OPTIONAL-DAYN | E3: VCF-AVI-REQD-CFG-001;VCF-AUTO-REQD-CFG-006 | F3: Avi controllers in mgmt domain. | G3: https://techdocs.broadcom.com/us/en/vmware-cis/vcf/vcf-9-0-and-later/9-1/design/vmware-cloud-foundation-concepts/vcf-fleet-sizing-models-9-x.html
A4: Management Domain AVI Load Balancer | B4: HA | C4: X-Large | D4: DES-AVI-VALIDATE;DES-PNP;DES-OPTIONAL-DAYN | E4: VCF-AVI-REQD-CFG-001;VCF-AUTO-REQD-CFG-006 | F4: Avi controllers in mgmt domain. | G4: https://techdocs.broadcom.com/us/en/vmware-cis/vcf/vcf-9-0-and-later/9-1/design/vmware-cloud-foundation-concepts/vcf-fleet-sizing-models-9-x.html
A5: Workload Domain AVI Load Balancer | B5: HA | C5: Small | D5: DES-AVI-VALIDATE;DES-PNP;DES-OPTIONAL-DAYN | E5: VCF-AVI-REQD-CFG-001 | F5: Optional WLD Avi footprint. | G5: https://techdocs.broadcom.com/us/en/vmware-cis/vcf/vcf-9-0-and-later/9-1/design/vmware-cloud-foundation-concepts/vcf-fleet-sizing-models-9-x.html
A6: Workload Domain AVI Load Balancer | B6: HA | C6: Large | D6: DES-AVI-VALIDATE;DES-PNP;DES-OPTIONAL-DAYN | E6: VCF-AVI-REQD-CFG-001 | F6: Optional WLD Avi footprint. | G6: https://techdocs.broadcom.com/us/en/vmware-cis/vcf/vcf-9-0-and-later/9-1/design/vmware-cloud-foundation-concepts/vcf-fleet-sizing-models-9-x.html
A7: Workload Domain AVI Load Balancer | B7: HA | C7: X-Large | D7: DES-AVI-VALIDATE;DES-PNP;DES-OPTIONAL-DAYN | E7: VCF-AVI-REQD-CFG-001 | F7: Optional WLD Avi footprint. | G7: https://techdocs.broadcom.com/us/en/vmware-cis/vcf/vcf-9-0-and-later/9-1/design/vmware-cloud-foundation-concepts/vcf-fleet-sizing-models-9-x.html
A8: vDefend and AVI Licensing Hub | B8: HA | C8: Base | D8: DES-AVI-VALIDATE;DES-PNP;DES-OPTIONAL-DAYN | F8: No Funnel bridge yet ‚Äî keep DES-PNP / Fleet fallback; extend bridge as needed. | G8: https://techdocs.broadcom.com/us/en/vmware-cis/vcf/vcf-9-0-and-later/9-1/design/vmware-cloud-foundation-concepts/vcf-fleet-sizing-models-9-x.html
A9: Management Domain Security Services Platform | B9: HA | C9: Medium | D9: DES-SSP-VALIDATE;DES-OPTIONAL-DAYN;DES-PNP | F9: No Funnel bridge yet ‚Äî keep DES-PNP / Fleet fallback; extend bridge as needed. | G9: https://techdocs.broadcom.com/us/en/vmware-cis/vcf/vcf-9-0-and-later/9-1/design/vmware-cloud-foundation-concepts/vcf-fleet-sizing-models-9-x.html
A10: Management Domain Security Services Platform | B10: HA | C10: Large | D10: DES-SSP-VALIDATE;DES-OPTIONAL-DAYN;DES-PNP | F10: No Funnel bridge yet ‚Äî keep DES-PNP / Fleet fallback; extend bridge as needed. | G10: https://techdocs.broadcom.com/us/en/vmware-cis/vcf/vcf-9-0-and-later/9-1/design/vmware-cloud-foundation-concepts/vcf-fleet-sizing-models-9-x.html
A11: Management Domain Security Services Platform | B11: HA | C11: X-Large | D11: DES-SSP-VALIDATE;DES-OPTIONAL-DAYN;DES-PNP | F11: No Funnel bridge yet ‚Äî keep DES-PNP / Fleet fallback; extend bridge as needed. | G11: https://techdocs.broadcom.com/us/en/vmware-cis/vcf/vcf-9-0-and-later/9-1/design/vmware-cloud-foundation-concepts/vcf-fleet-sizing-models-9-x.html
A12: Workload Domain Security Services Platform | B12: HA | C12: Medium | D12: DES-SSP-VALIDATE;DES-OPTIONAL-DAYN;DES-PNP | F12: No Funnel bridge yet ‚Äî keep DES-PNP / Fleet fallback; extend bridge as needed. | G12: https://techdocs.broadcom.com/us/en/vmware-cis/vcf/vcf-9-0-and-later/9-1/design/vmware-cloud-foundation-concepts/vcf-fleet-sizing-models-9-x.html
A13: Workload Domain Security Services Platform | B13: HA | C13: Large | D13: DES-SSP-VALIDATE;DES-OPTIONAL-DAYN;DES-PNP | F13: No Funnel bridge yet ‚Äî keep DES-PNP / Fleet fallback; extend bridge as needed. | G13: https://techdocs.broadcom.com/us/en/vmware-cis/vcf/vcf-9-0-and-later/9-1/design/vmware-cloud-foundation-concepts/vcf-fleet-sizing-models-9-x.html
A14: Workload Domain Security Services Platform | B14: HA | C14: X-Large | D14: DES-SSP-VALIDATE;DES-OPTIONAL-DAYN;DES-PNP | F14: No Funnel bridge yet ‚Äî keep DES-PNP / Fleet fallback; extend bridge as needed. | G14: https://techdocs.broadcom.com/us/en/vmware-cis/vcf/vcf-9-0-and-later/9-1/design/vmware-cloud-foundation-concepts/vcf-fleet-sizing-models-9-x.html
A15: Cloud Proxy | B15: HA | C15: Base | D15: VCF-OPS-REQD-COM-003;DES-PNP;DES-PROXY-HA | E15: VCF-EDGE-REQD-PAT-009 | F15: PAT-009 is edge/latency-triggered; keep COM-003 as TechDocs deploy rule. | G15: https://techdocs.broadcom.com/us/en/vmware-cis/vcf/vcf-9-0-and-later/9-1/design/vmware-cloud-foundation-concepts/vcf-operations.html
A16: Cloud Proxy | B16: Simple | C16: Small | D16: VCF-OPS-REQD-COM-003;DES-PNP;DES-PROXY-SIMPLE | E16: VCF-EDGE-REQD-PAT-009 | F16: PAT-009 is edge/latency-triggered; keep COM-003 as TechDocs deploy rule. | G16: https://techdocs.broadcom.com/us/en/vmware-cis/vcf/vcf-9-0-and-later/9-1/design/vmware-cloud-foundation-concepts/vcf-operations.html
A17: VCF Automation | B17: HA | C17: Medium | D17: VCF-AUTO-REQD-HA-001;DES-PNP | E17: VCF-AUTO-REQD-CFG-001;VCF-AUTO-REQD-CFG-002;VCF-AUTO-REQD-CFG-003;VCF-AUTO-REQD-CFG-006;VCF-AUTO-REQD-CFG-009;VCF-AUTO-REQD-CFG-010 | F17: CFG-002 is HA-only ‚Äî change Trigger from ALWAYS ‚Üí availabilityModel=HA. CFG-009 Large is production HA bias. | G17: https://techdocs.broadcom.com/us/en/vmware-cis/vcf/vcf-9-0-and-later/9-1/design/design-library/vcf-automation-deployment-models-9-x/vcf-automation-high-availability-deployment-model.html
A18: VCF Automation | B18: HA | C18: Large | D18: VCF-AUTO-REQD-HA-001;DES-PNP | E18: VCF-AUTO-REQD-CFG-001;VCF-AUTO-REQD-CFG-002;VCF-AUTO-REQD-CFG-003;VCF-AUTO-REQD-CFG-006;VCF-AUTO-REQD-CFG-009;VCF-AUTO-REQD-CFG-010 | F18: CFG-002 is HA-only ‚Äî change Trigger from ALWAYS ‚Üí availabilityModel=HA. CFG-009 Large is production HA bias. | G18: https://techdocs.broadcom.com/us/en/vmware-cis/vcf/vcf-9-0-and-later/9-1/design/design-library/vcf-automation-deployment-models-9-x/vcf-automation-high-availability-deployment-model.html
A19: VCF Automation | B19: Simple | C19: Small | D19: VCF-AUTO-REQD-SIM-001;VCF-AUTO-REQD-SIM-002;DES-PNP | E19: VCF-AUTO-REQD-CFG-001;VCF-AUTO-REQD-CFG-003;VCF-AUTO-REQD-CFG-004;VCF-AUTO-REQD-CFG-010 | F19: CFG-002 is HA-only ‚Äî change Trigger from ALWAYS ‚Üí availabilityModel=HA. CFG-009 Large is production HA bias. | G19: https://techdocs.broadcom.com/us/en/vmware-cis/vcf/vcf-9-0-and-later/9-1/design/design-library/vcf-automation-deployment-models-9-x/vcf-automation-simple-deployment-model.html
A20: VCF Operations | B20: HA | C20: Medium | D20: VCF-OPS-REQD-COM-001;DES-PNP;DES-FLEET-HA | E20: VCF-OPS-REQD-CFG-001;VCF-OPS-REQD-CFG-002;VCF-OPS-REQD-CFG-003;VCF-OPS-REQD-CFG-004;VCF-OPS-REQD-CFG-005;VCF-OPS-REQD-CFG-006;VCF-OPS-REQD-CFG-007;VCF-OPS-REQD-CFG-008 | F20: Add Ops SIM TechDocs ID; map HA to existing OPS CFG sizing/placement IDs. | G20: https://techdocs.broadcom.com/us/en/vmware-cis/vcf/vcf-9-0-and-later/9-1/design/vmware-cloud-foundation-concepts/vcf-operations.html
A21: VCF Operations | B21: HA | C21: Large | D21: VCF-OPS-REQD-COM-001;DES-PNP;DES-FLEET-HA | E21: VCF-OPS-REQD-CFG-001;VCF-OPS-REQD-CFG-002;VCF-OPS-REQD-CFG-003;VCF-OPS-REQD-CFG-004;VCF-OPS-REQD-CFG-005;VCF-OPS-REQD-CFG-006;VCF-OPS-REQD-CFG-007;VCF-OPS-REQD-CFG-008 | F21: Add Ops SIM TechDocs ID; map HA to existing OPS CFG sizing/placement IDs. | G21: https://techdocs.broadcom.com/us/en/vmware-cis/vcf/vcf-9-0-and-later/9-1/design/vmware-cloud-foundation-concepts/vcf-operations.html
A22: VCF Operations | B22: Simple | C22: Small | D22: VCF-OPS-REQD-COM-001;DES-PNP;VCF-OPS-REQD-SIM-001;DES-FLEET-SIMPLE | E22: VCF-OPS-REQD-CFG-001;VCF-OPS-REQD-CFG-002;VCF-OPS-REQD-CFG-003;VCF-OPS-REQD-CFG-004 | F22: Add Ops SIM TechDocs ID; map HA to existing OPS CFG sizing/placement IDs. | G22: https://techdocs.broadcom.com/us/en/vmware-cis/vcf/vcf-9-0-and-later/9-1/design/design-blueprints-for/infrastructure-modernization/vcf-fleet-in-a-single-site-with-minimal-footprint-blueprint/management-domain-design-selections/operations-layer/simple-vcf-operations-model.html
A23: Management Domain NSX Edges | B23: HA | C23: Small | D23: DES-PNP;DES-FLEET-HA;DES-OPTIONAL-DAYN | F23: No Funnel bridge yet ‚Äî keep DES-PNP / Fleet fallback; extend bridge as needed. | G23: https://techdocs.broadcom.com/us/en/vmware-cis/vcf/vcf-9-0-and-later/9-1/design/vmware-cloud-foundation-concepts/vcf-fleet-sizing-models-9-x.html
A24: Management Domain NSX Edges | B24: HA | C24: Medium | D24: DES-PNP;DES-FLEET-HA;DES-OPTIONAL-DAYN | F24: No Funnel bridge yet ‚Äî keep DES-PNP / Fleet fallback; extend bridge as needed. | G24: https://techdocs.broadcom.com/us/en/vmware-cis/vcf/vcf-9-0-and-later/9-1/design/vmware-cloud-foundation-concepts/vcf-fleet-sizing-models-9-x.html
A25: Management Domain NSX Edges | B25: HA | C25: Large | D25: DES-PNP;DES-FLEET-HA;DES-OPTIONAL-DAYN | F25: No Funnel bridge yet ‚Äî keep DES-PNP / Fleet fallback; extend bridge as needed. | G25: https://techdocs.broadcom.com/us/en/vmware-cis/vcf/vcf-9-0-and-later/9-1/design/vmware-cloud-foundation-concepts/vcf-fleet-sizing-models-9-x.html
A26: Management Domain NSX Edges | B26: HA | C26: X-Large | D26: DES-PNP;DES-FLEET-HA;DES-OPTIONAL-DAYN | F26: No Funnel bridge yet ‚Äî keep DES-PNP / Fleet fallback; extend bridge as needed. | G26: https://techdocs.broadcom.com/us/en/vmware-cis/vcf/vcf-9-0-and-later/9-1/design/vmware-cloud-foundation-concepts/vcf-fleet-sizing-models-9-x.html
A27: Management Domain NSX Managers (Local / Global) | B27: HA | C27: Medium | D27: DES-NSX-HA;DES-FLEET-HA;DES-PNP | E27: VCF-NSX-LM-REQD-CFG-001;VCF-NSX-LM-REQD-CFG-002;VCF-NSX-LM-REQD-CFG-004;VCF-NSX-LM-REQD-CFG-005 | F27: CFG-002 says ALWAYS 3-node ‚Äî gate with availabilityModel=HA. Add/adjust Simple (1-node) requirement. | G27: https://techdocs.broadcom.com/us/en/vmware-cis/vcf/vcf-9-0-and-later/9-1/design/vmware-cloud-foundation-concepts/vcf-fleet-sizing-models-9-x.html
A28: Management Domain NSX Managers (Local / Global) | B28: HA | C28: Large | D28: DES-NSX-HA;DES-FLEET-HA;DES-PNP | E28: VCF-NSX-LM-REQD-CFG-001;VCF-NSX-LM-REQD-CFG-002;VCF-NSX-LM-REQD-CFG-004;VCF-NSX-LM-REQD-CFG-005 | F28: CFG-002 says ALWAYS 3-node ‚Äî gate with availabilityModel=HA. Add/adjust Simple (1-node) requirement. | G28: https://techdocs.broadcom.com/us/en/vmware-cis/vcf/vcf-9-0-and-later/9-1/design/vmware-cloud-foundation-concepts/vcf-fleet-sizing-models-9-x.html
A29: Management Domain NSX Managers (Local / Global) | B29: Simple | C29: Small | D29: DES-NSX-SIMPLE;DES-FLEET-SIMPLE;DES-PNP | E29: VCF-NSX-LM-REQD-CFG-001;VCF-NSX-LM-REQD-CFG-005 | F29: CFG-002 says ALWAYS 3-node ‚Äî gate with availabilityModel=HA. Add/adjust Simple (1-node) requirement. | G29: https://techdocs.broadcom.com/us/en/vmware-cis/vcf/vcf-9-0-and-later/9-1/design/vmware-cloud-foundation-concepts/vcf-fleet-sizing-models-9-x.html
A30: Management Domain Virtual Network Appliances | B30: HA | C30: Small | D30: DES-PNP;DES-FLEET-HA;DES-OPTIONAL-DAYN | F30: No Funnel bridge yet ‚Äî keep DES-PNP / Fleet fallback; extend bridge as needed. | G30: https://techdocs.broadcom.com/us/en/vmware-cis/vcf/vcf-9-0-and-later/9-1/design/vmware-cloud-foundation-concepts/vcf-fleet-sizing-models-9-x.html
A31: Management Domain Virtual Network Appliances | B31: HA | C31: Medium | D31: DES-PNP;DES-FLEET-HA;DES-OPTIONAL-DAYN | F31: No Funnel bridge yet ‚Äî keep DES-PNP / Fleet fallback; extend bridge as needed. | G31: https://techdocs.broadcom.com/us/en/vmware-cis/vcf/vcf-9-0-and-later/9-1/design/vmware-cloud-foundation-concepts/vcf-fleet-sizing-models-9-x.html
A32: Management Domain Virtual Network Appliances | B32: HA | C32: Large | D32: DES-PNP;DES-FLEET-HA;DES-OPTIONAL-DAYN | F32: No Funnel bridge yet ‚Äî keep DES-PNP / Fleet fallback; extend bridge as needed. | G32: https://techdocs.broadcom.com/us/en/vmware-cis/vcf/vcf-9-0-and-later/9-1/design/vmware-cloud-foundation-concepts/vcf-fleet-sizing-models-9-x.html
A33: Management Domain Virtual Network Appliances | B33: HA | C33: X-Large | D33: DES-PNP;DES-FLEET-HA;DES-OPTIONAL-DAYN | F33: No Funnel bridge yet ‚Äî keep DES-PNP / Fleet fallback; extend bridge as needed. | G33: https://techdocs.broadcom.com/us/en/vmware-cis/vcf/vcf-9-0-and-later/9-1/design/vmware-cloud-foundation-concepts/vcf-fleet-sizing-models-9-x.html
A34: Management Domain vCenter | B34: HA | C34: Medium | D34: DES-VC-HA;DES-FLEET-HA;DES-PNP | E34: VCF-VC-REQD-CFG-001;VCF-VC-REQD-CFG-003;VCF-VC-REQD-CFG-005 | F34: vCenter stays 1 appliance; CFG-003 = vSphere HA not VCHA. Size via CFG-005. | G34: https://techdocs.broadcom.com/us/en/vmware-cis/vcf/vcf-9-0-and-later/9-1/design/vmware-cloud-foundation-concepts/vcf-fleet-sizing-models-9-x.html
A35: Management Domain vCenter | B35: HA | C35: Large | D35: DES-VC-HA;DES-FLEET-HA;DES-PNP | E35: VCF-VC-REQD-CFG-001;VCF-VC-REQD-CFG-003;VCF-VC-REQD-CFG-005 | F35: vCenter stays 1 appliance; CFG-003 = vSphere HA not VCHA. Size via CFG-005. | G35: https://techdocs.broadcom.com/us/en/vmware-cis/vcf/vcf-9-0-and-later/9-1/design/vmware-cloud-foundation-concepts/vcf-fleet-sizing-models-9-x.html
A36: Management Domain vCenter | B36: Simple | C36: Small | D36: DES-VC-SIMPLE;DES-FLEET-SIMPLE;DES-PNP | E36: VCF-VC-REQD-CFG-001;VCF-VC-REQD-CFG-003;VCF-VC-REQD-CFG-005 | F36: vCenter stays 1 appliance; CFG-003 = vSphere HA not VCHA. Size via CFG-005. | G36: https://techdocs.broadcom.com/us/en/vmware-cis/vcf/vcf-9-0-and-later/9-1/design/vmware-cloud-foundation-concepts/vcf-fleet-sizing-models-9-x.html
A37: Identity Broker | B37: HA | C37: Base | D37: DES-MS-HOSTED;VCF-MS-REQD-COM-001;VCF-MS-REQD-HA-001 | E37: VCF-AUTO-REQD-CFG-004 | F37: Hosted on MS runtime; Auto CFG-004 covers integration. | G37: https://techdocs.broadcom.com/us/en/vmware-cis/vcf/vcf-9-0-and-later/9-1/design/vmware-cloud-foundation-concepts/vcf-management-services-models.html
A38: Identity Broker | B38: Simple | C38: Small | D38: DES-MS-HOSTED;VCF-MS-REQD-COM-001;VCF-MS-REQD-SIM-001 | E38: VCF-AUTO-REQD-CFG-004 | F38: Hosted on MS runtime; Auto CFG-004 covers integration. | G38: https://techdocs.broadcom.com/us/en/vmware-cis/vcf/vcf-9-0-and-later/9-1/design/vmware-cloud-foundation-concepts/vcf-management-services-models.html
A39: License Server | B39: HA | C39: Base | D39: DES-LICENSE;DES-PNP | E39: VCF-LIC-REQD-CFG-001;VCF-LIC-RCMD-CFG-002 | F39: Map to LIC bundle IDs if present. | G39: https://techdocs.broadcom.com/us/en/vmware-cis/vcf/vcf-9-0-and-later/9-1/design/vmware-cloud-foundation-concepts/vcf-fleet-sizing-models-9-x.html
A40: License Server | B40: Simple | C40: Small | D40: DES-LICENSE;DES-PNP | E40: VCF-LIC-REQD-CFG-001;VCF-LIC-RCMD-CFG-002 | F40: Map to LIC bundle IDs if present. | G40: https://techdocs.broadcom.com/us/en/vmware-cis/vcf/vcf-9-0-and-later/9-1/design/vmware-cloud-foundation-concepts/vcf-fleet-sizing-models-9-x.html
A41: Log Management | B41: HA | C41: Medium | D41: DES-MS-HOSTED;VCF-MS-REQD-COM-001;VCF-MS-REQD-HA-001;DES-OPTIONAL-DAYN | F41: No Funnel bridge yet ‚Äî keep DES-PNP / Fleet fallback; extend bridge as needed. | G41: https://techdocs.broadcom.com/us/en/vmware-cis/vcf/vcf-9-0-and-later/9-1/design/vmware-cloud-foundation-concepts/vcf-management-services-models.html
A42: Log Management | B42: HA | C42: Large | D42: DES-MS-HOSTED;VCF-MS-REQD-COM-001;VCF-MS-REQD-HA-001;DES-OPTIONAL-DAYN | F42: No Funnel bridge yet ‚Äî keep DES-PNP / Fleet fallback; extend bridge as needed. | G42: https://techdocs.broadcom.com/us/en/vmware-cis/vcf/vcf-9-0-and-later/9-1/design/vmware-cloud-foundation-concepts/vcf-management-services-models.html
A43: Offline Software Depot | B43: HA | C43: Base | D43: DES-MS-HOSTED;VCF-MS-REQD-COM-001;VCF-MS-REQD-HA-001;DES-OPTIONAL-DAYN | F43: No Funnel bridge yet ‚Äî keep DES-PNP / Fleet fallback; extend bridge as needed. | G43: https://techdocs.broadcom.com/us/en/vmware-cis/vcf/vcf-9-0-and-later/9-1/design/vmware-cloud-foundation-concepts/vcf-management-services-models.html
A44: Protection Blueprint Requirements | B44: HA | C44: Base | D44: DES-PNP;DES-FLEET-HA | F44: No Funnel bridge yet ‚Äî keep DES-PNP / Fleet fallback; extend bridge as needed. | G44: https://techdocs.broadcom.com/us/en/vmware-cis/vcf/vcf-9-0-and-later/9-1/design/vmware-cloud-foundation-concepts/vcf-fleet-sizing-models-9-x.html
A45: Protection Blueprint Requirements | B45: Simple | C45: Small | D45: DES-PNP;DES-FLEET-SIMPLE | F45: No Funnel bridge yet ‚Äî keep DES-PNP / Fleet fallback; extend bridge as needed. | G45: https://techdocs.broadcom.com/us/en/vmware-cis/vcf/vcf-9-0-and-later/9-1/design/vmware-cloud-foundation-concepts/vcf-fleet-sizing-models-9-x.html
A46: Real-time Metrics | B46: HA | C46: Medium | D46: DES-MS-HOSTED;VCF-MS-REQD-COM-001;VCF-MS-REQD-HA-001;DES-OPTIONAL-DAYN | F46: No Funnel bridge yet ‚Äî keep DES-PNP / Fleet fallback; extend bridge as needed. | G46: https://techdocs.broadcom.com/us/en/vmware-cis/vcf/vcf-9-0-and-later/9-1/design/vmware-cloud-foundation-concepts/vcf-management-services-models.html
A47: Real-time Metrics | B47: Simple | C47: Small | D47: DES-MS-HOSTED;VCF-MS-REQD-COM-001;VCF-MS-REQD-SIM-001;DES-OPTIONAL-DAYN | F47: No Funnel bridge yet ‚Äî keep DES-PNP / Fleet fallback; extend bridge as needed. | G47: https://techdocs.broadcom.com/us/en/vmware-cis/vcf/vcf-9-0-and-later/9-1/design/vmware-cloud-foundation-concepts/vcf-management-services-models.html
A48: SDDC Manager | B48: HA | C48: Base | D48: DES-SDDC;DES-PNP | E48: VCF-SDDCMGR-REQD-CFG-001;VCF-SDDCMGR-REQD-CFG-005 | F48: CFG-005: do not alter default SDDC Manager size ‚Äî matches Base footprint. | G48: https://techdocs.broadcom.com/us/en/vmware-cis/vcf/vcf-9-0-and-later/9-1/design/vmware-cloud-foundation-concepts/vcf-fleet-sizing-models-9-x.html
A49: SDDC Manager | B49: Simple | C49: Small | D49: DES-SDDC;DES-PNP | E49: VCF-SDDCMGR-REQD-CFG-001;VCF-SDDCMGR-REQD-CFG-005 | F49: CFG-005: do not alter default SDDC Manager size ‚Äî matches Base footprint. | G49: https://techdocs.broadcom.com/us/en/vmware-cis/vcf/vcf-9-0-and-later/9-1/design/vmware-cloud-foundation-concepts/vcf-fleet-sizing-models-9-x.html
A50: VCF Operations for networks | B50: HA | C50: Medium | D50: DES-PNP;DES-FLEET-HA;DES-OPTIONAL-DAYN | F50: No Funnel bridge yet ‚Äî keep DES-PNP / Fleet fallback; extend bridge as needed. | G50: https://techdocs.broadcom.com/us/en/vmware-cis/vcf/vcf-9-0-and-later/9-1/design/vmware-cloud-foundation-concepts/vcf-fleet-sizing-models-9-x.html
A51: VCF Operations for networks | B51: HA | C51: Large | D51: DES-PNP;DES-FLEET-HA;DES-OPTIONAL-DAYN | F51: No Funnel bridge yet ‚Äî keep DES-PNP / Fleet fallback; extend bridge as needed. | G51: https://techdocs.broadcom.com/us/en/vmware-cis/vcf/vcf-9-0-and-later/9-1/design/vmware-cloud-foundation-concepts/vcf-fleet-sizing-models-9-x.html
A52: VCF Operations for networks | B52: Simple | C52: Small | D52: DES-PNP;DES-FLEET-SIMPLE;DES-OPTIONAL-DAYN | F52: No Funnel bridge yet ‚Äî keep DES-PNP / Fleet fallback; extend bridge as needed. | G52: https://techdocs.broadcom.com/us/en/vmware-cis/vcf/vcf-9-0-and-later/9-1/design/vmware-cloud-foundation-concepts/vcf-fleet-sizing-models-9-x.html
A53: VCF Operations for networks collector | B53: HA | C53: Base | D53: DES-PNP;DES-FLEET-HA;DES-OPTIONAL-DAYN | F53: No Funnel bridge yet ‚Äî keep DES-PNP / Fleet fallback; extend bridge as needed. | G53: https://techdocs.broadcom.com/us/en/vmware-cis/vcf/vcf-9-0-and-later/9-1/design/vmware-cloud-foundation-concepts/vcf-fleet-sizing-models-9-x.html
A54: VCF Operations for networks collector | B54: Simple | C54: Small | D54: DES-PNP;DES-FLEET-SIMPLE;DES-OPTIONAL-DAYN | F54: No Funnel bridge yet ‚Äî keep DES-PNP / Fleet fallback; extend bridge as needed. | G54: https://techdocs.broadcom.com/us/en/vmware-cis/vcf/vcf-9-0-and-later/9-1/design/vmware-cloud-foundation-concepts/vcf-fleet-sizing-models-9-x.html
A55: VCF services runtime control nodes | B55: HA | C55: Medium | D55: VCF-MS-REQD-COM-001;VCF-MS-REQD-COM-002;VCF-MS-REQD-COM-003;VCF-MS-REQD-HA-001 | E55: VCF-CLS-REQD-CFG-001;VCF-CLS-REQD-CFG-002 | F55: No MS runtime IDs in Funnel today ‚Äî add TechDocs SIM/HA rows. Host count still via VCF-CLS-REQD-CFG-001. | G55: https://techdocs.broadcom.com/us/en/vmware-cis/vcf/vcf-9-0-and-later/9-1/design/design-library/vcf-management-services-availabilty-detailed-design/vcf-management-services-high-availability-deployment-model.html
A56: VCF services runtime control nodes | B56: HA | C56: Large | D56: VCF-MS-REQD-COM-001;VCF-MS-REQD-COM-002;VCF-MS-REQD-COM-003;VCF-MS-REQD-HA-001 | E56: VCF-CLS-REQD-CFG-001;VCF-CLS-REQD-CFG-002 | F56: No MS runtime IDs in Funnel today ‚Äî add TechDocs SIM/HA rows. Host count still via VCF-CLS-REQD-CFG-001. | G56: https://techdocs.broadcom.com/us/en/vmware-cis/vcf/vcf-9-0-and-later/9-1/design/design-library/vcf-management-services-availabilty-detailed-design/vcf-management-services-high-availability-deployment-model.html
A57: VCF services runtime control nodes | B57: Simple | C57: Small | D57: VCF-MS-REQD-COM-001;VCF-MS-REQD-COM-002;VCF-MS-REQD-COM-003;VCF-MS-REQD-SIM-001 | E57: VCF-CLS-REQD-CFG-001;VCF-CLS-REQD-CFG-002 | F57: No MS runtime IDs in Funnel today ‚Äî add TechDocs SIM/HA rows. Host count still via VCF-CLS-REQD-CFG-001. | G57: https://techdocs.broadcom.com/us/en/vmware-cis/vcf/vcf-9-0-and-later/9-1/design/design-library/vcf-management-services-availabilty-detailed-design/vcf-management-services-simple-deployment-model.html
A58: VCF services runtime worker nodes | B58: HA | C58: Medium | D58: VCF-MS-REQD-COM-001;VCF-MS-REQD-COM-002;VCF-MS-REQD-COM-003;VCF-MS-REQD-HA-001 | E58: VCF-CLS-REQD-CFG-001;VCF-CLS-REQD-CFG-002 | F58: Same MS TechDocs IDs as control plane (paired topology). | G58: https://techdocs.broadcom.com/us/en/vmware-cis/vcf/vcf-9-0-and-later/9-1/design/design-library/vcf-management-services-availabilty-detailed-design/vcf-management-services-high-availability-deployment-model.html
A59: VCF services runtime worker nodes | B59: HA | C59: Large | D59: VCF-MS-REQD-COM-001;VCF-MS-REQD-COM-002;VCF-MS-REQD-COM-003;VCF-MS-REQD-HA-001 | E59: VCF-CLS-REQD-CFG-001;VCF-CLS-REQD-CFG-002 | F59: Same MS TechDocs IDs as control plane (paired topology). | G59: https://techdocs.broadcom.com/us/en/vmware-cis/vcf/vcf-9-0-and-later/9-1/design/design-library/vcf-management-services-availabilty-detailed-design/vcf-management-services-high-availability-deployment-model.html
A60: VCF services runtime worker nodes | B60: Simple | C60: Small | D60: VCF-MS-REQD-COM-001;VCF-MS-REQD-COM-002;VCF-MS-REQD-COM-003;VCF-MS-REQD-SIM-001 | E60: VCF-CLS-REQD-CFG-001;VCF-CLS-REQD-CFG-002 | F60: Same MS TechDocs IDs as control plane (paired topology). | G60: https://techdocs.broadcom.com/us/en/vmware-cis/vcf/vcf-9-0-and-later/9-1/design/design-library/vcf-management-services-availabilty-detailed-design/vcf-management-services-simple-deployment-model.html
A61: Workload Domain NSX Managers (Local / Global) | B61: HA | C61: Small | D61: DES-NSX-HA;DES-FLEET-HA;DES-PNP | E61: VCF-NSX-LM-REQD-CFG-003;VCF-NSX-LM-REQD-CFG-004;VCF-NSX-LM-REQD-CFG-005 | F61: VI NSX cluster IDs assume dedicated WLD; still HA-oriented. | G61: https://techdocs.broadcom.com/us/en/vmware-cis/vcf/vcf-9-0-and-later/9-1/design/vmware-cloud-foundation-concepts/vcf-fleet-sizing-models-9-x.html
A62: Workload Domain NSX Managers (Local / Global) | B62: HA | C62: Medium | D62: DES-NSX-HA;DES-FLEET-HA;DES-PNP | E62: VCF-NSX-LM-REQD-CFG-003;VCF-NSX-LM-REQD-CFG-004;VCF-NSX-LM-REQD-CFG-005 | F62: VI NSX cluster IDs assume dedicated WLD; still HA-oriented. | G62: https://techdocs.broadcom.com/us/en/vmware-cis/vcf/vcf-9-0-and-later/9-1/design/vmware-cloud-foundation-concepts/vcf-fleet-sizing-models-9-x.html
A63: Workload Domain NSX Managers (Local / Global) | B63: HA | C63: Large | D63: DES-NSX-HA;DES-FLEET-HA;DES-PNP | E63: VCF-NSX-LM-REQD-CFG-003;VCF-NSX-LM-REQD-CFG-004;VCF-NSX-LM-REQD-CFG-005 | F63: VI NSX cluster IDs assume dedicated WLD; still HA-oriented. | G63: https://techdocs.broadcom.com/us/en/vmware-cis/vcf/vcf-9-0-and-later/9-1/design/vmware-cloud-foundation-concepts/vcf-fleet-sizing-models-9-x.html
A64: Workload Domain NSX Managers (Local / Global) | B64: HA | C64: X-Large | D64: DES-NSX-HA;DES-FLEET-HA;DES-PNP | E64: VCF-NSX-LM-REQD-CFG-003;VCF-NSX-LM-REQD-CFG-004;VCF-NSX-LM-REQD-CFG-005 | F64: VI NSX cluster IDs assume dedicated WLD; still HA-oriented. | G64: https://techdocs.broadcom.com/us/en/vmware-cis/vcf/vcf-9-0-and-later/9-1/design/vmware-cloud-foundation-concepts/vcf-fleet-sizing-models-9-x.html
A65: Workload Domain vCenter | B65: HA | C65: Medium | D65: DES-VC-HA;DES-FLEET-HA;DES-PNP | E65: VCF-VC-REQD-CFG-002;VCF-VC-REQD-CFG-005 | F65: Only when VI WLD exists (DEC-ARCH-002). | G65: https://techdocs.broadcom.com/us/en/vmware-cis/vcf/vcf-9-0-and-later/9-1/design/vmware-cloud-foundation-concepts/vcf-fleet-sizing-models-9-x.html
A66: Workload Domain vCenter | B66: HA | C66: Large | D66: DES-VC-HA;DES-FLEET-HA;DES-PNP | E66: VCF-VC-REQD-CFG-002;VCF-VC-REQD-CFG-005 | F66: Only when VI WLD exists (DEC-ARCH-002). | G66: https://techdocs.broadcom.com/us/en/vmware-cis/vcf/vcf-9-0-and-later/9-1/design/vmware-cloud-foundation-concepts/vcf-fleet-sizing-models-9-x.html

Sheet Interop_DB
A1: Product | B1: Source_Version | C1: Target_Version | D1: Status | E1: Upgrade_Path_Notes
A2: Ops | B2: VCF Operations 9.1.0.0300 | C2: VCF Operations 9.1.0.0400 | D2: Compatible | E2: Direct Upgrade Supported
A3: Ops | B3: VCF Operations 9.1.0.0200 | C3: VCF Operations 9.1.0.0400 | D3: Compatible | E3: Direct Upgrade Supported
A4: Ops | B4: VCF Operations 9.1.0.0200 | C4: VCF Operations 9.1.0.0300 | D4: Compatible | E4: Direct Upgrade Supported
A5: Ops | B5: VCF Operations 9.1.0.0100 | C5: VCF Operations 9.1.0.0400 | D5: Compatible | E5: Direct Upgrade Supported
A6: Ops | B6: VCF Operations 9.1.0.0100 | C6: VCF Operations 9.1.0.0300 | D6: Compatible | E6: Direct Upgrade Supported
A7: Ops | B7: VCF Operations 9.1.0.0100 | C7: VCF Operations 9.1.0.0200 | D7: Compatible | E7: Direct Upgrade Supported
A8: Ops | B8: VCF Operations 9.1.0.0 | C8: VCF Operations 9.1.0.0400 | D8: Compatible | E8: Direct Upgrade Supported
A9: Ops | B9: VCF Operations 9.1.0.0 | C9: VCF Operations 9.1.0.0300 | D9: Compatible | E9: Direct Upgrade Supported
A10: Ops | B10: VCF Operations 9.1.0.0 | C10: VCF Operations 9.1.0.0200 | D10: Compatible | E10: Direct Upgrade Supported
A11: Ops | B11: VCF Operations 9.1.0.0 | C11: VCF Operations 9.1.0.0100 | D11: Compatible | E11: Direct Upgrade Supported
A12: Ops | B12: VCF Operations 9.0.2.0200 | C12: VCF Operations 9.1.0.0400 | D12: Compatible | E12: Direct Upgrade Supported
... A2909: vCenter | B2909: VMware vCenter 8.0 | C2909: VMware vCenter 8.0.0a | D2909: Compatible | E2909: Direct Upgrade Supported

Sheet Static Reference Tables
B2: Static Reference Tables
B3: The following values are used for lookups throughout the rest of the workbook
B6: Sizing Value References | E6: Include / Exclude
B7: Constant | C7: Value | E7: Include | F7: Include
B8: vCenter Appliance Size List | C8: Tiny | E8: Exclude | F8: Excluded
B9: vCenter Appliance Size List | C9: Small
B10: vCenter Appliance Size List | C10: Medium | E10: Yes / No | F10: Instance | G10: First Instance | H10: Additional Instance | I10: VVF
B11: vCenter Appliance Size List | C11: Large | E11: Yes | F11: First Instance | G11: Deploy a new VCF fleet | H11: Deploy a VCF Instance in an existing VCF fleet | I11: Deploy new VMware vSphere Foundation
B12: vCenter Appliance Size List | C12: XLarge | E12: No | F12: Additional Instance | G12: Create Workload Domain | H12: Create Workload Domain
B13: vCenter Storage Size List | C13: Default | G13: Create Cluster | H13: Create Cluster
B14: vCenter Storage Size List | C14: Large | E14: Deployment Type | G14: Deploy deferred components | H14: Deploy deferred components
B15: vCenter Storage Size List | C15: XLarge | E15: Full Instance
B16: NSX-T Manager Size List | C16: Extra_Small | E16: None Chosen
B17: NSX-T Manager Size List | C17: Small | E17: Workload Domain
B18: NSX-T Manager Size List | C18: Medium | E18: Cluster
B19: NSX-T Manager Size List | C19: Large | E19: One Or More VVDs
B20: NSX-T Manager Size List | C20: XLarge
B21: NSX-T Edge Size List | C21: Excluded | E21: Deployment Type
B22: NSX-T Edge Size List | C22: NSX Edge Small | E22: None Chosen
B23: NSX-T Edge Size List | C23: NSX Edge Medium | E23: Full Instance
B24: NSX-T Edge Size List | C24: NSX Edge Large | E24: Cluster
B25: NSX-T Edge Size List | C25: NSX Edge XLarge
B26: NSX-T Edge Size List | C26: VNA Small
B27: NSX-T Edge Size List | C27: VNA Medium
B28: NSX-T Edge Size List | C28: VNA Large
B29: NSX-T Edge Size List | C29: VNA XLarge
B31: Lookup Tables
B32: SDDC Manager | C32: Value
B33: CPU | C33: 4
B34: RAM | C34: 16
B35: Disk | C35: 914
B36: vCenter Appliance CPU | C36: Value
B37: Tiny | C37: 2
B38: Small | C38: 4
B39: Medium | C39: 8
B40: Large | C40: 16
B41: XLarge | C41: 24
B42: vCenter Appliance RAM | C42: Value
B43: Tiny | C43: 14
B44: Small | C44: 21
B45: Medium | C45: 30
B46: Large | C46: 39
B47: XLarge | C47: 58
B48: vCenter Disk | C48: Value
B49: TinyDefault | C49: 604
B50: TinyLarge | C50: 1494
B51: TinyXLarge | C51: 2874
B52: SmallDefault | C52: 694
B53: SmallLarge | C53: 1519
B54: SmallXLarge | C54: 2899
B55: MediumDefault | C55: 858
B56: MediumLarge | C56: 1658
B57: MediumXLarge | C57: 3038
B58: LargeDefault | C58: 1158
B59: LargeLarge | C59: 1708
B60: LargeXLarge | C60: 3088
... B63: XLargeXLarge | C63: 3213
B64: NSX-T Manager CPU | C64: Value
B65: Extra_Small | C65: 2
B66: Small | C66: 4
B67: Medium | C67: 6
B68: Large | C68: 12
B69: XLarge | C69: 24
B70: NSX-T Manager RAM | C70: Value
B71: Extra_Small | C71: 8
B72: Small | C72: 16
B73: Medium | C73: 24
B74: Large | C74: 48
B75: XLarge | C75: 96
B76: NSX-T Manager Disk | C76: Value
B77: Extra_Small | C77: 300
B78: Small | C78: 300
B79: Medium | C79: 300
B80: Large | C80: 300
B81: XLarge | C81: 400
B82: NSX-T Edge CPU | C82: Value
B83: NSX Edge Small | C83: 2
B84: NSX Edge Medium | C84: 4
B85: NSX Edge Large | C85: 8
B86: NSX Edge XLarge | C86: 16
B87: VNA Small | C87: 2
B88: VNA Medium | C88: 4
B89: VNA Large | C89: 8
B90: VNA XLarge | C90: 16
B91: NSX-T Edge RAM | C91: Value
B92: NSX Edge Small | C92: 4
B93: NSX Edge Medium | C93: 8
B94: NSX Edge Large | C94: 32
B95: NSX Edge XLarge | C95: 64
B96: VNA Small | C96: 4
B97: VNA Medium | C97: 8
B98: VNA Large | C98: 32
B99: VNA XLarge | C99: 64
B100: NSX-T Edge Disk | C100: Value
B101: NSX Edge Small | C101: 200
B102: NSX Edge Medium | C102: 200
B103: NSX Edge Large | C103: 200
B104: NSX Edge XLarge | C104: 200
B105: VNA Small | C105: 200
B106: VNA Medium | C106: 200
...

Sheet Change Control
B1: New | C1: Old
B2: input_vvs_dr_ntp1_server | C2: input_vvs_dr_ntp1_ip
B3: cluster_vsan_type_chosen | C3: input_cluster_vsan_type
B4: flt_vidb_chosen | C4: input_flt_vidb_deployment_mode
B5: mgmt_vns_chosen | C5: input_mgmt_ec_gateway_type
B6: wld_cl01_vsan_client_network_chosen | C6: input_wld_cl01_vsan_client_network_chosen
B7: vvs_dr_flt_logs_nodea_hostname | C7: input_xreg_logs_nodea_hostname
B8: vvs_dr_flt_logs_nodeb_hostname | C8: input_xreg_logs_nodeb_hostname
B9: vvs_dr_flt_logs_nodec_hostname | C9: input_xreg_logs_nodec_hostname
B10: vvs_dr_flt_net_nodea_hostname | C10: input_xreg_net_nodea_hostname
B11: vvs_dr_flt_net_nodeb_hostname | C11: input_xreg_net_nodeb_hostname
B12: vvs_dr_flt_net_nodeb_hostname | C12: input_xreg_net_nodec_hostname
... B36: mgmt_vcfops_appliance_size_chosen | C36: xreg_vrops_appliance_size_chosen

Sheet Arkham
A1: Added Stuff
A2: pnp_version_history | B2: 91001 | W2: 9.0 PnP Fields
A3: Fleet Deployment CIDR | B3: =IF(flt_custom_network_chosen="Shared Management Network",IF(mgmt_dpg_reuse_result="Included",CONCATENATE(prefix_mgmt_az1_cidr,"10.0/24"),CONCATENATE(prefix_mgmt_az1_cidr,"11.0/24")),IF(flt_custom_network_chosen="Overlay",CONCATENATE(prefix_xreg_cidr,".0/24"),CONCATENATE(prefix_flt_shared_cidr,".0/24"))) -> #REF! | W3: Network Traffic: NSX
A4: Fleet Deployment Network | B4: =IF(flt_custom_network_chosen="Shared Management Network",IF(mgmt_dpg_reuse_result="Included",CONCATENATE(prefix_mgmt_az1_cidr,"10.0"),CONCATENATE(prefix_mgmt_az1_cidr,"11.0")),IF(flt_custom_network_chosen="Overlay",CONCATENATE(prefix_xreg_cidr,".0"),CONCATENATE(prefix_flt_shared_cidr,".0"))) -> #REF! | W4: Transport Zones
A5: Fleet Deployment Gateway IP | B5: =IF(flt_custom_network_chosen="Shared Management Network",IF(mgmt_dpg_reuse_result="Included",CONCATENATE(prefix_mgmt_az1_cidr,"10.1"),CONCATENATE(prefix_mgmt_az1_cidr,"11.1")),IF(flt_custom_network_chosen="Overlay",CONCATENATE(prefix_xreg_cidr,".1"),CONCATENATE(prefix_flt_shared_cidr,".1"))) -> #REF! | W5: Transport Zone Name | X5: =CONCATENATE("overlay-tz-",this_instance,"-m01-nsx01") -> #REF! | Z5: =IF(mgmt_domain_existing_vcenter_chosen="Selected","Inputs are masked out as you have opted to import an existing vCenter Server", IF(mgmt_cl01_vds_profile_chosen="Storage Traffic Separation","Overlay Traffic will be configured on Primary Distributed Switch", IF(mgmt_cl01_vds_profile_chosen="NSX Traffic Separation","Overlay Traffic will be configured on Secondary Distributed Switch", IF(mgmt_cl01_vds_profile_chosen="Storage Traffic and NSX Traffic Separation","Overlay Traffic will be configured on Tertiary Distributed Switch", IF(mgmt_cl01_vds_profile_chosen="Custom","","Overlay Traffic will be configured on Primary Distributed Switch"))))) -> #REF!
A6: Fleet Deployment Mask | B6: 255.255.255.0 | W6: Pool name | X6: =CONCATENATE(this_instance,"01-m01","-r01-ip-pool01-host") -> #REF! | Z6: =IF(mgmt_host_overlay_addressing_chosen<>"IP Pool","This input is masked out and only required if configuring IP Pools for Host Overlay","") -> #REF!
A7: Fleet Deployment MTU | B7: 9000 | W7: Description | X7: ESX Host Overlay TEP IP Pool | Z7: =IF(mgmt_host_overlay_addressing_chosen<>"IP Pool","This input is masked out and only required if configuring IP Pools for Host Overlay","") -> #REF!
A8: Fleet Deployment VLANID | B8: =CONCATENATE(MID(B5, FIND(".",B5)+1, FIND(".",B5,FIND(".",B5)+1) - FIND(".",B5) - 1),MID(B5, FIND(".", B5, FIND(".", B5)+1)+1, FIND(".", B5, FIND(".", B5, FIND(".", B5)+1)+1) - (FIND(".", B5, FIND(".", B5)+1)+1) )) -> #REF!
W9: Fleet management appliance
A10: Moved Stuff | W10: Use same password as VCF Operations | X10: Unselected | Y10: Unselected | Z10: =IF(mgmt_domain_password_creation_chosen="Selected","Inputs are masked out as you have opted to deploy with system generated passwords","") -> #REF!
A11: Child DNS Zone | B11: =CONCATENATE(this_instance,".rainpole.io") -> #REF!
A12: vSAN Witness DNS Zone | B12: =CONCATENATE(other_instance,".rainpole.io") -> #REF! | W12: VCF-A
A13: DNS Server 1 (Cross-Instance Components) | B13: =IF(mgmt_dpg_reuse_result="Included",CONCATENATE(prefix_mgmt_az1_cidr,"10.4"),CONCATENATE(prefix_mgmt_az1_cidr,"11.4")) -> #REF! | W13: Certifcate
A14: DNS Server 2 (Cross-Instance Components) | B14: =IF(mgmt_dpg_reuse_result="Included",CONCATENATE(prefix_mgmt_az1_cidr,"10.5"),CONCATENATE(prefix_mgmt_az1_cidr,"11.5")) -> #REF! | W14: Add Certifcate | X14: Generate Certificate | Y14: Generate Certificate | Z14: =IF(vcf_automation_cert_type_chosen="Generate Certificate","Create a self signed cert in VMware Cloud Foundation Operations",IF(vcf_automation_cert_type_chosen="Import Certificate","Import a signed cert from your CA","")) -> Create a self signed cert in VMware Cloud Foundation Operations
A15: Domain Controller | B15: =CONCATENATE(this_instance,"-ad01") -> #REF! | W15: Alias | X15: =CONCATENATE(prefix_portable_component,"-auto01","-cert") -> flt-auto01-cert
A16: SMTP Server | B16: smtp.rainpole.io | W16: Certificate File | X16: =CONCATENATE(prefix_portable_component,"-auto01","-cert.pem") -> flt-auto01-cert.pem
A17: SMTP Server Port | B17: 25 | W17: Common Name (CN) | X17: =CONCATENATE(prefix_portable_component,"-auto01.",sample_parent_dns_zone) -> #REF!
A18: NTP Server 1 (Cross-Instance Components) | B18: =CONCATENATE("ntp.",this_instance,".rainpole.io") -> #REF! | W18: Organization (O) | X18: Rainpole
A19: NTP Server 2 (Cross-Instance Components) | B19: =CONCATENATE("ntp.",other_instance,".rainpole.io") -> #REF! | W19: Organization (OU) | X19: IT
B20: =CONCATENATE(prefix_wld_az1_rack_cidr,"23.0/24") -> #REF! | W20: Country Code (C) | X20: US
B21: =CONCATENATE(prefix_wld_az1_rack_cidr,"24.0/24") -> #REF! | W21: Locality (L) | X21: San Francisco
B22: =CONCATENATE(prefix_wld_az1_rack_cidr,"26.0/24") -> #REF! | W22: State (ST) | X22: CA
B23: =CONCATENATE(prefix_wld_az1_rack_cidr,"25.0/24") -> #REF! | W23: Key Length | X23: 4096 | Y23: 4096
B24: =CONCATENATE(prefix_wld_az1_rack_cidr,"34.0/24") -> #REF! | W24: Select Certificate | X24: =sample_vcf_automation_cert_alias -> flt-auto01-cert
B25: =CONCATENATE(prefix_wld_az1_rack_cidr,"35.0/24") -> #REF! | W25: Infrastructure
B26: =CONCATENATE(prefix_wld_az1_rack_cidr,"37.0/24") -> #REF! | W26: Select vCenter Server | X26: =sample_mgmt_vc_fqdn -> #REF! | Y26: =mgmt_vc_fqdn -> #REF!
B27: =CONCATENATE(prefix_wld_az1_rack_cidr,"36.0/24") -> #REF! | W27: Select Cluster | X27: =CONCATENATE(sample_mgmt_datacenter,"#",sample_mgmt_cl01_cluster) -> #REF!
B28: =CONCATENATE(prefix_wld_az1_rack_cidr,"45.0/24") -> #REF! | W28: Select Folder | X28: =CONCATENATE(this_instance,"-m01-cl01-fd-vcfauto01") -> #REF! | Z28: Must be available in vCenter prior to running workflow
B29: =CONCATENATE(prefix_wld_az1_rack_cidr,"46.0/24") -> #REF! | W29: Select Resource Pool | X29: =CONCATENATE(this_instance,"-m01-cl01-rp-vcfauto01") -> #REF! | Z29: Must be available in vCenter prior to running workflow
B30: =CONCATENATE(prefix_wld_az1_rack_cidr,"48.0/24") -> #REF! | W30: Select Network | X30: =IF(OR(flt_custom_network_chosen="NSX Overlay segment",flt_custom_network_chosen="NSX VLAN segment"),CONCATENATE(prefix_portable_component,"-m01-seg01"),IF(flt_custom_network_chosen="Dedicated Management Network",CONCATENATE(this_instance,"-m01-cl01-vds01-pg-flt-mgmt"),CONCATENATE(this_instance,"-m01-cl01-vds01-pg-vm-mgmt"))) -> #REF! | Z30: Must be available in vCenter prior to running workflow
B31: =CONCATENATE(prefix_wld_az1_rack_cidr,"47.0/24") -> #REF! | W31: Select Datastore | X31: =sample_mgmt_cl01_vsan_datastore -> #REF!
B32: =CONCATENATE(prefix_wld_az1_rack_cidr,"56.0/24") -> #REF! | W32: Network
B33: =CONCATENATE(prefix_wld_az1_rack_cidr,"57.0/24") -> #REF! | W33: Domain Name | X33: =sample_parent_dns_zone -> #REF! | Y33: =parent_dns_zone -> #REF!
B34: =CONCATENATE(prefix_wld_az1_rack_cidr,"59.0/24") -> #REF! | W34: Domain Search Path | X34: =sample_parent_dns_zone -> #REF! | Y34: =parent_dns_zone -> #REF!
B35: =CONCATENATE(prefix_wld_az1_rack_cidr,"58.0/24") -> #REF! | W35: DNS Servers | X35: =CONCATENATE(sample_region_dns1_ip,",",sample_region_dns2_ip) -> #REF! | Y35: =CONCATENATE(region_dns1_ip,",",region_dns2_ip) -> #REF!
B36: =CONCATENATE(prefix_wld_az1_rack_cidr,"67.0/24") -> #REF! | W36: Time Sync Mode | X36: Use NTP Server | Y36: Use NTP Server
B37: =CONCATENATE(prefix_wld_az1_rack_cidr,"68.0/24") -> #REF! | W37: NTP Servers | X37: =CONCATENATE(sample_region_ntp1_server,",",sample_region_ntp2_server) -> #REF! | Y37: =CONCATENATE(region_ntp1_server,",",region_ntp2_server) -> #REF!
B38: =CONCATENATE(prefix_wld_az1_rack_cidr,"70.0/24") -> #REF! | W38: Default IPv4 Gateway | X38: =IF(flt_custom_network_chosen="Shared Management Network",IF(mgmt_dpg_reuse_result="Included",CONCATENATE(prefix_mgmt_az1_cidr,"10.1"),CONCATENATE(prefix_mgmt_az1_cidr,"11.1")),IF(flt_custom_network_chosen="NSX Overlay Segment",CONCATENATE(prefix_xreg_cidr,".1"),CONCATENATE(prefix_flt_shared_cidr,".1"))) -> #REF!
B39: =CONCATENATE(prefix_wld_az1_rack_cidr,"69.0/24") -> #REF! | W39: IPv4 Netmask | X39: 255.255.255.0
B40: =CONCATENATE(prefix_wld_az1_rack_cidr,"78.0/24") -> #REF! | W40: Components
B41: =CONCATENATE(prefix_wld_az1_rack_cidr,"79.0/24") -> #REF! | W41: VMware System User Password Alias | X41: flt-auto01-admin-password
B42: =CONCATENATE(prefix_wld_az1_rack_cidr,"81.0/24") -> #REF! | W42: VMware System User Password Description | X42: VCF Automation Admin Password
B43: =CONCATENATE(prefix_wld_az1_rack_cidr,"80.0/24") -> #REF! | W43: VMware System Username | X43: admin
B44: =CONCATENATE(prefix_wld_az1_rack_cidr,"89.0/24") -> #REF! | W44: Root Password Alias | X44: =CONCATENATE(prefix_portable_component,"-auto01","-password") -> flt-auto01-password
B45: =CONCATENATE(prefix_wld_az1_rack_cidr,"90.0/24") -> #REF! | W45: Root Password | X45: VMw@re1!VMw@re1!
B46: =CONCATENATE(prefix_wld_az1_rack_cidr,"92.0/24") -> #REF! | W46: Root Password Description | X46: VCF Automation root Password
B47: =CONCATENATE(prefix_wld_az1_rack_cidr,"91.0/24") -> #REF! | W47: Root Username | X47: root
W48: vCenter Server List | X48: =sample_mgmt_vc_fqdn -> #REF!
B49: MGMT Exisitng NSX-GM | C49: =IF(ISBLANK(input_mgmt_existing_active_nsx_gm),"Value Missing",input_mgmt_existing_active_nsx_gm) -> #REF! | W49: FQDN | X49: =sample_vcf_automation_vip_fqdn -> #REF! | Y49: {=vcf_automation_vip_fqdn} -> #REF!
B50: Cross instance Tier 0 | C50: =IF(ISBLANK(input_mgmt_existing_cross_instance_t0_name),"Value Missing",input_mgmt_existing_cross_instance_t0_name) -> #REF! | W50: Certifcate | X50: =sample_vcf_automation_cert_alias -> flt-auto01-cert | Y50: {=vcf_automation_cert_alias} -> Value Missing
W51: FQDN | X51: =sample_vcf_automation_vip_fqdn -> #REF! | Y51: {=vcf_automation_vip_fqdn} -> #REF!
W52: Controller Type | X52: Internal Load Balancer | Y52: Internal Load Balancer
W53: Node Prefix | X53: =CONCATENATE(prefix_portable_component,"-auto") -> flt-auto | Y53: flt-auto | Z53: VCF Automation virtual machines will be deployed with flt-auto-<generated id>
W54: Primary VIP | X54: =sample_vcf_automation_vip_ip -> #REF! | Y54: {=vcf_automation_vip_ip} -> #REF!
B55: Rack2 | C55: Input | E55: Rack3 | F55: Input | H55: Rack4 | I55: Input | K55: Rack5 | L55: Input | N55: Rack6 | O55: Input | Q55: Rack7 | R55: Input | T55: Rack8 | U55: Input | W55: Internal Cluster CIDR | X55: 192.18.0.0/15 | Y55: 192.18.0.0/15 | Z55: The CIDR used for pods running the internal Kubernetes cluster
A56: VLAN Uplink1 | B56: =IF(cluster_wld_domain_chosen="VI Workload Domain",(CONCATENATE(prefix_wld_az1_vlan,"28")),(CONCATENATE(prefix_mgmt_az1_vlan,"28"))) -> #REF! | E56: =IF(cluster_wld_domain_chosen="VI Workload Domain",(CONCATENATE(prefix_wld_az1_vlan,"39")),(CONCATENATE(prefix_mgmt_az1_vlan,"39"))) -> #REF! | H56: =IF(cluster_wld_domain_chosen="VI Workload Domain",(CONCATENATE(prefix_wld_az1_vlan,"50")),(CONCATENATE(prefix_mgmt_az1_vlan,"50"))) -> #REF! | K56: =IF(cluster_wld_domain_chosen="VI Workload Domain",(CONCATENATE(prefix_wld_az1_vlan,"61")),(CONCATENATE(prefix_mgmt_az1_vlan,"61"))) -> #REF! | N56: =IF(cluster_wld_domain_chosen="VI Workload Domain",(CONCATENATE(prefix_wld_az1_vlan,"72")),(CONCATENATE(prefix_mgmt_az1_vlan,"72"))) -> #REF! | Q56: =IF(cluster_wld_domain_chosen="VI Workload Domain",(CONCATENATE(prefix_wld_az1_vlan,"83")),(CONCATENATE(prefix_mgmt_az1_vlan,"83"))) -> #REF! | T56: =IF(cluster_wld_domain_chosen="VI Workload Domain",(CONCATENATE(prefix_wld_az1_vlan,"94")),(CONCATENATE(prefix_mgmt_az1_vlan,"94"))) -> #REF! | W56: Additional VIPs | X56: N/A
A57: VLAN Uplink2 | B57: =IF(cluster_wld_domain_chosen="VI Workload Domain",(CONCATENATE(prefix_wld_az1_vlan,"29")),(CONCATENATE(prefix_mgmt_az1_vlan,"29"))) -> #REF! | E57: =IF(cluster_wld_domain_chosen="VI Workload Domain",(CONCATENATE(prefix_wld_az1_vlan,"40")),(CONCATENATE(prefix_mgmt_az1_vlan,"40"))) -> #REF! | H57: =IF(cluster_wld_domain_chosen="VI Workload Domain",(CONCATENATE(prefix_wld_az1_vlan,"51")),(CONCATENATE(prefix_mgmt_az1_vlan,"51"))) -> #REF! | K57: =IF(cluster_wld_domain_chosen="VI Workload Domain",(CONCATENATE(prefix_wld_az1_vlan,"62")),(CONCATENATE(prefix_mgmt_az1_vlan,"62"))) -> #REF! | N57: =IF(cluster_wld_domain_chosen="VI Workload Domain",(CONCATENATE(prefix_wld_az1_vlan,"73")),(CONCATENATE(prefix_mgmt_az1_vlan,"73"))) -> #REF! | Q57: =IF(cluster_wld_domain_chosen="VI Workload Domain",(CONCATENATE(prefix_wld_az1_vlan,"84")),(CONCATENATE(prefix_mgmt_az1_vlan,"84"))) -> #REF! | T57: =IF(cluster_wld_domain_chosen="VI Workload Domain",(CONCATENATE(prefix_wld_az1_vlan,"95")),(CONCATENATE(prefix_mgmt_az1_vlan,"95"))) -> #REF! | W57: Cluster Node IP Pool #1 | X57: =IF(flt_custom_network_chosen="Shared Management Network",IF(mgmt_dpg_reuse_result="Included",CONCATENATE(prefix_mgmt_az1_cidr,"10.40"),CONCATENATE(prefix_mgmt_az1_cidr,"11.40")),IF(flt_custom_network_chosen="NSX Overlay Segment",CONCATENATE(prefix_xreg_cidr,".40"),CONCATENATE(prefix_flt_shared_cidr,".40"))) -> #REF!
A58: VLAN Edge Overlay | B58: =IF(cluster_wld_domain_chosen="VI Workload Domain",(CONCATENATE(prefix_wld_az1_vlan,"30")),(CONCATENATE(prefix_mgmt_az1_vlan,"30"))) -> #REF! | E58: =IF(cluster_wld_domain_chosen="VI Workload Domain",(CONCATENATE(prefix_wld_az1_vlan,"41")),(CONCATENATE(prefix_mgmt_az1_vlan,"41"))) -> #REF! | H58: =IF(cluster_wld_domain_chosen="VI Workload Domain",(CONCATENATE(prefix_wld_az1_vlan,"52")),(CONCATENATE(prefix_mgmt_az1_vlan,"52"))) -> #REF! | K58: =IF(cluster_wld_domain_chosen="VI Workload Domain",(CONCATENATE(prefix_wld_az1_vlan,"63")),(CONCATENATE(prefix_mgmt_az1_vlan,"63"))) -> #REF! | N58: =IF(cluster_wld_domain_chosen="VI Workload Domain",(CONCATENATE(prefix_wld_az1_vlan,"74")),(CONCATENATE(prefix_mgmt_az1_vlan,"74"))) -> #REF! | Q58: =IF(cluster_wld_domain_chosen="VI Workload Domain",(CONCATENATE(prefix_wld_az1_vlan,"85")),(CONCATENATE(prefix_mgmt_az1_vlan,"85"))) -> #REF! | T58: =IF(cluster_wld_domain_chosen="VI Workload Domain",(CONCATENATE(prefix_wld_az1_vlan,"96")),(CONCATENATE(prefix_mgmt_az1_vlan,"96"))) -> #REF! | W58: Cluster Node IP Pool #2 | X58: =IF(flt_custom_network_chosen="Shared Management Network",IF(mgmt_dpg_reuse_result="Included",CONCATENATE(prefix_mgmt_az1_cidr,"10.41"),CONCATENATE(prefix_mgmt_az1_cidr,"11.41")),IF(flt_custom_network_chosen="NSX Overlay Segment",CONCATENATE(prefix_xreg_cidr,".41"),CONCATENATE(prefix_flt_shared_cidr,".41"))) -> #REF!
A59: Network Uplink1 | B59: =IF(cluster_wld_domain_chosen="VI Workload Domain",CONCATENATE(prefix_wld_az1_cidr,"28.0"),CONCATENATE(prefix_mgmt_az1_cidr,"28.0")) -> #REF! | E59: =IF(cluster_wld_domain_chosen="VI Workload Domain",CONCATENATE(prefix_wld_az1_cidr,"39.0"),CONCATENATE(prefix_mgmt_az1_cidr,"39.0")) -> #REF! | H59: =IF(cluster_wld_domain_chosen="VI Workload Domain",CONCATENATE(prefix_wld_az1_cidr,"50.0"),CONCATENATE(prefix_mgmt_az1_cidr,"50.0")) -> #REF! | K59: =IF(cluster_wld_domain_chosen="VI Workload Domain",CONCATENATE(prefix_wld_az1_cidr,"61.0"),CONCATENATE(prefix_mgmt_az1_cidr,"61.0")) -> #REF! | N59: =IF(cluster_wld_domain_chosen="VI Workload Domain",CONCATENATE(prefix_wld_az1_cidr,"72.0"),CONCATENATE(prefix_mgmt_az1_cidr,"72.0")) -> #REF! | Q59: =IF(cluster_wld_domain_chosen="VI Workload Domain",CONCATENATE(prefix_wld_az1_cidr,"83.0"),CONCATENATE(prefix_mgmt_az1_cidr,"83.0")) -> #REF! | T59: =IF(cluster_wld_domain_chosen="VI Workload Domain",CONCATENATE(prefix_wld_az1_cidr,"94.0"),CONCATENATE(prefix_mgmt_az1_cidr,"94.0")) -> #REF! | W59: Cluster Node IP Pool #3 | X59: =IF(flt_custom_network_chosen="Shared Management Network",IF(mgmt_dpg_reuse_result="Included",CONCATENATE(prefix_mgmt_az1_cidr,"10.42"),CONCATENATE(prefix_mgmt_az1_cidr,"11.42")),IF(flt_custom_network_chosen="NSX Overlay Segment",CONCATENATE(prefix_xreg_cidr,".42"),CONCATENATE(prefix_flt_shared_cidr,".42"))) -> #REF!
A60: Network Uplink2 | B60: =IF(cluster_wld_domain_chosen="VI Workload Domain",CONCATENATE(prefix_wld_az1_cidr,"29.0"),CONCATENATE(prefix_mgmt_az1_cidr,"29.0")) -> #REF! | E60: =IF(cluster_wld_domain_chosen="VI Workload Domain",CONCATENATE(prefix_wld_az1_cidr,"40.0"),CONCATENATE(prefix_mgmt_az1_cidr,"40.0")) -> #REF! | H60: =IF(cluster_wld_domain_chosen="VI Workload Domain",CONCATENATE(prefix_wld_az1_cidr,"51.0"),CONCATENATE(prefix_mgmt_az1_cidr,"51.0")) -> #REF! | K60: =IF(cluster_wld_domain_chosen="VI Workload Domain",CONCATENATE(prefix_wld_az1_cidr,"62.0"),CONCATENATE(prefix_mgmt_az1_cidr,"62.0")) -> #REF! | N60: =IF(cluster_wld_domain_chosen="VI Workload Domain",CONCATENATE(prefix_wld_az1_cidr,"73.0"),CONCATENATE(prefix_mgmt_az1_cidr,"73.0")) -> #REF! | Q60: =IF(cluster_wld_domain_chosen="VI Workload Domain",CONCATENATE(prefix_wld_az1_cidr,"84.0"),CONCATENATE(prefix_mgmt_az1_cidr,"84.0")) -> #REF! | T60: =IF(cluster_wld_domain_chosen="VI Workload Domain",CONCATENATE(prefix_wld_az1_cidr,"95.0"),CONCATENATE(prefix_mgmt_az1_cidr,"95.0")) -> #REF! | W60: Cluster Node IP Pool #4 | X60: =IF(flt_custom_network_chosen="Shared Management Network",IF(mgmt_dpg_reuse_result="Included",CONCATENATE(prefix_mgmt_az1_cidr,"10.43"),CONCATENATE(prefix_mgmt_az1_cidr,"11.43")),IF(flt_custom_network_chosen="NSX Overlay Segment",CONCATENATE(prefix_xreg_cidr,".43"),CONCATENATE(prefix_flt_shared_cidr,".43"))) -> #REF!
A61: Network Edge Overlay | B61: =IF(cluster_wld_domain_chosen="VI Workload Domain",CONCATENATE(prefix_wld_az1_cidr,"30.0"),CONCATENATE(prefix_mgmt_az1_cidr,"30.0")) -> #REF! | E61: =IF(cluster_wld_domain_chosen="VI Workload Domain",CONCATENATE(prefix_wld_az1_cidr,"41.0"),CONCATENATE(prefix_mgmt_az1_cidr,"41.0")) -> #REF! | H61: =IF(cluster_wld_domain_chosen="VI Workload Domain",CONCATENATE(prefix_wld_az1_cidr,"52.0"),CONCATENATE(prefix_mgmt_az1_cidr,"52.0")) -> #REF! | K61: =IF(cluster_wld_domain_chosen="VI Workload Domain",CONCATENATE(prefix_wld_az1_cidr,"63.0"),CONCATENATE(prefix_mgmt_az1_cidr,"63.0")) -> #REF! | N61: =IF(cluster_wld_domain_chosen="VI Workload Domain",CONCATENATE(prefix_wld_az1_cidr,"74.0"),CONCATENATE(prefix_mgmt_az1_cidr,"74.0")) -> #REF! | Q61: =IF(cluster_wld_domain_chosen="VI Workload Domain",CONCATENATE(prefix_wld_az1_cidr,"85.0"),CONCATENATE(prefix_mgmt_az1_cidr,"85.0")) -> #REF! | T61: =IF(cluster_wld_domain_chosen="VI Workload Domain",CONCATENATE(prefix_wld_az1_cidr,"96.0"),CONCATENATE(prefix_mgmt_az1_cidr,"96.0")) -> #REF! | W61: Cluster Node IP Pool #5 | X61: =IF(flt_custom_network_chosen="Shared Management Network",IF(mgmt_dpg_reuse_result="Included",CONCATENATE(prefix_mgmt_az1_cidr,"10.44"),CONCATENATE(prefix_mgmt_az1_cidr,"11.44")),IF(flt_custom_network_chosen="NSX Overlay Segment",CONCATENATE(prefix_xreg_cidr,".44"),CONCATENATE(prefix_flt_shared_cidr,".44"))) -> #REF!
A62: Gateway Uplink1 | B62: =IF(cluster_wld_domain_chosen="VI Workload Domain",CONCATENATE(prefix_wld_az1_cidr,"28.1"),CONCATENATE(prefix_mgmt_az1_cidr,"28.1")) -> #REF! | E62: =IF(cluster_wld_domain_chosen="VI Workload Domain",CONCATENATE(prefix_wld_az1_cidr,"39.1"),CONCATENATE(prefix_mgmt_az1_cidr,"39.1")) -> #REF! | H62: =IF(cluster_wld_domain_chosen="VI Workload Domain",CONCATENATE(prefix_wld_az1_cidr,"50.1"),CONCATENATE(prefix_mgmt_az1_cidr,"50.1")) -> #REF! | K62: =IF(cluster_wld_domain_chosen="VI Workload Domain",CONCATENATE(prefix_wld_az1_cidr,"61.1"),CONCATENATE(prefix_mgmt_az1_cidr,"61.1")) -> #REF! | N62: =IF(cluster_wld_domain_chosen="VI Workload Domain",CONCATENATE(prefix_wld_az1_cidr,"72.1"),CONCATENATE(prefix_mgmt_az1_cidr,"72.1")) -> #REF! | Q62: =IF(cluster_wld_domain_chosen="VI Workload Domain",CONCATENATE(prefix_wld_az1_cidr,"83.1"),CONCATENATE(prefix_mgmt_az1_cidr,"83.1")) -> #REF! | T62: =IF(cluster_wld_domain_chosen="VI Workload Domain",CONCATENATE(prefix_wld_az1_cidr,"94.1"),CONCATENATE(prefix_mgmt_az1_cidr,"94.1")) -> #REF! | W62: Cluster Node IP Pool #6 | X62: =IF(flt_custom_network_chosen="Shared Management Network",IF(mgmt_dpg_reuse_result="Included",CONCATENATE(prefix_mgmt_az1_cidr,"10.45"),CONCATENATE(prefix_mgmt_az1_cidr,"11.45")),IF(flt_custom_network_chosen="NSX Overlay Segment",CONCATENATE(prefix_xreg_cidr,".45"),CONCATENATE(prefix_flt_shared_cidr,".45"))) -> #REF!
A63: Gateway Uplink2 | B63: =IF(cluster_wld_domain_chosen="VI Workload Domain",CONCATENATE(prefix_wld_az1_cidr,"29.1"),CONCATENATE(prefix_mgmt_az1_cidr,"29.1")) -> #REF! | E63: =IF(cluster_wld_domain_chosen="VI Workload Domain",CONCATENATE(prefix_wld_az1_cidr,"40.1"),CONCATENATE(prefix_mgmt_az1_cidr,"40.1")) -> #REF! | H63: =IF(cluster_wld_domain_chosen="VI Workload Domain",CONCATENATE(prefix_wld_az1_cidr,"51.1"),CONCATENATE(prefix_mgmt_az1_cidr,"51.1")) -> #REF! | K63: =IF(cluster_wld_domain_chosen="VI Workload Domain",CONCATENATE(prefix_wld_az1_cidr,"62.1"),CONCATENATE(prefix_mgmt_az1_cidr,"62.1")) -> #REF! | N63: =IF(cluster_wld_domain_chosen="VI Workload Domain",CONCATENATE(prefix_wld_az1_cidr,"73.1"),CONCATENATE(prefix_mgmt_az1_cidr,"73.1")) -> #REF! | Q63: =IF(cluster_wld_domain_chosen="VI Workload Domain",CONCATENATE(prefix_wld_az1_cidr,"84.1"),CONCATENATE(prefix_mgmt_az1_cidr,"84.1")) -> #REF! | T63: =IF(cluster_wld_domain_chosen="VI Workload Domain",CONCATENATE(prefix_wld_az1_cidr,"95.1"),CONCATENATE(prefix_mgmt_az1_cidr,"95.1")) -> #REF!
A64: Gateway Edge Overlay | B64: =IF(cluster_wld_domain_chosen="VI Workload Domain",CONCATENATE(prefix_wld_az1_cidr,"30.1"),CONCATENATE(prefix_mgmt_az1_cidr,"30.1")) -> #REF! | E64: =IF(cluster_wld_domain_chosen="VI Workload Domain",CONCATENATE(prefix_wld_az1_cidr,"41.1"),CONCATENATE(prefix_mgmt_az1_cidr,"41.1")) -> #REF! | H64: =IF(cluster_wld_domain_chosen="VI Workload Domain",CONCATENATE(prefix_wld_az1_cidr,"52.1"),CONCATENATE(prefix_mgmt_az1_cidr,"52.1")) -> #REF! | K64: =IF(cluster_wld_domain_chosen="VI Workload Domain",CONCATENATE(prefix_wld_az1_cidr,"63.1"),CONCATENATE(prefix_mgmt_az1_cidr,"63.1")) -> #REF! | N64: =IF(cluster_wld_domain_chosen="VI Workload Domain",CONCATENATE(prefix_wld_az1_cidr,"74.1"),CONCATENATE(prefix_mgmt_az1_cidr,"74.1")) -> #REF! | Q64: =IF(cluster_wld_domain_chosen="VI Workload Domain",CONCATENATE(prefix_wld_az1_cidr,"85.1"),CONCATENATE(prefix_mgmt_az1_cidr,"85.1")) -> #REF! | T64: =IF(cluster_wld_domain_chosen="VI Workload Domain",CONCATENATE(prefix_wld_az1_cidr,"96.1"),CONCATENATE(prefix_mgmt_az1_cidr,"96.1")) -> #REF!
A65: Mask Uplink1 | B65: 255.255.255.0 | E65: 255.255.255.0 | H65: 255.255.255.0 | K65: 255.255.255.0 | N65: 255.255.255.0 | Q65: 255.255.255.0 | T65: 255.255.255.0
A66: Mask Uplink2 | B66: 255.255.255.0 | E66: 255.255.255.0 | H66: 255.255.255.0 | K66: 255.255.255.0 | N66: 255.255.255.0 | Q66: 255.255.255.0 | T66: 255.255.255.0
A67: Mask Edge Overlay | B67: 255.255.255.0 | E67: 255.255.255.0 | H67: 255.255.255.0 | K67: 255.255.255.0 | N67: 255.255.255.0 | Q67: 255.255.255.0 | T67: 255.255.255.0
A68: MTU Uplink1 | B68: 9000 | E68: 9000 | H68: 9000 | K68: 9000 | N68: 9000 | Q68: 9000 | T68: 9000
A69: MTU Uplink2 | B69: 9000 | E69: 9000 | H69: 9000 | K69: 9000 | N69: 9000 | Q69: 9000 | T69: 9000
A70: MTU Edge Overlay | B70: 9000 | E70: 9000 | H70: 9000 | K70: 9000 | N70: 9000 | Q70: 9000 | T70: 9000
A71: Edge Overlay Pool: Start IP | B71: =IF(cluster_wld_domain_chosen="VI Workload Domain",CONCATENATE(prefix_wld_az1_cidr,"30.2"),CONCATENATE(prefix_mgmt_az1_cidr,"30.2")) -> #REF! | E71: =IF(cluster_wld_domain_chosen="VI Workload Domain",CONCATENATE(prefix_wld_az1_cidr,"41.2"),CONCATENATE(prefix_mgmt_az1_cidr,"41.2")) -> #REF! | H71: =IF(cluster_wld_domain_chosen="VI Workload Domain",CONCATENATE(prefix_wld_az1_cidr,"52.2"),CONCATENATE(prefix_mgmt_az1_cidr,"52.2")) -> #REF! | K71: =IF(cluster_wld_domain_chosen="VI Workload Domain",CONCATENATE(prefix_wld_az1_cidr,"63.2"),CONCATENATE(prefix_mgmt_az1_cidr,"63.2")) -> #REF! | N71: =IF(cluster_wld_domain_chosen="VI Workload Domain",CONCATENATE(prefix_wld_az1_cidr,"74.2"),CONCATENATE(prefix_mgmt_az1_cidr,"74.2")) -> #REF! | Q71: =IF(cluster_wld_domain_chosen="VI Workload Domain",CONCATENATE(prefix_wld_az1_cidr,"85.2"),CONCATENATE(prefix_mgmt_az1_cidr,"85.2")) -> #REF! | T71: =IF(cluster_wld_domain_chosen="VI Workload Domain",CONCATENATE(prefix_wld_az1_cidr,"96.2"),CONCATENATE(prefix_mgmt_az1_cidr,"96.2")) -> #REF!
A72: Edge Overlay Pool: End IP | B72: =IF(cluster_wld_domain_chosen="VI Workload Domain",CONCATENATE(prefix_wld_az1_cidr,"30.5"),CONCATENATE(prefix_mgmt_az1_cidr,"30.5")) -> #REF! | E72: =IF(cluster_wld_domain_chosen="VI Workload Domain",CONCATENATE(prefix_wld_az1_cidr,"41.5"),CONCATENATE(prefix_mgmt_az1_cidr,"41.5")) -> #REF! | H72: =IF(cluster_wld_domain_chosen="VI Workload Domain",CONCATENATE(prefix_wld_az1_cidr,"52.5"),CONCATENATE(prefix_mgmt_az1_cidr,"52.5")) -> #REF! | K72: =IF(cluster_wld_domain_chosen="VI Workload Domain",CONCATENATE(prefix_wld_az1_cidr,"63.5"),CONCATENATE(prefix_mgmt_az1_cidr,"63.5")) -> #REF! | N72: =IF(cluster_wld_domain_chosen="VI Workload Domain",CONCATENATE(prefix_wld_az1_cidr,"74.5"),CONCATENATE(prefix_mgmt_az1_cidr,"74.5")) -> #REF! | Q72: =IF(cluster_wld_domain_chosen="VI Workload Domain",CONCATENATE(prefix_wld_az1_cidr,"85.5"),CONCATENATE(prefix_mgmt_az1_cidr,"85.5")) -> #REF! | T72: =IF(cluster_wld_domain_chosen="VI Workload Domain",CONCATENATE(prefix_wld_az1_cidr,"96.5"),CONCATENATE(prefix_mgmt_az1_cidr,"96.5")) -> #REF!
A73: NSX Edge Nodes Autonomous System ID | B73: =IF(cluster_wld_domain_chosen="VI Workload Domain",IF(mgmt_domain_chosen="First Instance","65102",IF(wld_nsxt_federation_result="Included","65202","65102")),IF(mgmt_domain_chosen="First Instance","65101",IF(mgmt_nsxt_federation_result="Included","65201","65101"))) -> #REF! | E73: =IF(cluster_wld_domain_chosen="VI Workload Domain",IF(mgmt_domain_chosen="First Instance","65102",IF(wld_nsxt_federation_result="Included","65202","65102")),IF(mgmt_domain_chosen="First Instance","65101",IF(mgmt_nsxt_federation_result="Included","65201","65101"))) -> #REF! | H73: =IF(cluster_wld_domain_chosen="VI Workload Domain",IF(mgmt_domain_chosen="First Instance","65102",IF(wld_nsxt_federation_result="Included","65202","65102")),IF(mgmt_domain_chosen="First Instance","65101",IF(mgmt_nsxt_federation_result="Included","65201","65101"))) -> #REF! | K73: =IF(cluster_wld_domain_chosen="VI Workload Domain",IF(mgmt_domain_chosen="First Instance","65102",IF(wld_nsxt_federation_result="Included","65202","65102")),IF(mgmt_domain_chosen="First Instance","65101",IF(mgmt_nsxt_federation_result="Included","65201","65101"))) -> #REF! | N73: =IF(cluster_wld_domain_chosen="VI Workload Domain",IF(mgmt_domain_chosen="First Instance","65102",IF(wld_nsxt_federation_result="Included","65202","65102")),IF(mgmt_domain_chosen="First Instance","65101",IF(mgmt_nsxt_federation_result="Included","65201","65101"))) -> #REF! | Q73: =IF(cluster_wld_domain_chosen="VI Workload Domain",IF(mgmt_domain_chosen="First Instance","65102",IF(wld_nsxt_federation_result="Included","65202","65102")),IF(mgmt_domain_chosen="First Instance","65101",IF(mgmt_nsxt_federation_result="Included","65201","65101"))) -> #REF! | T73: =IF(cluster_wld_domain_chosen="VI Workload Domain",IF(mgmt_domain_chosen="First Instance","65102",IF(wld_nsxt_federation_result="Included","65202","65102")),IF(mgmt_domain_chosen="First Instance","65101",IF(mgmt_nsxt_federation_result="Included","65201","65101"))) -> #REF!
A74: Top of Rack 1 - IP Address | B74: =IF(cluster_wld_domain_chosen="VI Workload Domain",CONCATENATE(prefix_wld_az1_cidr,"28.10"),CONCATENATE(prefix_mgmt_az1_cidr,"28.10")) -> #REF! | E74: =IF(cluster_wld_domain_chosen="VI Workload Domain",CONCATENATE(prefix_wld_az1_cidr,"39.10"),CONCATENATE(prefix_mgmt_az1_cidr,"39.10")) -> #REF! | H74: =IF(cluster_wld_domain_chosen="VI Workload Domain",CONCATENATE(prefix_wld_az1_cidr,"50.10"),CONCATENATE(prefix_mgmt_az1_cidr,"50.10")) -> #REF! | K74: =IF(cluster_wld_domain_chosen="VI Workload Domain",CONCATENATE(prefix_wld_az1_cidr,"61.10"),CONCATENATE(prefix_mgmt_az1_cidr,"61.10")) -> #REF! | N74: =IF(cluster_wld_domain_chosen="VI Workload Domain",CONCATENATE(prefix_wld_az1_cidr,"72.10"),CONCATENATE(prefix_mgmt_az1_cidr,"72.10")) -> #REF! | Q74: =IF(cluster_wld_domain_chosen="VI Workload Domain",CONCATENATE(prefix_wld_az1_cidr,"83.10"),CONCATENATE(prefix_mgmt_az1_cidr,"83.10")) -> #REF! | T74: =IF(cluster_wld_domain_chosen="VI Workload Domain",CONCATENATE(prefix_wld_az1_cidr,"94.10"),CONCATENATE(prefix_mgmt_az1_cidr,"94.10")) -> #REF!
A75: Top of Rack 1 - Autonomous System ID | B75: =IF(cluster_wld_domain_chosen="VI Workload Domain",IF(mgmt_domain_chosen="First Instance",CONCATENATE(asn_start,asn_instance,asn_wld_az1,2),IF(wld_nsxt_federation_result="Included",CONCATENATE(asn_start,asn_instance,asn_wld_az1,2),CONCATENATE(asn_start,asn_instance,asn_mgmt_az1,2))),IF(mgmt_domain_chosen="First Instance",CONCATENATE(asn_start,asn_instance,asn_mgmt_az1,2),IF(mgmt_nsxt_federation_result="Included",CONCATENATE(asn_start,asn_instance,asn_mgmt_az1,2),CONCATENATE(asn_start,asn_instance,asn_mgmt_az1,2)))) -> #REF! | E75: =IF(cluster_wld_domain_chosen="VI Workload Domain",IF(mgmt_domain_chosen="First Instance",CONCATENATE(asn_start,asn_instance,asn_wld_az1,3),IF(wld_nsxt_federation_result="Included",CONCATENATE(asn_start,asn_instance,asn_wld_az1,3),CONCATENATE(asn_start,asn_instance,asn_mgmt_az1,3))),IF(mgmt_domain_chosen="First Instance",CONCATENATE(asn_start,asn_instance,asn_mgmt_az1,3),IF(mgmt_nsxt_federation_result="Included",CONCATENATE(asn_start,asn_instance,asn_mgmt_az1,3),CONCATENATE(asn_start,asn_instance,asn_mgmt_az1,3)))) -> #REF! | H75: =IF(cluster_wld_domain_chosen="VI Workload Domain",IF(mgmt_domain_chosen="First Instance",CONCATENATE(asn_start,asn_instance,asn_wld_az1,4),IF(wld_nsxt_federation_result="Included",CONCATENATE(asn_start,asn_instance,asn_wld_az1,4),CONCATENATE(asn_start,asn_instance,asn_mgmt_az1,4))),IF(mgmt_domain_chosen="First Instance",CONCATENATE(asn_start,asn_instance,asn_mgmt_az1,4),IF(mgmt_nsxt_federation_result="Included",CONCATENATE(asn_start,asn_instance,asn_mgmt_az1,4),CONCATENATE(asn_start,asn_instance,asn_mgmt_az1,4)))) -> #REF! | K75: =IF(cluster_wld_domain_chosen="VI Workload Domain",IF(mgmt_domain_chosen="First Instance",CONCATENATE(asn_start,asn_instance,asn_wld_az1,5),IF(wld_nsxt_federation_result="Included",CONCATENATE(asn_start,asn_instance,asn_wld_az1,5),CONCATENATE(asn_start,asn_instance,asn_mgmt_az1,5))),IF(mgmt_domain_chosen="First Instance",CONCATENATE(asn_start,asn_instance,asn_mgmt_az1,5),IF(mgmt_nsxt_federation_result="Included",CONCATENATE(asn_start,asn_instance,asn_mgmt_az1,5),CONCATENATE(asn_start,asn_instance,asn_mgmt_az1,5)))) -> #REF! | N75: =IF(cluster_wld_domain_chosen="VI Workload Domain",IF(mgmt_domain_chosen="First Instance",CONCATENATE(asn_start,asn_instance,asn_wld_az1,6),IF(wld_nsxt_federation_result="Included",CONCATENATE(asn_start,asn_instance,asn_wld_az1,6),CONCATENATE(asn_start,asn_instance,asn_mgmt_az1,6))),IF(mgmt_domain_chosen="First Instance",CONCATENATE(asn_start,asn_instance,asn_mgmt_az1,6),IF(mgmt_nsxt_federation_result="Included",CONCATENATE(asn_start,asn_instance,asn_mgmt_az1,6),CONCATENATE(asn_start,asn_instance,asn_mgmt_az1,6)))) -> #REF! | Q75: =IF(cluster_wld_domain_chosen="VI Workload Domain",IF(mgmt_domain_chosen="First Instance",CONCATENATE(asn_start,asn_instance,asn_wld_az1,7),IF(wld_nsxt_federation_result="Included",CONCATENATE(asn_start,asn_instance,asn_wld_az1,7),CONCATENATE(asn_start,asn_instance,asn_mgmt_az1,7))),IF(mgmt_domain_chosen="First Instance",CONCATENATE(asn_start,asn_instance,asn_mgmt_az1,7),IF(mgmt_nsxt_federation_result="Included",CONCATENATE(asn_start,asn_instance,asn_mgmt_az1,7),CONCATENATE(asn_start,asn_instance,asn_mgmt_az1,7)))) -> #REF! | T75: =IF(cluster_wld_domain_chosen="VI Workload Domain",IF(mgmt_domain_chosen="First Instance",CONCATENATE(asn_start,asn_instance,asn_wld_az1,8),IF(wld_nsxt_federation_result="Included",CONCATENATE(asn_start,asn_instance,asn_wld_az1,8),CONCATENATE(asn_start,asn_instance,asn_mgmt_az1,8))),IF(mgmt_domain_chosen="First Instance",CONCATENATE(asn_start,asn_instance,asn_mgmt_az1,8),IF(mgmt_nsxt_federation_result="Included",CONCATENATE(asn_start,asn_instance,asn_mgmt_az1,8),CONCATENATE(asn_start,asn_instance,asn_mgmt_az1,8)))) -> #REF!
A76: Top of Rack 1 - BGP Neighbor Password | B76: VMw@re1! | E76: VMw@re1! | H76: VMw@re1! | K76: VMw@re1! | N76: VMw@re1! | Q76: VMw@re1! | T76: VMw@re1!
A77: Top of Rack 2 - IP Address | B77: =IF(cluster_wld_domain_chosen="VI Workload Domain",CONCATENATE(prefix_wld_az1_cidr,"29.10"),CONCATENATE(prefix_mgmt_az1_cidr,"29.10")) -> #REF! | E77: =IF(cluster_wld_domain_chosen="VI Workload Domain",CONCATENATE(prefix_wld_az1_cidr,"40.10"),CONCATENATE(prefix_mgmt_az1_cidr,"40.10")) -> #REF! | H77: =IF(cluster_wld_domain_chosen="VI Workload Domain",CONCATENATE(prefix_wld_az1_cidr,"51.10"),CONCATENATE(prefix_mgmt_az1_cidr,"51.10")) -> #REF! | K77: =IF(cluster_wld_domain_chosen="VI Workload Domain",CONCATENATE(prefix_wld_az1_cidr,"62.10"),CONCATENATE(prefix_mgmt_az1_cidr,"62.10")) -> #REF! | N77: =IF(cluster_wld_domain_chosen="VI Workload Domain",CONCATENATE(prefix_wld_az1_cidr,"73.10"),CONCATENATE(prefix_mgmt_az1_cidr,"73.10")) -> #REF! | Q77: =IF(cluster_wld_domain_chosen="VI Workload Domain",CONCATENATE(prefix_wld_az1_cidr,"84.10"),CONCATENATE(prefix_mgmt_az1_cidr,"84.10")) -> #REF! | T77: =IF(cluster_wld_domain_chosen="VI Workload Domain",CONCATENATE(prefix_wld_az1_cidr,"95.10"),CONCATENATE(prefix_mgmt_az1_cidr,"95.10")) -> #REF!
A78: Top of Rack 2 - Autonomous System ID | B78: =IF(cluster_wld_domain_chosen="VI Workload Domain",IF(mgmt_domain_chosen="First Instance",CONCATENATE(asn_start,asn_instance,asn_wld_az1,2),IF(wld_nsxt_federation_result="Included",CONCATENATE(asn_start,asn_instance,asn_wld_az1,2),CONCATENATE(asn_start,asn_instance,asn_mgmt_az1,2))),IF(mgmt_domain_chosen="First Instance",CONCATENATE(asn_start,asn_instance,asn_mgmt_az1,2),IF(mgmt_nsxt_federation_result="Included",CONCATENATE(asn_start,asn_instance,asn_mgmt_az1,2),CONCATENATE(asn_start,asn_instance,asn_mgmt_az1,2)))) -> #REF! | E78: =IF(cluster_wld_domain_chosen="VI Workload Domain",IF(mgmt_domain_chosen="First Instance",CONCATENATE(asn_start,asn_instance,asn_wld_az1,3),IF(wld_nsxt_federation_result="Included",CONCATENATE(asn_start,asn_instance,asn_wld_az1,3),CONCATENATE(asn_start,asn_instance,asn_mgmt_az1,3))),IF(mgmt_domain_chosen="First Instance",CONCATENATE(asn_start,asn_instance,asn_mgmt_az1,3),IF(mgmt_nsxt_federation_result="Included",CONCATENATE(asn_start,asn_instance,asn_mgmt_az1,3),CONCATENATE(asn_start,asn_instance,asn_mgmt_az1,3)))) -> #REF! | H78: =IF(cluster_wld_domain_chosen="VI Workload Domain",IF(mgmt_domain_chosen="First Instance",CONCATENATE(asn_start,asn_instance,asn_wld_az1,4),IF(wld_nsxt_federation_result="Included",CONCATENATE(asn_start,asn_instance,asn_wld_az1,4),CONCATENATE(asn_start,asn_instance,asn_mgmt_az1,4))),IF(mgmt_domain_chosen="First Instance",CONCATENATE(asn_start,asn_instance,asn_mgmt_az1,4),IF(mgmt_nsxt_federation_result="Included",CONCATENATE(asn_start,asn_instance,asn_mgmt_az1,4),CONCATENATE(asn_start,asn_instance,asn_mgmt_az1,4)))) -> #REF! | K78: =IF(cluster_wld_domain_chosen="VI Workload Domain",IF(mgmt_domain_chosen="First Instance",CONCATENATE(asn_start,asn_instance,asn_wld_az1,5),IF(wld_nsxt_federation_result="Included",CONCATENATE(asn_start,asn_instance,asn_wld_az1,5),CONCATENATE(asn_start,asn_instance,asn_mgmt_az1,5))),IF(mgmt_domain_chosen="First Instance",CONCATENATE(asn_start,asn_instance,asn_mgmt_az1,5),IF(mgmt_nsxt_federation_result="Included",CONCATENATE(asn_start,asn_instance,asn_mgmt_az1,5),CONCATENATE(asn_start,asn_instance,asn_mgmt_az1,5)))) -> #REF! | N78: =IF(cluster_wld_domain_chosen="VI Workload Domain",IF(mgmt_domain_chosen="First Instance",CONCATENATE(asn_start,asn_instance,asn_wld_az1,6),IF(wld_nsxt_federation_result="Included",CONCATENATE(asn_start,asn_instance,asn_wld_az1,6),CONCATENATE(asn_start,asn_instance,asn_mgmt_az1,6))),IF(mgmt_domain_chosen="First Instance",CONCATENATE(asn_start,asn_instance,asn_mgmt_az1,6),IF(mgmt_nsxt_federation_result="Included",CONCATENATE(asn_start,asn_instance,asn_mgmt_az1,6),CONCATENATE(asn_start,asn_instance,asn_mgmt_az1,6)))) -> #REF! | Q78: =IF(cluster_wld_domain_chosen="VI Workload Domain",IF(mgmt_domain_chosen="First Instance",CONCATENATE(asn_start,asn_instance,asn_wld_az1,7),IF(wld_nsxt_federation_result="Included",CONCATENATE(asn_start,asn_instance,asn_wld_az1,7),CONCATENATE(asn_start,asn_instance,asn_mgmt_az1,7))),IF(mgmt_domain_chosen="First Instance",CONCATENATE(asn_start,asn_instance,asn_mgmt_az1,7),IF(mgmt_nsxt_federation_result="Included",CONCATENATE(asn_start,asn_instance,asn_mgmt_az1,7),CONCATENATE(asn_start,asn_instance,asn_mgmt_az1,7)))) -> #REF! | T78: =IF(cluster_wld_domain_chosen="VI Workload Domain",IF(mgmt_domain_chosen="First Instance",CONCATENATE(asn_start,asn_instance,asn_wld_az1,8),IF(wld_nsxt_federation_result="Included",CONCATENATE(asn_start,asn_instance,asn_wld_az1,8),CONCATENATE(asn_start,asn_instance,asn_mgmt_az1,8))),IF(mgmt_domain_chosen="First Instance",CONCATENATE(asn_start,asn_instance,asn_mgmt_az1,8),IF(mgmt_nsxt_federation_result="Included",CONCATENATE(asn_start,asn_instance,asn_mgmt_az1,8),CONCATENATE(asn_start,asn_instance,asn_mgmt_az1,8)))) -> #REF!
A79: Top of Rack 2 - BGP Neighbor Password | B79: VMw@re1! | E79: VMw@re1! | H79: VMw@re1! | K79: VMw@re1! | N79: VMw@re1! | Q79: VMw@re1! | T79: VMw@re1!

Sheet Value Reference Tables - MR
E2: VMware Cloud Foundation Network Value Reference Tables
E3: Transposed and Calculated Values. All values are named cells for reference in other areas of the Workbook
B6: Bundle Download | E6: MGMT Rack 1 VLANs (Primary AZ) | H6: Rack 1 VLANs (Primary AZ) | K6: Rack 2 VLANs (Primary AZ) | N6: Rack 3 VLANs (Primary AZ) | Q6: Rack 4 VLANs (Primary AZ) | T6: Rack 5 VLANs (Primary AZ) | W6: Rack 6 VLANs (Primary AZ) | Z6: Rack 7 VLANs (Primary AZ) | AC6: Rack 8 VLANs (Primary AZ) | AG6: Modifiers
B7: Name | C7: Value | E7: Name | F7: AZ1 Actual Value | H7: Name | I7: AZ1 Actual Value | K7: Name | L7: AZ1 Actual Value | N7: Name | O7: AZ1 Actual Value | Q7: Name | R7: AZ1 Actual Value | T7: Name | U7: AZ1 Actual Value | W7: Name | X7: AZ1 Actual Value | Z7: Name | AA7: AZ1 Actual Value | AC7: Name | AD7: AZ1 Actual Value | AG7: WLD Rack2 AZ1 Host VLAN Prefix | AH7: =IF(AND(this_instance="sfo",wld_domain_number_chosen=1),13,IF(AND(this_instance="sfo",wld_domain_number_chosen=2),15,IF(AND(this_instance="sfo",wld_domain_number_chosen=3),17,IF(AND(this_instance="lax",wld_domain_number_chosen=1),23,IF(AND(this_instance="lax",wld_domain_number_chosen=2),25,IF(AND(this_instance="lax",wld_domain_number_chosen=3),27)))))) -> #REF!
B8: Depot Type | C8: =mgmt_offline_depot_chosen -> #REF! | E8: Management VM Network | F8: #REF! | H8: Management VM Network | I8: =IF(ISBLANK(input_wld_az1_mgmt_vm_vlan),"Value Missing",input_wld_az1_mgmt_vm_vlan) -> #REF! | K8: Management VM Network | L8: =IF(ISBLANK(input_wld_az1_rack2_mgmt_vm_vlan),"Value Missing",input_wld_az1_rack2_mgmt_vm_vlan) -> Value Missing | N8: Management VM Network | O8: =IF(ISBLANK(input_wld_az1_rack3_mgmt_vm_vlan),"Value Missing",input_wld_az1_rack3_mgmt_vm_vlan) -> Value Missing | Q8: Management VM Network | R8: =IF(ISBLANK(input_wld_az1_rack4_mgmt_vm_vlan),"Value Missing",input_wld_az1_rack4_mgmt_vm_vlan) -> Value Missing | T8: Management VM Network | U8: =IF(ISBLANK(input_wld_az1_rack5_mgmt_vm_vlan),"Value Missing",input_wld_az1_rack5_mgmt_vm_vlan) -> Value Missing | W8: Management VM Network | X8: =IF(ISBLANK(input_wld_az1_rack6_mgmt_vm_vlan),"Value Missing",input_wld_az1_rack6_mgmt_vm_vlan) -> Value Missing | Z8: Management VM Network | AA8: =IF(ISBLANK(input_wld_az1_rack7_mgmt_vm_vlan),"Value Missing",input_wld_az1_rack7_mgmt_vm_vlan) -> Value Missing | AC8: Management VM Network | AD8: =IF(ISBLANK(input_wld_az1_rack8_mgmt_vm_vlan),"Value Missing",input_wld_az1_rack8_mgmt_vm_vlan) -> Value Missing | AG8: WLD Rack 2 AZ2 Host VLAN Prefix | AH8: =IF(AND(this_instance="sfo",wld_domain_number_chosen=1),14,IF(AND(this_instance="sfo",wld_domain_number_chosen=2),16,IF(AND(this_instance="sfo",wld_domain_number_chosen=3),18,IF(AND(this_instance="lax",wld_domain_number_chosen=1),24,IF(AND(this_instance="lax",wld_domain_number_chosen=2),26,IF(AND(this_instance="lax",wld_domain_number_chosen=3),28)))))) -> #REF!
B9: Hostname | C9: =mgmt_offline_depot_fqdn -> #REF! | E9: ESXi Management Network | F9: =IF(ISBLANK(input_mgmt_az1_mgmt_vlan),"Value Missing",input_mgmt_az1_mgmt_vlan) -> #REF! | H9: ESXi Management Network | I9: =IF(ISBLANK(input_wld_az1_mgmt_vlan),"Value Missing",input_wld_az1_mgmt_vlan) -> #REF! | K9: ESXi Management Network | L9: =IF(ISBLANK(input_wld_az1_rack2_mgmt_vlan),"Value Missing",input_wld_az1_rack2_mgmt_vlan) -> #REF! | N9: ESXi Management Network | O9: =IF(ISBLANK(input_wld_az1_rack3_mgmt_vlan),"Value Missing",input_wld_az1_rack3_mgmt_vlan) -> #REF! | Q9: ESXi Management Network | R9: =IF(ISBLANK(input_wld_az1_rack4_mgmt_vlan),"Value Missing",input_wld_az1_rack4_mgmt_vlan) -> #REF! | T9: ESXi Management Network | U9: =IF(ISBLANK(input_wld_az1_rack5_mgmt_vlan),"Value Missing",input_wld_az1_rack5_mgmt_vlan) -> #REF! | W9: ESXi Management Network | X9: =IF(ISBLANK(input_wld_az1_rack6_mgmt_vlan),"Value Missing",input_wld_az1_rack6_mgmt_vlan) -> #REF! | Z9: ESXi Management Network | AA9: =IF(ISBLANK(input_wld_az1_rack7_mgmt_vlan),"Value Missing",input_wld_az1_rack7_mgmt_vlan) -> #REF! | AC9: ESXi Management Network | AD9: =IF(ISBLANK(input_wld_az1_rack8_mgmt_vlan),"Value Missing",input_wld_az1_rack8_mgmt_vlan) -> #REF! | AG9: WLD Rack 2 AZ1 Host CIDR Prefix | AH9: =CONCATENATE("10.",prefix_wld_az1_rack_vlan,".") -> #REF!
B10: Port | C10: =mgmt_offline_depot_port -> #REF! | E10: vMotion Network | F10: =IF(ISBLANK(input_mgmt_az1_vmotion_vlan),"Value Missing",input_mgmt_az1_vmotion_vlan) -> #REF! | H10: vMotion Network | I10: =IF(ISBLANK(input_wld_az1_vmotion_vlan),"Value Missing",input_wld_az1_vmotion_vlan) -> #REF! | K10: vMotion Network | L10: =IF(ISBLANK(input_wld_az1_rack2_vmotion_vlan),"Value Missing",input_wld_az1_rack2_vmotion_vlan) -> #REF! | N10: vMotion Network | O10: =IF(ISBLANK(input_wld_az1_rack3_vmotion_vlan),"Value Missing",input_wld_az1_rack3_vmotion_vlan) -> #REF! | Q10: vMotion Network | R10: =IF(ISBLANK(input_wld_az1_rack4_vmotion_vlan),"Value Missing",input_wld_az1_rack4_vmotion_vlan) -> #REF! | T10: vMotion Network | U10: =IF(ISBLANK(input_wld_az1_rack5_vmotion_vlan),"Value Missing",input_wld_az1_rack5_vmotion_vlan) -> #REF! | W10: vMotion Network | X10: =IF(ISBLANK(input_wld_az1_rack6_vmotion_vlan),"Value Missing",input_wld_az1_rack6_vmotion_vlan) -> #REF! | Z10: vMotion Network | AA10: =IF(ISBLANK(input_wld_az1_rack7_vmotion_vlan),"Value Missing",input_wld_az1_rack7_vmotion_vlan) -> #REF! | AC10: vMotion Network | AD10: =IF(ISBLANK(input_wld_az1_rack8_vmotion_vlan),"Value Missing",input_wld_az1_rack8_vmotion_vlan) -> #REF! | AG10: WLD Rack 2 AZ2 Host CIDR Prefix | AH10: =CONCATENATE("10.",prefix_wld_az2_rack_vlan) -> #REF!
B11: Password | C11: =svc_my_vmware_password -> #REF! | E11: =CONCATENATE("Principal Storage Network ",wld_principal_storage_chosen) -> #REF! | F11: =IF(ISBLANK(input_mgmt_az1_vsan_vlan),"Value Missing",input_mgmt_az1_vsan_vlan) -> #REF! | H11: vSAN Network | I11: =IF(ISBLANK(input_wld_az1_principal_storage_vlan),"Value Missing",input_wld_az1_principal_storage_vlan) -> #REF! | K11: =CONCATENATE("Principal Storage Network ",wld_principal_storage_chosen) -> #REF! | L11: =IF(ISBLANK(input_wld_az1_rack2_principal_storage_vlan),"Value Missing",input_wld_az1_rack2_principal_storage_vlan) -> #REF! | N11: =CONCATENATE("Principal Storage Network ",wld_principal_storage_chosen) -> #REF! | O11: =IF(ISBLANK(input_wld_az1_rack3_principal_storage_vlan),"Value Missing",input_wld_az1_rack3_principal_storage_vlan) -> #REF! | Q11: =CONCATENATE("Principal Storage Network ",wld_principal_storage_chosen) -> #REF! | R11: =IF(ISBLANK(input_wld_az1_rack4_principal_storage_vlan),"Value Missing",input_wld_az1_rack4_principal_storage_vlan) -> #REF! | T11: =CONCATENATE("Principal Storage Network ",wld_principal_storage_chosen) -> #REF! | U11: =IF(ISBLANK(input_wld_az1_rack5_principal_storage_vlan),"Value Missing",input_wld_az1_rack5_principal_storage_vlan) -> #REF! | W11: =CONCATENATE("Principal Storage Network ",wld_principal_storage_chosen) -> #REF! | X11: =IF(ISBLANK(input_wld_az1_rack6_principal_storage_vlan),"Value Missing",input_wld_az1_rack6_principal_storage_vlan) -> #REF! | Z11: =CONCATENATE("Principal Storage Network ",wld_principal_storage_chosen) -> #REF! | AA11: =IF(ISBLANK(input_wld_az1_rack7_principal_storage_vlan),"Value Missing",input_wld_az1_rack7_principal_storage_vlan) -> #REF! | AC11: =CONCATENATE("Principal Storage Network ",wld_principal_storage_chosen) -> #REF! | AD11: =IF(ISBLANK(input_wld_az1_rack8_principal_storage_vlan),"Value Missing",input_wld_az1_rack8_principal_storage_vlan) -> #REF!
B12: Proxy Configuration | C12: =mgmt_offline_depot_chosen -> #REF! | E12: NSX Host Overlay | F12: =IF(ISBLANK(input_mgmt_az1_host_overlay_vlan),"Value Missing",input_mgmt_az1_host_overlay_vlan) -> #REF! | H12: NSX Host Overlay | I12: =IF(ISBLANK(input_wld_az1_host_overlay_vlan),"Value Missing",input_wld_az1_host_overlay_vlan) -> #REF! | K12: NSX Host Overlay | L12: =IF(ISBLANK(input_wld_az1_rack2_host_overlay_vlan),"Value Missing",input_wld_az1_rack2_host_overlay_vlan) -> #REF! | N12: NSX Host Overlay | O12: =IF(ISBLANK(input_wld_az1_rack3_host_overlay_vlan),"Value Missing",input_wld_az1_rack3_host_overlay_vlan) -> #REF! | Q12: NSX Host Overlay | R12: =IF(ISBLANK(input_wld_az1_rack4_host_overlay_vlan),"Value Missing",input_wld_az1_rack4_host_overlay_vlan) -> #REF! | T12: NSX Host Overlay | U12: =IF(ISBLANK(input_wld_az1_rack5_host_overlay_vlan),"Value Missing",input_wld_az1_rack5_host_overlay_vlan) -> #REF! | W12: NSX Host Overlay | X12: =IF(ISBLANK(input_wld_az1_rack6_host_overlay_vlan),"Value Missing",input_wld_az1_rack6_host_overlay_vlan) -> #REF! | Z12: NSX Host Overlay | AA12: =IF(ISBLANK(input_wld_az1_rack7_host_overlay_vlan),"Value Missing",input_wld_az1_rack7_host_overlay_vlan) -> #REF! | AC12: NSX Host Overlay | AD12: =IF(ISBLANK(input_wld_az1_rack8_host_overlay_vlan),"Value Missing",input_wld_az1_rack8_host_overlay_vlan) -> #REF!
B13: Protocol | C13: =mgmt_internet_proxy_type_chosen -> #REF! | E13: Secondary Storage Network (NFS) | F13: =IF(ISBLANK(input_mgmt_az1_secondary_storage_vlan),"Value Missing",input_mgmt_az1_secondary_storage_vlan) -> #REF! | H13: Secondary Storage Network (NFS) | I13: =IF(ISBLANK(input_wld_az1_secondary_storage_vlan),"Value Missing",input_wld_az1_secondary_storage_vlan) -> #REF! | K13: Secondary Storage Network (NFS) | L13: =IF(ISBLANK(input_wld_az1_rack2_secondary_storage_vlan),"Value Missing",input_wld_az1_rack2_secondary_storage_vlan) -> Value Missing | N13: Secondary Storage Network (NFS) | O13: =IF(ISBLANK(input_wld_az1_rack3_secondary_storage_vlan),"Value Missing",input_wld_az1_rack3_secondary_storage_vlan) -> Value Missing | Q13: Secondary Storage Network (NFS) | R13: =IF(ISBLANK(input_wld_az1_rack4_secondary_storage_vlan),"Value Missing",input_wld_az1_rack4_secondary_storage_vlan) -> Value Missing | T13: Secondary Storage Network (NFS) | U13: =IF(ISBLANK(input_wld_az1_rack5_secondary_storage_vlan),"Value Missing",input_wld_az1_rack5_secondary_storage_vlan) -> Value Missing | W13: Secondary Storage Network (NFS) | X13: =IF(ISBLANK(input_wld_az1_rack6_secondary_storage_vlan),"Value Missing",input_wld_az1_rack6_secondary_storage_vlan) -> Value Missing | Z13: Secondary Storage Network (NFS) | AA13: =IF(ISBLANK(input_wld_az1_rack7_secondary_storage_vlan),"Value Missing",input_wld_az1_rack7_secondary_storage_vlan) -> Value Missing | AC13: Secondary Storage Network (NFS) | AD13: =IF(ISBLANK(input_wld_az1_rack8_secondary_storage_vlan),"Value Missing",input_wld_az1_rack8_secondary_storage_vlan) -> Value Missing
B14: Internet Proxy Chosen | C14: =mgmt_internet_proxy_chosen -> #REF! | E14: VCF Management Network | F14: =IF(ISBLANK(input_mgmt_az1_vcf_mgmt_vlan),"Value Missing",input_mgmt_az1_vcf_mgmt_vlan) -> #REF! | H14: vSAN Network - vSAN Storage Cluster | I14: =IF(ISBLANK(input_wld_az1_storage_cluster_vlan),"Value Missing",input_wld_az1_storage_cluster_vlan) -> #REF! | K14: vSAN Network - vSAN Storage Cluster | N14: vSAN Network - vSAN Storage Cluster | Q14: vSAN Network - vSAN Storage Cluster | T14: vSAN Network - vSAN Storage Cluster | W14: vSAN Network - vSAN Storage Cluster | Z14: vSAN Network - vSAN Storage Cluster | AC14: vSAN Network - vSAN Storage Cluster
B15: Proxy Address | C15: =IF(ISBLANK(input_mgmt_internet_proxy_address),"Value Missing",input_mgmt_internet_proxy_address) -> #REF! | E15: NSX Edge Uplink 1 | F15: =IF(ISBLANK(input_mgmt_az1_uplink01_vlan),"Value Missing",input_mgmt_az1_uplink01_vlan) -> #REF! | H15: NSX Edge Uplink 1 | I15: =IF(ISBLANK(input_wld_az1_uplink01_vlan),"Value Missing",input_wld_az1_uplink01_vlan) -> #REF! | K15: NSX Edge Uplink 1 | L15: =IF(ISBLANK(input_wld_az1_rack2_uplink01_vlan),"Value Missing",input_wld_az1_rack2_uplink01_vlan) -> Value Missing | N15: NSX Edge Uplink 1 | O15: =IF(ISBLANK(input_wld_az1_rack3_uplink01_vlan),"Value Missing",input_wld_az1_rack3_uplink01_vlan) -> Value Missing | Q15: NSX Edge Uplink 1 | R15: =IF(ISBLANK(input_wld_az1_rack4_uplink01_vlan),"Value Missing",input_wld_az1_rack4_uplink01_vlan) -> Value Missing | T15: NSX Edge Uplink 1 | U15: =IF(ISBLANK(input_wld_az1_rack5_uplink01_vlan),"Value Missing",input_wld_az1_rack5_uplink01_vlan) -> Value Missing | W15: NSX Edge Uplink 1 | X15: =IF(ISBLANK(input_wld_az1_rack6_uplink01_vlan),"Value Missing",input_wld_az1_rack6_uplink01_vlan) -> Value Missing | Z15: NSX Edge Uplink 1 | AA15: =IF(ISBLANK(input_wld_az1_rack7_uplink01_vlan),"Value Missing",input_wld_az1_rack7_uplink01_vlan) -> Value Missing | AC15: NSX Edge Uplink 1 | AD15: =IF(ISBLANK(input_wld_az1_rack8_uplink01_vlan),"Value Missing",input_wld_az1_rack8_uplink01_vlan) -> Value Missing
B16: Proxy Port | C16: =mgmt_internet_proxy_port -> #REF! | E16: NSX Edge Uplink 2 | F16: =IF(ISBLANK(input_mgmt_az1_uplink02_vlan),"Value Missing",input_mgmt_az1_uplink02_vlan) -> #REF! | H16: NSX Edge Uplink 2 | I16: =IF(ISBLANK(input_wld_az1_uplink02_vlan),"Value Missing",input_wld_az1_uplink02_vlan) -> #REF! | K16: NSX Edge Uplink 2 | L16: =IF(ISBLANK(input_wld_az1_rack2_uplink02_vlan),"Value Missing",input_wld_az1_rack2_uplink02_vlan) -> Value Missing | N16: NSX Edge Uplink 2 | O16: =IF(ISBLANK(input_wld_az1_rack3_uplink02_vlan),"Value Missing",input_wld_az1_rack3_uplink02_vlan) -> Value Missing | Q16: NSX Edge Uplink 2 | R16: =IF(ISBLANK(input_wld_az1_rack4_uplink02_vlan),"Value Missing",input_wld_az1_rack4_uplink02_vlan) -> Value Missing | T16: NSX Edge Uplink 2 | U16: =IF(ISBLANK(input_wld_az1_rack5_uplink02_vlan),"Value Missing",input_wld_az1_rack5_uplink02_vlan) -> Value Missing | W16: NSX Edge Uplink 2 | X16: =IF(ISBLANK(input_wld_az1_rack6_uplink02_vlan),"Value Missing",input_wld_az1_rack6_uplink02_vlan) -> Value Missing | Z16: NSX Edge Uplink 2 | AA16: =IF(ISBLANK(input_wld_az1_rack7_uplink02_vlan),"Value Missing",input_wld_az1_rack7_uplink02_vlan) -> Value Missing | AC16: NSX Edge Uplink 2 | AD16: =IF(ISBLANK(input_wld_az1_rack8_uplink02_vlan),"Value Missing",input_wld_az1_rack8_uplink02_vlan) -> Value Missing
B17: Proxy Authentication | C17: =mgmt_internet_proxy_auth_chosen -> #REF! | E17: NSX Edge Overlay | F17: =IF(ISBLANK(input_mgmt_az1_edge_overlay_vlan),"Value Missing",input_mgmt_az1_edge_overlay_vlan) -> #REF! | H17: NSX Edge Overlay | I17: =IF(ISBLANK(input_wld_az1_edge_overlay_vlan),"Value Missing",input_wld_az1_edge_overlay_vlan) -> #REF! | K17: NSX Edge Overlay | L17: =IF(ISBLANK(input_wld_az1_rack2_edge_overlay_vlan),"Value Missing",input_wld_az1_rack2_edge_overlay_vlan) -> Value Missing | N17: NSX Edge Overlay | O17: =IF(ISBLANK(input_wld_az1_rack3_edge_overlay_vlan),"Value Missing",input_wld_az1_rack3_edge_overlay_vlan) -> Value Missing | Q17: NSX Edge Overlay | R17: =IF(ISBLANK(input_wld_az1_rack4_edge_overlay_vlan),"Value Missing",input_wld_az1_rack4_edge_overlay_vlan) -> Value Missing | T17: NSX Edge Overlay | U17: =IF(ISBLANK(input_wld_az1_rack5_edge_overlay_vlan),"Value Missing",input_wld_az1_rack5_edge_overlay_vlan) -> Value Missing | W17: NSX Edge Overlay | X17: =IF(ISBLANK(input_wld_az1_rack6_edge_overlay_vlan),"Value Missing",input_wld_az1_rack6_edge_overlay_vlan) -> Value Missing | Z17: NSX Edge Overlay | AA17: =IF(ISBLANK(input_wld_az1_rack7_edge_overlay_vlan),"Value Missing",input_wld_az1_rack7_edge_overlay_vlan) -> Value Missing | AC17: NSX Edge Overlay | AD17: =IF(ISBLANK(input_wld_az1_rack8_edge_overlay_vlan),"Value Missing",input_wld_az1_rack8_edge_overlay_vlan) -> Value Missing | AG17: Start ASN
B18: Username | C18: =IF(ISBLANK(input_mgmt_internet_proxy_email),"Value Missing",input_mgmt_internet_proxy_email) -> #REF! | E18: NSX RTEP Overlay | F18: =IF(ISBLANK(input_mgmt_az1_rtep_overlay_vlan),"Value Missing",input_mgmt_az1_rtep_overlay_vlan) -> #REF! | H18: NSX RTEP Overlay | I18: =IF(ISBLANK(input_wld_az1_rtep_overlay_vlan),"Value Missing",input_wld_az1_rtep_overlay_vlan) -> #REF! | K18: NSX RTEP Overlay | N18: NSX RTEP Overlay | Q18: NSX RTEP Overlay | T18: NSX RTEP Overlay | W18: NSX RTEP Overlay | Z18: NSX RTEP Overlay | AC18: NSX RTEP Overlay | AG18: Instance 1 | AH18: =IF(this_instance="sfo",1,2) -> #REF!
B19: Password | C19: =IF(ISBLANK(input_mgmt_internet_proxy_password),"Value Missing",input_mgmt_internet_proxy_password) -> #REF! | E19: vSphere Replication | F19: =IF(ISBLANK(input_mgmt_az1_vrms_vlan),"Value Missing",input_mgmt_az1_vrms_vlan) -> Value Missing | H19: vSphere Replication | I19: =IF(ISBLANK(input_wld_az1_vrms_vlan),"Value Missing",input_wld_az1_vrms_vlan) -> Value Missing | K19: vSphere Replication | N19: vSphere Replication | Q19: vSphere Replication | T19: vSphere Replication | W19: vSphere Replication | Z19: vSphere Replication | AC19: vSphere Replication | AG19: asn_mgmt_az1 | AH19: 1
AG20: asn_mgmt_az2 | AH20: 2
B21: General Info | E21: MGMT Rack 1 Network CIDRs (Primary AZ) | H21: Rack 1 Network CIDRs (Primary AZ) | K21: Rack 2 Network CIDRs (Primary AZ) | N21: Rack 3 Network CIDRs (Primary AZ) | Q21: Rack 4 Network CIDRs (Primary AZ) | T21: Rack 5 Network CIDRs (Primary AZ) | W21: Rack 6 Network CIDRs (Primary AZ) | Z21: Rack 7 Network CIDRs (Primary AZ) | AC21: Rack 8 Network CIDRs (Primary AZ) | AG21: asn_wld_az1 | AH21: =IF(wld_domain_number_chosen=1,3,IF(wld_domain_number_chosen=2,5,7)) -> 3
B22: Name | C22: Value | E22: Name | F22: AZ1 Actual Value | H22: Name | I22: AZ1 Actual Value | K22: Name | L22: AZ1 Actual Value | N22: Name | O22: AZ1 Actual Value | Q22: Name | R22: AZ1 Actual Value | T22: Name | U22: AZ1 Actual Value | W22: Name | X22: AZ1 Actual Value | Z22: Name | AA22: AZ1 Actual Value | AC22: Name | AD22: AZ1 Actual Value | AG22: asn_wld_az2 | AH22: =IF(wld_domain_number_chosen=1,4,IF(wld_domain_number_chosen=2,6,8)) -> 4
B23: Deployment Type | C23: =mgmt_domain_deployment_type_chosen -> #REF! | E23: Management VM Network | F23: =IF(mgmt_az1_mgmt_vm_network="Value missing","Value Missing",CONCATENATE(mgmt_az1_mgmt_vm_network,"/",VLOOKUP(mgmt_az1_mgmt_vm_mask,table_mask_to_cidr,2,FALSE))) -> #REF! | H23: Management VM Network | I23: =IF(wld_az1_mgmt_vm_network="Value missing","Value Missing",CONCATENATE(wld_az1_mgmt_vm_network,"/",VLOOKUP(wld_az1_mgmt_vm_mask,table_mask_to_cidr,2,FALSE))) -> #REF! | K23: Management VM Network | L23: =IF(ISBLANK(input_wld_az1_rack2_mgmt_vm_cidr),"Value Missing",input_wld_az1_rack2_mgmt_vm_cidr) -> Value Missing | N23: Management VM Network | O23: =IF(ISBLANK(input_wld_az1_rack3_mgmt_vm_cidr),"Value Missing",input_wld_az1_rack3_mgmt_vm_cidr) -> Value Missing | Q23: Management VM Network | R23: =IF(ISBLANK(input_wld_az1_rack4_mgmt_vm_cidr),"Value Missing",input_wld_az1_rack4_mgmt_vm_cidr) -> Value Missing | T23: Management VM Network | U23: =IF(ISBLANK(input_wld_az1_rack5_mgmt_vm_cidr),"Value Missing",input_wld_az1_rack5_mgmt_vm_cidr) -> Value Missing | W23: Management VM Network | X23: =IF(ISBLANK(input_wld_az1_rack6_mgmt_vm_cidr),"Value Missing",input_wld_az1_rack6_mgmt_vm_cidr) -> Value Missing | Z23: Management VM Network | AA23: =IF(ISBLANK(input_wld_az1_rack7_mgmt_vm_cidr),"Value Missing",input_wld_az1_rack7_mgmt_vm_cidr) -> Value Missing | AC23: Management VM Network | AD23: =IF(ISBLANK(input_wld_az1_rack8_mgmt_vm_cidr),"Value Missing",input_wld_az1_rack8_mgmt_vm_cidr) -> Value Missing
B24: Instance Name | C24: =IF(ISBLANK(input_mgmt_sddc_domain),"Value Missing",input_mgmt_sddc_domain) -> #REF! | E24: ESXi Management Network | F24: =IF(mgmt_az1_mgmt_network="Value missing","Value Missing",CONCATENATE(mgmt_az1_mgmt_network,"/",VLOOKUP(mgmt_az1_mgmt_mask,table_mask_to_cidr,2,FALSE))) -> #REF! | H24: ESXi Management Network | I24: =IF(wld_az1_mgmt_network="Value missing","Value Missing",CONCATENATE(wld_az1_mgmt_network,"/",VLOOKUP(wld_az1_mgmt_mask,table_mask_to_cidr,2,FALSE))) -> #REF! | K24: ESXi Management Network | L24: =IF(ISBLANK(input_wld_az1_rack2_mgmt_cidr),"Value Missing",input_wld_az1_rack2_mgmt_cidr) -> #REF! | N24: ESXi Management Network | O24: =IF(ISBLANK(input_wld_az1_rack3_mgmt_cidr),"Value Missing",input_wld_az1_rack3_mgmt_cidr) -> #REF! | Q24: ESXi Management Network | R24: =IF(ISBLANK(input_wld_az1_rack4_mgmt_cidr),"Value Missing",input_wld_az1_rack4_mgmt_cidr) -> #REF! | T24: ESXi Management Network | U24: =IF(ISBLANK(input_wld_az1_rack5_mgmt_cidr),"Value Missing",input_wld_az1_rack5_mgmt_cidr) -> #REF! | W24: ESXi Management Network | X24: =IF(ISBLANK(input_wld_az1_rack6_mgmt_cidr),"Value Missing",input_wld_az1_rack6_mgmt_cidr) -> #REF! | Z24: ESXi Management Network | AA24: =IF(ISBLANK(input_wld_az1_rack7_mgmt_cidr),"Value Missing",input_wld_az1_rack7_mgmt_cidr) -> #REF! | AC24: ESXi Management Network | AD24: =IF(ISBLANK(input_wld_az1_rack8_mgmt_cidr),"Value Missing",input_wld_az1_rack8_mgmt_cidr) -> #REF!
B25: Version | C25: =vcf_version -> #REF! | E25: vMotion Network | F25: =IF(mgmt_az1_vmotion_network="Value missing","Value Missing",CONCATENATE(mgmt_az1_vmotion_network,"/",VLOOKUP(mgmt_az1_vmotion_mask,table_mask_to_cidr,2,FALSE))) -> #REF! | H25: vMotion Network | I25: =IF(wld_az1_vmotion_network="Value missing","Value Missing",CONCATENATE(wld_az1_vmotion_network,"/",VLOOKUP(wld_az1_vmotion_mask,table_mask_to_cidr,2,FALSE))) -> #REF! | K25: vMotion Network | L25: =IF(OR(wld_az1_rack2_vmotion_network="Value Missing",wld_az1_rack2_vmotion_mask="Value Missing"),"Value Missing",(CONCATENATE(wld_az1_rack2_vmotion_network,"/",VLOOKUP(wld_az1_rack2_vmotion_mask,table_mask_to_cidr,2,FALSE)))) -> #REF! | N25: vMotion Network | O25: =IF(OR(wld_az1_rack3_vmotion_network="Value Missing",wld_az1_rack3_vmotion_mask="Value Missing"),"Value Missing",(CONCATENATE(wld_az1_rack3_vmotion_network,"/",VLOOKUP(wld_az1_rack3_vmotion_mask,table_mask_to_cidr,2,FALSE)))) -> #REF! | Q25: vMotion Network | R25: =IF(OR(wld_az1_rack4_vmotion_network="Value Missing",wld_az1_rack4_vmotion_mask="Value Missing"),"Value Missing",(CONCATENATE(wld_az1_rack4_vmotion_network,"/",VLOOKUP(wld_az1_rack4_vmotion_mask,table_mask_to_cidr,2,FALSE)))) -> #REF! | T25: vMotion Network | U25: =IF(OR(wld_az1_rack5_vmotion_network="Value Missing",wld_az1_rack5_vmotion_mask="Value Missing"),"Value Missing",(CONCATENATE(wld_az1_rack5_vmotion_network,"/",VLOOKUP(wld_az1_rack5_vmotion_mask,table_mask_to_cidr,2,FALSE)))) -> #REF! | W25: vMotion Network | X25: =IF(OR(wld_az1_rack6_vmotion_network="Value Missing",wld_az1_rack6_vmotion_mask="Value Missing"),"Value Missing",(CONCATENATE(wld_az1_rack6_vmotion_network,"/",VLOOKUP(wld_az1_rack6_vmotion_mask,table_mask_to_cidr,2,FALSE)))) -> #REF! | Z25: vMotion Network | AA25: =IF(OR(wld_az1_rack7_vmotion_network="Value Missing",wld_az1_rack7_vmotion_mask="Value Missing"),"Value Missing",(CONCATENATE(wld_az1_rack7_vmotion_network,"/",VLOOKUP(wld_az1_rack7_vmotion_mask,table_mask_to_cidr,2,FALSE)))) -> #REF! | AC25: vMotion Network | AD25: =IF(OR(wld_az1_rack8_vmotion_network="Value Missing",wld_az1_rack8_vmotion_mask="Value Missing"),"Value Missing",(CONCATENATE(wld_az1_rack8_vmotion_network,"/",VLOOKUP(wld_az1_rack8_vmotion_mask,table_mask_to_cidr,2,FALSE)))) -> #REF!
B26: Deployment Model | C26: =mgmt_domain_vcf_operations_ha_mode_chosen -> #REF! | E26: =CONCATENATE("Principal Storage Network ",wld_principal_storage_chosen) -> #REF! | F26: =IF(mgmt_az1_vsan_network="Value missing","Value Missing",CONCATENATE(mgmt_az1_vsan_network,"/",VLOOKUP(mgmt_az1_vsan_mask,table_mask_to_cidr,2,FALSE))) -> #REF! | H26: vSAN Network | I26: =IF(wld_az1_principal_storage_network="Value missing","Value Missing",CONCATENATE(wld_az1_principal_storage_network,"/",VLOOKUP(wld_az1_principal_storage_mask,table_mask_to_cidr,2,FALSE))) -> #REF! | K26: =CONCATENATE("Principal Storage Network ",wld_principal_storage_chosen) -> #REF! | L26: =IF(OR(wld_az1_rack2_principal_storage_network="Value Missing",wld_az1_rack2_principal_storage_mask="Value Missing"),"Value Missing",(CONCATENATE(wld_az1_rack2_principal_storage_network,"/",VLOOKUP(wld_az1_rack2_principal_storage_mask,table_mask_to_cidr,2,FALSE)))) -> #REF! | N26: =CONCATENATE("Principal Storage Network ",wld_principal_storage_chosen) -> #REF! | O26: =IF(OR(wld_az1_rack3_principal_storage_network="Value Missing",wld_az1_rack3_principal_storage_mask="Value Missing"),"Value Missing",(CONCATENATE(wld_az1_rack3_principal_storage_network,"/",VLOOKUP(wld_az1_rack3_principal_storage_mask,table_mask_to_cidr,2,FALSE)))) -> #REF! | Q26: =CONCATENATE("Principal Storage Network ",wld_principal_storage_chosen) -> #REF! | R26: =IF(OR(wld_az1_rack4_principal_storage_network="Value Missing",wld_az1_rack4_principal_storage_mask="Value Missing"),"Value Missing",(CONCATENATE(wld_az1_rack4_principal_storage_network,"/",VLOOKUP(wld_az1_rack4_principal_storage_mask,table_mask_to_cidr,2,FALSE)))) -> #REF! | T26: =CONCATENATE("Principal Storage Network ",wld_principal_storage_chosen) -> #REF! | U26: =IF(OR(wld_az1_rack5_principal_storage_network="Value Missing",wld_az1_rack5_principal_storage_mask="Value Missing"),"Value Missing",(CONCATENATE(wld_az1_rack5_principal_storage_network,"/",VLOOKUP(wld_az1_rack5_principal_storage_mask,table_mask_to_cidr,2,FALSE)))) -> #REF! | W26: =CONCATENATE("Principal Storage Network ",wld_principal_storage_chosen) -> #REF! | X26: =IF(OR(wld_az1_rack6_principal_storage_network="Value Missing",wld_az1_rack6_principal_storage_mask="Value Missing"),"Value Missing",(CONCATENATE(wld_az1_rack6_principal_storage_network,"/",VLOOKUP(wld_az1_rack6_principal_storage_mask,table_mask_to_cidr,2,FALSE)))) -> #REF! | Z26: =CONCATENATE("Principal Storage Network ",wld_principal_storage_chosen) -> #REF! | AA26: =IF(OR(wld_az1_rack7_principal_storage_network="Value Missing",wld_az1_rack7_principal_storage_mask="Value Missing"),"Value Missing",(CONCATENATE(wld_az1_rack7_principal_storage_network,"/",VLOOKUP(wld_az1_rack7_principal_storage_mask,table_mask_to_cidr,2,FALSE)))) -> #REF! | AC26: =CONCATENATE("Principal Storage Network ",wld_principal_storage_chosen) -> #REF! | AD26: =IF(OR(wld_az1_rack8_principal_storage_network="Value Missing",wld_az1_rack8_principal_storage_mask="Value Missing"),"Value Missing",(CONCATENATE(wld_az1_rack8_principal_storage_network,"/",VLOOKUP(wld_az1_rack8_principal_storage_mask,table_mask_to_cidr,2,FALSE)))) -> #REF!
B27: Password Creation Auto-generate passwords | C27: =IF(mgmt_domain_password_creation_chosen="Included","Selected","Unselected") -> #REF! | E27: NSX Host Overlay | F27: =IF(mgmt_az1_host_overlay_network="Value missing","Value Missing",CONCATENATE(mgmt_az1_host_overlay_network,"/",VLOOKUP(mgmt_az1_host_overlay_mask,table_mask_to_cidr,2,FALSE))) -> #REF! | H27: NSX Host Overlay | I27: =IF(ISBLANK(input_wld_az1_host_overlay_cidr),"Value Missing",input_wld_az1_host_overlay_cidr) -> #REF! | K27: NSX Host Overlay | L27: =IF(OR(wld_az1_rack2_host_overlay_network="Value Missing",wld_az1_rack2_host_overlay_mask="Value Missing"),"Value Missing",(CONCATENATE(wld_az1_rack2_host_overlay_network,"/",VLOOKUP(wld_az1_rack2_host_overlay_mask,table_mask_to_cidr,2,FALSE)))) -> #REF! | N27: NSX Host Overlay | O27: =IF(OR(wld_az1_rack3_host_overlay_network="Value Missing",wld_az1_rack3_host_overlay_mask="Value Missing"),"Value Missing",(CONCATENATE(wld_az1_rack3_host_overlay_network,"/",VLOOKUP(wld_az1_rack3_host_overlay_mask,table_mask_to_cidr,2,FALSE)))) -> #REF! | Q27: NSX Host Overlay | R27: =IF(OR(wld_az1_rack4_host_overlay_network="Value Missing",wld_az1_rack4_host_overlay_mask="Value Missing"),"Value Missing",(CONCATENATE(wld_az1_rack4_host_overlay_network,"/",VLOOKUP(wld_az1_rack4_host_overlay_mask,table_mask_to_cidr,2,FALSE)))) -> #REF! | T27: NSX Host Overlay | U27: =IF(OR(wld_az1_rack5_host_overlay_network="Value Missing",wld_az1_rack5_host_overlay_mask="Value Missing"),"Value Missing",(CONCATENATE(wld_az1_rack5_host_overlay_network,"/",VLOOKUP(wld_az1_rack5_host_overlay_mask,table_mask_to_cidr,2,FALSE)))) -> #REF! | W27: NSX Host Overlay | X27: =IF(OR(wld_az1_rack6_host_overlay_network="Value Missing",wld_az1_rack6_host_overlay_mask="Value Missing"),"Value Missing",(CONCATENATE(wld_az1_rack6_host_overlay_network,"/",VLOOKUP(wld_az1_rack6_host_overlay_mask,table_mask_to_cidr,2,FALSE)))) -> #REF! | Z27: NSX Host Overlay | AA27: =IF(OR(wld_az1_rack7_host_overlay_network="Value Missing",wld_az1_rack7_host_overlay_mask="Value Missing"),"Value Missing",(CONCATENATE(wld_az1_rack7_host_overlay_network,"/",VLOOKUP(wld_az1_rack7_host_overlay_mask,table_mask_to_cidr,2,FALSE)))) -> #REF! | AC27: NSX Host Overlay | AD27: =IF(OR(wld_az1_rack8_host_overlay_network="Value Missing",wld_az1_rack8_host_overlay_mask="Value Missing"),"Value Missing",(CONCATENATE(wld_az1_rack8_host_overlay_network,"/",VLOOKUP(wld_az1_rack8_host_overlay_mask,table_mask_to_cidr,2,FALSE)))) -> #REF!
B28: FLT-MGR use Use same password as VCF Operations | C28: =mgmt_flt_fm_reuse_password_chosen -> Unselected | E28: Secondary Storage Network (NFS) | F28: =IF(mgmt_az1_secondary_storage_network="Value missing","Value Missing",CONCATENATE(mgmt_az1_secondary_storage_network,"/",VLOOKUP(mgmt_az1_secondary_storage_mask,table_mask_to_cidr,2,FALSE))) -> #REF! | H28: Secondary Storage Network (NFS) | I28: =IF(wld_az1_secondary_storage_network="Value missing","Value Missing",CONCATENATE(wld_az1_secondary_storage_network,"/",VLOOKUP(wld_az1_secondary_storage_mask,table_mask_to_cidr,2,FALSE))) -> #REF! | K28: Secondary Storage Network (NFS) | L28: =IF(OR(wld_az1_rack2_secondary_storage_network="Value Missing",wld_az1_rack2_secondary_storage_mask="Value Missing"),"Value Missing",(CONCATENATE(wld_az1_rack2_secondary_storage_network,"/",VLOOKUP(wld_az1_rack2_secondary_storage_mask,table_mask_to_cidr,2,FALSE)))) -> Value Missing | N28: Secondary Storage Network (NFS) | O28: =IF(OR(wld_az1_rack3_secondary_storage_network="Value Missing",wld_az1_rack3_secondary_storage_mask="Value Missing"),"Value Missing",(CONCATENATE(wld_az1_rack3_secondary_storage_network,"/",VLOOKUP(wld_az1_rack3_secondary_storage_mask,table_mask_to_cidr,2,FALSE)))) -> Value Missing | Q28: Secondary Storage Network (NFS) | R28: =IF(OR(wld_az1_rack4_secondary_storage_network="Value Missing",wld_az1_rack4_secondary_storage_mask="Value Missing"),"Value Missing",(CONCATENATE(wld_az1_rack4_secondary_storage_network,"/",VLOOKUP(wld_az1_rack4_secondary_storage_mask,table_mask_to_cidr,2,FALSE)))) -> Value Missing | T28: Secondary Storage Network (NFS) | U28: =IF(OR(wld_az1_rack5_secondary_storage_network="Value Missing",wld_az1_rack5_secondary_storage_mask="Value Missing"),"Value Missing",(CONCATENATE(wld_az1_rack5_secondary_storage_network,"/",VLOOKUP(wld_az1_rack5_secondary_storage_mask,table_mask_to_cidr,2,FALSE)))) -> Value Missing | W28: Secondary Storage Network (NFS) | X28: =IF(OR(wld_az1_rack6_secondary_storage_network="Value Missing",wld_az1_rack6_secondary_storage_mask="Value Missing"),"Value Missing",(CONCATENATE(wld_az1_rack6_secondary_storage_network,"/",VLOOKUP(wld_az1_rack6_secondary_storage_mask,table_mask_to_cidr,2,FALSE)))) -> Value Missing | Z28: Secondary Storage Network (NFS) | AA28: =IF(OR(wld_az1_rack7_secondary_storage_network="Value Missing",wld_az1_rack7_secondary_storage_mask="Value Missing"),"Value Missing",(CONCATENATE(wld_az1_rack7_secondary_storage_network,"/",VLOOKUP(wld_az1_rack7_secondary_storage_mask,table_mask_to_cidr,2,FALSE)))) -> Value Missing | AC28: Secondary Storage Network (NFS) | AD28: =IF(OR(wld_az1_rack7_secondary_storage_network="Value Missing",wld_az1_rack8_secondary_storage_mask="Value Missing"),"Value Missing",(CONCATENATE(wld_az1_rack8_secondary_storage_network,"/",VLOOKUP(wld_az1_rack8_secondary_storage_mask,table_mask_to_cidr,2,FALSE)))) -> Value Missing
E29: VCF Management Network | F29: =IF(mgmt_az1_vcf_mgmt_network="Value missing","Value Missing",CONCATENATE(mgmt_az1_vcf_mgmt_network,"/",VLOOKUP(mgmt_az1_vcf_mgmt_mask,table_mask_to_cidr,2,FALSE))) -> #REF! | H29: vSAN Network - vSAN Storage Cluster | I29: =IF(wld_az1_storage_cluster_network="Value missing","Value Missing",CONCATENATE(wld_az1_storage_cluster_network,"/",VLOOKUP(wld_az1_storage_cluster_mask,table_mask_to_cidr,2,FALSE))) -> #REF! | K29: vSAN Network - vSAN Storage Cluster | N29: vSAN Network - vSAN Storage Cluster | Q29: vSAN Network - vSAN Storage Cluster | T29: vSAN Network - vSAN Storage Cluster | W29: vSAN Network - vSAN Storage Cluster | Z29: vSAN Network - vSAN Storage Cluster | AC29: vSAN Network - vSAN Storage Cluster
B30: Deployment Parameters | E30: NSX Edge Uplink 1 | F30: =IF(ISBLANK(input_mgmt_az1_uplink01_cidr),"Value Missing",input_mgmt_az1_uplink01_cidr) -> #REF! | H30: NSX Edge Uplink 1 | I30: =IF(ISBLANK(input_wld_az1_uplink01_cidr),"Value Missing",input_wld_az1_uplink01_cidr) -> #REF! | K30: NSX Edge Uplink 1 | L30: =IF(OR(wld_az1_rack2_uplink01_network="Value Missing",wld_az1_rack2_uplink01_mask="Value Missing"),"Value Missing",(CONCATENATE(wld_az1_rack2_uplink01_network,"/",VLOOKUP(wld_az1_rack2_uplink01_mask,table_mask_to_cidr,2,FALSE)))) -> Value Missing | N30: NSX Edge Uplink 1 | O30: =IF(OR(wld_az1_rack3_uplink01_network="Value Missing",wld_az1_rack3_uplink01_mask="Value Missing"),"Value Missing",(CONCATENATE(wld_az1_rack3_uplink01_network,"/",VLOOKUP(wld_az1_rack3_uplink01_mask,table_mask_to_cidr,2,FALSE)))) -> Value Missing | Q30: NSX Edge Uplink 1 | R30: =IF(OR(wld_az1_rack4_uplink01_network="Value Missing",wld_az1_rack4_uplink01_mask="Value Missing"),"Value Missing",(CONCATENATE(wld_az1_rack4_uplink01_network,"/",VLOOKUP(wld_az1_rack4_uplink01_mask,table_mask_to_cidr,2,FALSE)))) -> Value Missing | T30: NSX Edge Uplink 1 | U30: =IF(OR(wld_az1_rack5_uplink01_network="Value Missing",wld_az1_rack5_uplink01_mask="Value Missing"),"Value Missing",(CONCATENATE(wld_az1_rack5_uplink01_network,"/",VLOOKUP(wld_az1_rack5_uplink01_mask,table_mask_to_cidr,2,FALSE)))) -> Value Missing | W30: NSX Edge Uplink 1 | X30: =IF(OR(wld_az1_rack6_uplink01_network="Value Missing",wld_az1_rack6_uplink01_mask="Value Missing"),"Value Missing",(CONCATENATE(wld_az1_rack6_uplink01_network,"/",VLOOKUP(wld_az1_rack6_uplink01_mask,table_mask_to_cidr,2,FALSE)))) -> Value Missing | Z30: NSX Edge Uplink 1 | AA30: =IF(OR(wld_az1_rack7_uplink01_network="Value Missing",wld_az1_rack7_uplink01_mask="Value Missing"),"Value Missing",(CONCATENATE(wld_az1_rack7_uplink01_network,"/",VLOOKUP(wld_az1_rack7_uplink01_mask,table_mask_to_cidr,2,FALSE)))) -> Value Missing | AC30: NSX Edge Uplink 1 | AD30: =IF(OR(wld_az1_rack8_uplink01_network="Value Missing",wld_az1_rack8_uplink01_mask="Value Missing"),"Value Missing",(CONCATENATE(wld_az1_rack8_uplink01_network,"/",VLOOKUP(wld_az1_rack8_uplink01_mask,table_mask_to_cidr,2,FALSE)))) -> Value Missing
B31: Name | C31: Value | E31: NSX Edge Uplink 2 | F31: =IF(ISBLANK(input_mgmt_az1_uplink02_cidr),"Value Missing",input_mgmt_az1_uplink02_cidr) -> #REF! | H31: NSX Edge Uplink 2 | I31: =IF(ISBLANK(input_wld_az1_uplink02_cidr),"Value Missing",input_wld_az1_uplink02_cidr) -> #REF! | K31: NSX Edge Uplink 2 | L31: =IF(OR(wld_az1_rack2_uplink02_network="Value Missing",wld_az1_rack2_uplink02_mask="Value Missing"),"Value Missing",(CONCATENATE(wld_az1_rack2_uplink02_network,"/",VLOOKUP(wld_az1_rack2_uplink02_mask,table_mask_to_cidr,2,FALSE)))) -> Value Missing | N31: NSX Edge Uplink 2 | O31: =IF(OR(wld_az1_rack3_uplink02_network="Value Missing",wld_az1_rack3_uplink02_mask="Value Missing"),"Value Missing",(CONCATENATE(wld_az1_rack3_uplink02_network,"/",VLOOKUP(wld_az1_rack3_uplink02_mask,table_mask_to_cidr,2,FALSE)))) -> Value Missing | Q31: NSX Edge Uplink 2 | R31: =IF(OR(wld_az1_rack4_uplink02_network="Value Missing",wld_az1_rack4_uplink02_mask="Value Missing"),"Value Missing",(CONCATENATE(wld_az1_rack4_uplink02_network,"/",VLOOKUP(wld_az1_rack4_uplink02_mask,table_mask_to_cidr,2,FALSE)))) -> Value Missing | T31: NSX Edge Uplink 2 | U31: =IF(OR(wld_az1_rack5_uplink02_network="Value Missing",wld_az1_rack5_uplink02_mask="Value Missing"),"Value Missing",(CONCATENATE(wld_az1_rack5_uplink02_network,"/",VLOOKUP(wld_az1_rack5_uplink02_mask,table_mask_to_cidr,2,FALSE)))) -> Value Missing | W31: NSX Edge Uplink 2 | X31: =IF(OR(wld_az1_rack6_uplink02_network="Value Missing",wld_az1_rack6_uplink02_mask="Value Missing"),"Value Missing",(CONCATENATE(wld_az1_rack6_uplink02_network,"/",VLOOKUP(wld_az1_rack6_uplink02_mask,table_mask_to_cidr,2,FALSE)))) -> Value Missing | Z31: NSX Edge Uplink 2 | AA31: =IF(OR(wld_az1_rack7_uplink02_network="Value Missing",wld_az1_rack7_uplink02_mask="Value Missing"),"Value Missing",(CONCATENATE(wld_az1_rack7_uplink02_network,"/",VLOOKUP(wld_az1_rack7_uplink02_mask,table_mask_to_cidr,2,FALSE)))) -> Value Missing | AC31: NSX Edge Uplink 2 | AD31: =IF(OR(wld_az1_rack8_uplink02_network="Value Missing",wld_az1_rack8_uplink02_mask="Value Missing"),"Value Missing",(CONCATENATE(wld_az1_rack8_uplink02_network,"/",VLOOKUP(wld_az1_rack8_uplink02_mask,table_mask_to_cidr,2,FALSE)))) -> Value Missing
B32: DNS | E32: NSX Edge Overlay | F32: =IF(ISBLANK(input_mgmt_az1_edge_overlay_cidr),"Value Missing",input_mgmt_az1_edge_overlay_cidr) -> #REF! | H32: NSX Edge Overlay | I32: =IF(ISBLANK(input_wld_az1_edge_overlay_cidr),"Value Missing",input_wld_az1_edge_overlay_cidr) -> #REF! | K32: NSX Edge Overlay | L32: =IF(OR(wld_az1_rack2_edge_overlay_network="Value Missing",wld_az1_rack2_edge_overlay_mask="Value Missing"),"Value Missing",(CONCATENATE(wld_az1_rack2_edge_overlay_network,"/",VLOOKUP(wld_az1_rack2_edge_overlay_mask,table_mask_to_cidr,2,FALSE)))) -> Value Missing | N32: NSX Edge Overlay | O32: =IF(OR(wld_az1_rack3_edge_overlay_network="Value Missing",wld_az1_rack3_edge_overlay_mask="Value Missing"),"Value Missing",(CONCATENATE(wld_az1_rack3_edge_overlay_network,"/",VLOOKUP(wld_az1_rack3_edge_overlay_mask,table_mask_to_cidr,2,FALSE)))) -> Value Missing | Q32: NSX Edge Overlay | R32: =IF(OR(wld_az1_rack4_edge_overlay_network="Value Missing",wld_az1_rack4_edge_overlay_mask="Value Missing"),"Value Missing",(CONCATENATE(wld_az1_rack4_edge_overlay_network,"/",VLOOKUP(wld_az1_rack4_edge_overlay_mask,table_mask_to_cidr,2,FALSE)))) -> Value Missing | T32: NSX Edge Overlay | U32: =IF(OR(wld_az1_rack5_edge_overlay_network="Value Missing",wld_az1_rack5_edge_overlay_mask="Value Missing"),"Value Missing",(CONCATENATE(wld_az1_rack5_edge_overlay_network,"/",VLOOKUP(wld_az1_rack5_edge_overlay_mask,table_mask_to_cidr,2,FALSE)))) -> Value Missing | W32: NSX Edge Overlay | X32: =IF(OR(wld_az1_rack6_edge_overlay_network="Value Missing",wld_az1_rack6_edge_overlay_mask="Value Missing"),"Value Missing",(CONCATENATE(wld_az1_rack6_edge_overlay_network,"/",VLOOKUP(wld_az1_rack6_edge_overlay_mask,table_mask_to_cidr,2,FALSE)))) -> Value Missing | Z32: NSX Edge Overlay | AA32: =IF(OR(wld_az1_rack7_edge_overlay_network="Value Missing",wld_az1_rack7_edge_overlay_mask="Value Missing"),"Value Missing",(CONCATENATE(wld_az1_rack7_edge_overlay_network,"/",VLOOKUP(wld_az1_rack7_edge_overlay_mask,table_mask_to_cidr,2,FALSE)))) -> Value Missing | AC32: NSX Edge Overlay | AD32: =IF(OR(wld_az1_rack8_edge_overlay_network="Value Missing",wld_az1_rack8_edge_overlay_mask="Value Missing"),"Value Missing",(CONCATENATE(wld_az1_rack8_edge_overlay_network,"/",VLOOKUP(wld_az1_rack8_edge_overlay_mask,table_mask_to_cidr,2,FALSE)))) -> Value Missing
B33: Zone name | C33: =parent_dns_zone -> #REF! | E33: NSX RTEP Overlay | F33: =IF(ISBLANK(input_mgmt_az1_rtep_overlay_cidr),"Value Missing",input_mgmt_az1_rtep_overlay_cidr) -> #REF! | H33: NSX RTEP Overlay | I33: =IF(ISBLANK(input_wld_az1_rtep_overlay_cidr),"Value Missing",input_wld_az1_rtep_overlay_cidr) -> #REF! | K33: NSX RTEP Overlay | N33: NSX RTEP Overlay | Q33: NSX RTEP Overlay | T33: NSX RTEP Overlay | W33: NSX RTEP Overlay | Z33: NSX RTEP Overlay | AC33: NSX RTEP Overlay
B34: Server #1 | C34: =region_dns1_ip -> #REF! | E34: vSphere Replication | H34: vSphere Replication | I34: =IF(ISBLANK(input_wld_az1_vrms_cidr),"Value Missing",input_wld_az1_vrms_cidr) -> Value Missing | K34: vSphere Replication | N34: vSphere Replication | Q34: vSphere Replication | T34: vSphere Replication | W34: vSphere Replication | Z34: vSphere Replication | AC34: vSphere Replication
B35: Server #2 | C35: =region_dns2_ip -> #REF!
B36: NTP | E36: MGMT Rack 1 Network (Primary AZ) | H36: Rack 1 Network (Primary AZ) | K36: Rack 2 Network (Primary AZ) | N36: Rack 3 Network (Primary AZ) | Q36: Rack 4 Network (Primary AZ) | T36: Rack 5 Network (Primary AZ) | W36: Rack 6 Network (Primary AZ) | Z36: Rack 7 Network (Primary AZ) | AC36: Rack 8 Network (Primary AZ)
B37: Server #1 | C37: =region_ntp1_server -> #REF! | E37: Name | F37: AZ1 Actual Value | H37: Name | I37: AZ1 Actual Value | K37: Name | L37: AZ1 Actual Value | N37: Name | O37: AZ1 Actual Value | Q37: Name | R37: AZ1 Actual Value | T37: Name | U37: AZ1 Actual Value | W37: Name | X37: AZ1 Actual Value | Z37: Name | AA37: AZ1 Actual Value | AC37: Name | AD37: AZ1 Actual Value
B38: Server #2 | C38: =region_ntp2_server -> #REF! | E38: Management VM Network | F38: =IF(mgmt_az1_mgmt_vm_gateway_cidr="Value Missing","Value Missing",CONCATENATE(_xludf.TEXTBEFORE(mgmt_az1_mgmt_vm_gateway_cidr,".",3),".0")) -> #REF! | H38: Management VM Network | I38: =IF(wld_az1_mgmt_vm_gateway_cidr="Value Missing","Value Missing",CONCATENATE(_xludf.TEXTBEFORE(wld_az1_mgmt_vm_gateway_cidr,".",3),".0")) -> #REF! | K38: Management VM Network | N38: Management VM Network | Q38: Management VM Network | T38: Management VM Network | W38: Management VM Network | Z38: Management VM Network | AC38: Management VM Network
B39: Server #3 | E39: ESXi Management Network | F39: =IF(mgmt_az1_mgmt_gateway_cidr="Value Missing","Value Missing",CONCATENATE(_xludf.TEXTBEFORE(mgmt_az1_mgmt_gateway_cidr,".",3),".0")) -> #REF! | H39: ESXi Management Network | I39: =IF(wld_az1_mgmt_gateway_cidr="Value Missing","Value Missing",CONCATENATE(_xludf.TEXTBEFORE(wld_az1_mgmt_gateway_cidr,".",3),".0")) -> #REF! | K39: ESXi Management Network | L39: =IF(wld_az1_rack2_mgmt_cidr="Value Missing","Value Missing",IF(ISBLANK(wld_az1_rack2_mgmt_cidr),"Value Missing",LEFT(wld_az1_rack2_mgmt_cidr,(FIND("/",wld_az1_rack2_mgmt_cidr)-1)))) -> #REF! | N39: ESXi Management Network | O39: =IF(wld_az1_rack3_mgmt_cidr="Value Missing","Value Missing",IF(ISBLANK(wld_az1_rack3_mgmt_cidr),"Value Missing",LEFT(wld_az1_rack3_mgmt_cidr,(FIND("/",wld_az1_rack3_mgmt_cidr)-1)))) -> #REF! | Q39: ESXi Management Network | R39: =IF(wld_az1_rack4_mgmt_cidr="Value Missing","Value Missing",IF(ISBLANK(wld_az1_rack4_mgmt_cidr),"Value Missing",LEFT(wld_az1_rack4_mgmt_cidr,(FIND("/",wld_az1_rack4_mgmt_cidr)-1)))) -> #REF! | T39: ESXi Management Network | U39: =IF(wld_az1_rack5_mgmt_cidr="Value Missing","Value Missing",IF(ISBLANK(wld_az1_rack5_mgmt_cidr),"Value Missing",LEFT(wld_az1_rack5_mgmt_cidr,(FIND("/",wld_az1_rack5_mgmt_cidr)-1)))) -> #REF! | W39: ESXi Management Network | X39: =IF(wld_az1_rack6_mgmt_cidr="Value Missing","Value Missing",IF(ISBLANK(wld_az1_rack6_mgmt_cidr),"Value Missing",LEFT(wld_az1_rack6_mgmt_cidr,(FIND("/",wld_az1_rack6_mgmt_cidr)-1)))) -> #REF! | Z39: ESXi Management Network | AA39: =IF(wld_az1_rack7_mgmt_cidr="Value Missing","Value Missing",IF(ISBLANK(wld_az1_rack7_mgmt_cidr),"Value Missing",LEFT(wld_az1_rack7_mgmt_cidr,(FIND("/",wld_az1_rack7_mgmt_cidr)-1)))) -> #REF! | AC39: ESXi Management Network | AD39: =IF(wld_az1_rack8_mgmt_cidr="Value Missing","Value Missing",IF(ISBLANK(wld_az1_rack8_mgmt_cidr),"Value Missing",LEFT(wld_az1_rack8_mgmt_cidr,(FIND("/",wld_az1_rack8_mgmt_cidr)-1)))) -> #REF!
B40: Enable Customer Experience Improvement Program (CEIP) | C40: =IF(ISBLANK(mgmt_ceip_status_chosen),"Value Missing",mgmt_ceip_status_chosen) -> #REF! | E40: vMotion Network | F40: =IF(mgmt_az1_vmotion_gateway_cidr="Value Missing","Value Missing",CONCATENATE(_xludf.TEXTBEFORE(mgmt_az1_vmotion_gateway_cidr,".",3),".0")) -> #REF! | H40: vMotion Network | I40: =IF(wld_az1_vmotion_gateway_cidr="Value Missing","Value Missing",CONCATENATE(_xludf.TEXTBEFORE(wld_az1_vmotion_gateway_cidr,".",3),".0")) -> #REF! | K40: vMotion Network | L40: =IF(ISBLANK(input_wld_az1_rack2_vmotion_network),"Value Missing",input_wld_az1_rack2_vmotion_network) -> #REF! | N40: vMotion Network | O40: =IF(ISBLANK(input_wld_az1_rack3_vmotion_network),"Value Missing",input_wld_az1_rack3_vmotion_network) -> #REF! | Q40: vMotion Network | R40: =IF(ISBLANK(input_wld_az1_rack4_vmotion_network),"Value Missing",input_wld_az1_rack4_vmotion_network) -> #REF! | T40: vMotion Network | U40: =IF(ISBLANK(input_wld_az1_rack5_vmotion_network),"Value Missing",input_wld_az1_rack5_vmotion_network) -> #REF! | W40: vMotion Network | X40: =IF(ISBLANK(input_wld_az1_rack6_vmotion_network),"Value Missing",input_wld_az1_rack6_vmotion_network) -> #REF! | Z40: vMotion Network | AA40: =IF(ISBLANK(input_wld_az1_rack7_vmotion_network),"Value Missing",input_wld_az1_rack7_vmotion_network) -> #REF! | AC40: vMotion Network | AD40: =IF(ISBLANK(input_wld_az1_rack8_vmotion_network),"Value Missing",input_wld_az1_rack8_vmotion_network) -> #REF!
E41: =CONCATENATE("Principal Storage Network ",wld_principal_storage_chosen) -> #REF! | F41: =IF(mgmt_az1_vsan_gateway_cidr="Value Missing","Value Missing",CONCATENATE(_xludf.TEXTBEFORE(mgmt_az1_vsan_gateway_cidr,".",3),".0")) -> #REF! | H41: vSAN Network | I41: =IF(wld_az1_principal_storage_gateway_cidr="Value Missing","Value Missing",CONCATENATE(_xludf.TEXTBEFORE(wld_az1_principal_storage_gateway_cidr,".",3),".0")) -> #REF! | K41: =CONCATENATE("Principal Storage Network ",wld_principal_storage_chosen) -> #REF! | L41: =IF(ISBLANK(input_wld_az1_rack2_principal_storage_network),"Value Missing",input_wld_az1_rack2_principal_storage_network) -> #REF! | N41: =CONCATENATE("Principal Storage Network ",wld_principal_storage_chosen) -> #REF! | O41: =IF(ISBLANK(input_wld_az1_rack3_principal_storage_network),"Value Missing",input_wld_az1_rack3_principal_storage_network) -> #REF! | Q41: =CONCATENATE("Principal Storage Network ",wld_principal_storage_chosen) -> #REF! | R41: =IF(ISBLANK(input_wld_az1_rack4_principal_storage_network),"Value Missing",input_wld_az1_rack4_principal_storage_network) -> #REF! | T41: =CONCATENATE("Principal Storage Network ",wld_principal_storage_chosen) -> #REF! | U41: =IF(ISBLANK(input_wld_az1_rack5_principal_storage_network),"Value Missing",input_wld_az1_rack5_principal_storage_network) -> #REF! | W41: =CONCATENATE("Principal Storage Network ",wld_principal_storage_chosen) -> #REF! | X41: =IF(ISBLANK(input_wld_az1_rack6_principal_storage_network),"Value Missing",input_wld_az1_rack6_principal_storage_network) -> #REF! | Z41: =CONCATENATE("Principal Storage Network ",wld_principal_storage_chosen) -> #REF! | AA41: =IF(ISBLANK(input_wld_az1_rack7_principal_storage_network),"Value Missing",input_wld_az1_rack7_principal_storage_network) -> #REF! | AC41: =CONCATENATE("Principal Storage Network ",wld_principal_storage_chosen) -> #REF! | AD41: =IF(ISBLANK(input_wld_az1_rack8_principal_storage_network),"Value Missing",input_wld_az1_rack8_principal_storage_network) -> #REF!
B42: vCenter | E42: NSX Host Overlay | F42: =IF(mgmt_az1_host_overlay_gateway_cidr="Value Missing","Value Missing",CONCATENATE(_xludf.TEXTBEFORE(mgmt_az1_host_overlay_gateway_cidr,".",3),".0")) -> #REF! | H42: NSX Host Overlay | I42: =IF(wld_az1_host_overlay_cidr="Value Missing","Value Missing",IF(ISBLANK(wld_az1_host_overlay_cidr),"Value Missing",LEFT(wld_az1_host_overlay_cidr,(FIND("/",wld_az1_host_overlay_cidr)-1)))) -> #REF! | K42: NSX Host Overlay | L42: =IF(ISBLANK(input_wld_az1_rack2_host_overlay_network),"Value Missing",input_wld_az1_rack2_host_overlay_network) -> #REF! | N42: NSX Host Overlay | O42: =IF(ISBLANK(input_wld_az1_rack2_host_overlay_network),"Value Missing",input_wld_az1_rack3_host_overlay_network) -> #REF! | Q42: NSX Host Overlay | R42: =IF(ISBLANK(input_wld_az1_rack4_host_overlay_network),"Value Missing",input_wld_az1_rack4_host_overlay_network) -> #REF! | T42: NSX Host Overlay | U42: =IF(ISBLANK(input_wld_az1_rack5_host_overlay_network),"Value Missing",input_wld_az1_rack5_host_overlay_network) -> #REF! | W42: NSX Host Overlay | X42: =IF(ISBLANK(input_wld_az1_rack6_host_overlay_network),"Value Missing",input_wld_az1_rack6_host_overlay_network) -> #REF! | Z42: NSX Host Overlay | AA42: =IF(ISBLANK(input_wld_az1_rack7_host_overlay_network),"Value Missing",input_wld_az1_rack7_host_overlay_network) -> #REF! | AC42: NSX Host Overlay | AD42: =IF(ISBLANK(input_wld_az1_rack8_host_overlay_network),"Value Missing",input_wld_az1_rack8_host_overlay_network) -> #REF!
B43: Name | C43: Value | E43: Secondary Storage Network (NFS) | F43: =IF(mgmt_az1_secondary_storage_gateway_cidr="Value Missing","Value Missing",CONCATENATE(_xludf.TEXTBEFORE(mgmt_az1_secondary_storage_gateway_cidr,".",3),".0")) -> #REF! | H43: Secondary Storage Network (NFS) | I43: =IF(wld_az1_secondary_storage_gateway_cidr="Value Missing","Value Missing",CONCATENATE(_xludf.TEXTBEFORE(wld_az1_secondary_storage_gateway_cidr,".",3),".0")) -> #REF! | K43: vSAN Network - vSAN Storage Cluster | N43: vSAN Network - vSAN Storage Cluster | Q43: vSAN Network - vSAN Storage Cluster | T43: vSAN Network - vSAN Storage Cluster | W43: vSAN Network - vSAN Storage Cluster | Z43: vSAN Network - vSAN Storage Cluster | AC43: vSAN Network - vSAN Storage Cluster
B44: FQDN | C44: =IF(ISBLANK(mgmt_vc_fqdn),"Value Missing",mgmt_vc_fqdn) -> #REF! | E44: VCF Management Network | F44: =IF(mgmt_az1_vcf_mgmt_gateway_cidr="Value Missing","Value Missing",CONCATENATE(_xludf.TEXTBEFORE(mgmt_az1_vcf_mgmt_gateway_cidr,".",3),".0")) -> #REF! | H44: vSAN Network - vSAN Storage Cluster | I44: =IF(wld_az1_storage_cluster_gateway_cidr="Value Missing","Value Missing",CONCATENATE(_xludf.TEXTBEFORE(wld_az1_storage_cluster_gateway_cidr,".",3),".0")) -> #REF! | K44: Secondary Storage Network (NFS) | L44: =IF(ISBLANK(input_wld_az1_rack2_secondary_storage_network),"Value Missing",input_wld_az1_rack2_secondary_storage_network) -> Value Missing | N44: Secondary Storage Network (NFS) | O44: =IF(ISBLANK(input_wld_az1_rack3_secondary_storage_network),"Value Missing",input_wld_az1_rack3_secondary_storage_network) -> Value Missing | Q44: Secondary Storage Network (NFS) | R44: =IF(ISBLANK(input_wld_az1_rack4_secondary_storage_network),"Value Missing",input_wld_az1_rack4_secondary_storage_network) -> Value Missing | T44: Secondary Storage Network (NFS) | U44: =IF(ISBLANK(input_wld_az1_rack5_secondary_storage_network),"Value Missing",input_wld_az1_rack5_secondary_storage_network) -> Value Missing | W44: Secondary Storage Network (NFS) | X44: =IF(ISBLANK(input_wld_az1_rack6_secondary_storage_network),"Value Missing",input_wld_az1_rack6_secondary_storage_network) -> Value Missing | Z44: Secondary Storage Network (NFS) | AA44: =IF(ISBLANK(input_wld_az1_rack7_secondary_storage_network),"Value Missing",input_wld_az1_rack7_secondary_storage_network) -> Value Missing | AC44: Secondary Storage Network (NFS) | AD44: =IF(ISBLANK(input_wld_az1_rack8_secondary_storage_network),"Value Missing",input_wld_az1_rack8_secondary_storage_network) -> Value Missing
B45: Appliance Size | C45: =mgmt_vcenter_appliance_size_chosen -> #REF! | E45: NSX Edge Uplink 1 | F45: =IF(mgmt_az1_uplink01_cidr="Value Missing",mgmt_az1_uplink01_cidr,LEFT(mgmt_az1_uplink01_cidr,(FIND("/",mgmt_az1_uplink01_cidr)-1))) -> #REF! | H45: NSX Edge Uplink 1 | I45: =IF(wld_az1_uplink01_cidr="Value Missing",wld_az1_uplink01_cidr,IF(ISBLANK(wld_az1_uplink01_cidr),"Value Missing",LEFT(wld_az1_uplink01_cidr,(FIND("/",wld_az1_uplink01_cidr)-1)))) -> #REF! | K45: NSX Edge Uplink 1 | L45: =IF(ISBLANK(input_wld_az1_rack2_uplink01_network),"Value Missing",input_wld_az1_rack2_uplink01_network) -> Value Missing | N45: NSX Edge Uplink 1 | O45: =IF(ISBLANK(input_wld_az1_rack3_uplink01_network),"Value Missing",input_wld_az1_rack3_uplink01_network) -> Value Missing | Q45: NSX Edge Uplink 1 | R45: =IF(ISBLANK(input_wld_az1_rack4_uplink01_network),"Value Missing",input_wld_az1_rack4_uplink01_network) -> Value Missing | T45: NSX Edge Uplink 1 | U45: =IF(ISBLANK(input_wld_az1_rack5_uplink01_network),"Value Missing",input_wld_az1_rack5_uplink01_network) -> Value Missing | W45: NSX Edge Uplink 1 | X45: =IF(ISBLANK(input_wld_az1_rack6_uplink01_network),"Value Missing",input_wld_az1_rack6_uplink01_network) -> Value Missing | Z45: NSX Edge Uplink 1 | AA45: =IF(ISBLANK(input_wld_az1_rack7_uplink01_network),"Value Missing",input_wld_az1_rack7_uplink01_network) -> Value Missing | AC45: NSX Edge Uplink 1 | AD45: =IF(ISBLANK(input_wld_az1_rack8_uplink01_network),"Value Missing",input_wld_az1_rack8_uplink01_network) -> Value Missing
